Workbook
Name AREA: #REF!
Name GST: #REF!
Name IDP: #REF!
Name IFT: #REF!
Name PLG: #REF!

Sheet Resumen  - Se oculta 2,0
B5: IFT | C5: =+IFT!O3 -> 0.25 | D5: =+IFT!C8 -> EMPLAZAMIENTO | F5: =+IFT!F8 -> 0.94 | H5: =+IFT!F3 -> 0.93175 | I5: =+'Dashboard Gral (2.0)'!C5 -> 0.25
D6: =+IFT!C19 -> EDIFICACION | F6: =+IFT!F19 -> 0.925 | J6: =+H5*I5+H10*I10+H16*I16+H21*I21 -> 0.95677083 | L6: COM. ALDO PATRICIO BALKENHOL FLORES EIRL
D7: =+IFT!C40 -> ALMACENAMIENTO Y MANIPULEO | F7: =+IFT!F40 -> 0.91 | J7: =+ROUND(J6*100,1)&"%"&" "&D39 -> 95,7% PROACTIVO
D8: =+IFT!C58 -> TRANSPORTE Y REPARTO | F8: =+IFT!F58 -> 1 | J8: Valor Año anterior | L8: =VLOOKUP(L6,[3]Gantt!$E$3:$AG$31,29,0) -> 0.9683
D9: =+IFT!C61 -> INFORMACIÓN Y COMUNICACIONES | F9: =+IFT!F61 -> 1 | L9: =IFERROR(IF(ROUND((J6-L8)*100,1)<0,"-"&ROUND((J6-L8)*100,1)&" pp vs AA","+"&ROUND((J6-L8)*100,1)&" pp vs AA"),"N/A") -> --1,2 pp vs AA
B10: PLG | C10: =+PLG!O3 -> 0.25 | D10: =+PLG!C8 -> ABASTECIMIENTO Y RECEPCIÓN | F10: =+PLG!F8 -> 1 | H10: =+PLG!F3 -> 0.96 | I10: =+'Dashboard Gral (2.0)'!C10 -> 0.25
D11: =+PLG!C18 -> ALMACENAMIENTO Y MANIPULEO | F11: =+PLG!F18 -> 0.75
D12: =+PLG!C28 -> REPOSICION INVENTARIOS | F12: =+PLG!F28 -> 1
D13: =+PLG!C36 -> CONSOLIDADOS Y PEDIDOS | F13: =+PLG!F36 -> 1
D14: =+PLG!C48 -> TRANSPORTE Y REPARTO | F14: =+PLG!F48 -> 0.85
D15: =+PLG!C56 -> RETORNO Y/O DEVOLUCIONES | F15: =+PLG!F56 -> 1
B16: GST | C16: =+GST!O3 -> 0.2 | D16: =+GST!C8 -> ORGANIZACIÓN | F16: =+GST!F8 -> 1 | H16: =+GST!F3 -> 0.958 | I16: =+'Dashboard Gral (2.0)'!C16 -> 0.2
D17: =+GST!C31 -> PLANIFICACION | F17: =+GST!F31 -> 1
D18: =+GST!C42 -> INFORMACION Y COMUNICACIONES | F18: =+GST!F42 -> 1
D19: =+GST!C48 -> FORMACION Y DESARROLLO | F19: =+GST!F48 -> 1
D20: =+GST!C52 -> MEDICION Y MEJORA | F20: =+GST!F52 -> 0.86
B21: IDP | C21: =+IDP!O3 -> 0.3 | D21: =+IDP!C8 -> ABASTECIMIENTO Y RECEPCIÓN | F21: =+IDP!F8 -> 1 | H21: =+IDP!F3 -> 0.97411111 | I21: =+'Dashboard Gral (2.0)'!C21 -> 0.3
D22: =+IDP!C14 -> ALMACENAMIENTO Y MANIPULEO | F22: =+IDP!F14 -> 0.94444444
D23: =+IDP!C33 -> TRANSPORTE Y REPARTO | F23: =+IDP!F33 -> 1
D24: =+IDP!C42 -> RETORNO Y/O DEVOLUCIONES | F24: =+IDP!F42 -> 1
D25: =+IDP!C49 -> LIMPIEZA | F25: =+IDP!F49 -> 1
D26: =+IDP!C58 -> MANEJO INTEGRADO DE PLAGAS | F26: =+IDP!F58 -> 0.88
B31: Categoria
B32: 85% > y 100% | D32: PROACTIVO | F32: =+D33 -> ACTIVO | G32: 0.85
B33: 70% > y < 85% | D33: ACTIVO | F33: =+D34 -> REACTIVO | G33: =+G32 -> 0.85 | H33: 0.7
B34: 50% > y < 70% | D34: REACTIVO | F34: =+D35 -> INACTIVO | G34: =+H33 -> 0.7 | H34: 0.5
B35: 25% > y < 50% | D35: INACTIVO | F35: =+D35 -> INACTIVO | G35: =+H34 -> 0.5 | H35: 0
B36: 0% > y < 25% | D36: N/A | G36: =+H35 -> 0 | H36: 0
A39: Adherencia | B39: =+J6 -> 0.95677083 | D39: =IF(B39>=G32,D32,IF(AND((B39<G33),(B39>=H33)),D33,IF(AND((B39<G34),(B39>=H34)),D34,D35))) -> PROACTIVO
R40: Estadio | S40: Indice | U40: Condicionales
A41: Condicionales | B41: =+'Condicionales 2.0'!G19 -> 12 | D41: =+ROUND(B39*100,1)&"%"&" "&D39 -> 95,7% PROACTIVO | R41: Proactivo | S41: Mayor / Igual | T41: 8.51 | U41: 12 | V41: =
A42: Categoria Final | B42: =VLOOKUP($D$39&$B$41,$K$48:$L$96,2,0) -> PROACTIVO
B43: =IF(D39=B42,"Mantiene Estadio","Cae de Estadio") -> Mantiene Estadio | D43: =+"Estadio final 2025: "&B42 -> Estadio final 2025: PROACTIVO | R43: Activo | S43: Mayor / Igual | T43: 8.51 | U43: 9 | V43: =+S43 -> Mayor / Igual
R44: Activo | S44: Mayor / Igual | T44: 7.01 | U44: 11 | V44: =+S44 -> Mayor / Igual
R46: Reactivo | S46: Mayor / Igual | T46: 8.51 | U46: 6 | V46: =+S46 -> Mayor / Igual
R47: Reactivo | S47: Mayor / Igual | T47: 7.01 | U47: 9 | V47: =+S47 -> Mayor / Igual
I48: Proactivo | J48: 12 | K48: =+I48&J48 -> Proactivo12 | L48: PROACTIVO
I49: Proactivo | J49: 11 | K49: =+I49&J49 -> Proactivo11 | L49: ACTIVO | R49: Inactivo | S49: Mayor / Igual | T49: 8.51 | U49: 6 | V49: Menor
I50: Proactivo | J50: 10 | K50: =+I50&J50 -> Proactivo10 | L50: ACTIVO | R50: Inactivo | S50: Mayor / Igual | T50: 7.01 | U50: 9 | V50: Menor
I51: Proactivo | J51: 9 | K51: =+I51&J51 -> Proactivo9 | L51: ACTIVO | R51: Inactivo | S51: Mayor / Igual | T51: 5.01 | U51: 12 | V51: Menor
I52: Proactivo | J52: 8 | K52: =+I52&J52 -> Proactivo8 | L52: ACTIVO
I53: Proactivo | J53: 7 | K53: =+I53&J53 -> Proactivo7 | L53: REACTIVO
I54: Proactivo | J54: 6 | K54: =+I54&J54 -> Proactivo6 | L54: REACTIVO
I55: Proactivo | J55: 5 | K55: =+I55&J55 -> Proactivo5 | L55: REACTIVO
I56: Proactivo | J56: 4 | K56: =+I56&J56 -> Proactivo4 | L56: REACTIVO
I57: Proactivo | J57: 3 | K57: =+I57&J57 -> Proactivo3 | L57: REACTIVO
I58: Proactivo | J58: 2 | K58: =+I58&J58 -> Proactivo2 | L58: REACTIVO
I59: Proactivo | J59: 1 | K59: =+I59&J59 -> Proactivo1 | L59: REACTIVO
I60: Activo | J60: 12 | K60: =+I60&J60 -> Activo12 | L60: ACTIVO
I61: Activo | J61: 11 | K61: =+I61&J61 -> Activo11 | L61: ACTIVO
I62: Activo | J62: 10 | K62: =+I62&J62 -> Activo10 | L62: ACTIVO
I63: Activo | J63: 9 | K63: =+I63&J63 -> Activo9 | L63: ACTIVO
... I96: Inactivo | J96: 0 | K96: =+I96&J96 -> Inactivo0 | L96: INACTIVO

Sheet Inicio

Sheet 2.0>>>

Sheet Dashboard Gral (2.0)
B5: IFT | C5: 0.25 | D5: =+IFT!C8 -> EMPLAZAMIENTO | G5: =+IFT!F8 -> 0.94 | I5: =+IFT!F3 -> 0.93175 | J5: =+I5*C5 -> 0.2329375
D6: =+IFT!C19 -> EDIFICACION | G6: =+IFT!F19 -> 0.925
D7: =+IFT!C40 -> ALMACENAMIENTO Y MANIPULEO | G7: =+IFT!F40 -> 0.91
D8: =+IFT!C58 -> TRANSPORTE Y REPARTO | G8: =+IFT!F58 -> 1
D9: =+IFT!C61 -> INFORMACIÓN Y COMUNICACIONES | G9: =+IFT!F61 -> 1
B10: PLG | C10: 0.25 | D10: =+PLG!C8 -> ABASTECIMIENTO Y RECEPCIÓN | G10: =+PLG!F8 -> 1 | I10: =+PLG!F3 -> 0.96 | J10: =+I10*C10 -> 0.24
D11: =+PLG!C18 -> ALMACENAMIENTO Y MANIPULEO | G11: =+PLG!F18 -> 0.75
D12: =+PLG!C28 -> REPOSICION INVENTARIOS | G12: =+PLG!F28 -> 1
D13: =+PLG!C36 -> CONSOLIDADOS Y PEDIDOS | G13: =+PLG!F36 -> 1
D14: =+PLG!C48 -> TRANSPORTE Y REPARTO | G14: =+PLG!F48 -> 0.85
D15: =+PLG!C56 -> RETORNO Y/O DEVOLUCIONES | G15: =+PLG!F56 -> 1
B16: GST | C16: 0.2 | D16: =+GST!C8 -> ORGANIZACIÓN | G16: =+GST!F8 -> 1 | I16: =+GST!F3 -> 0.958 | J16: =+I16*C16 -> 0.1916
D17: =+GST!C31 -> PLANIFICACION | G17: =+GST!F31 -> 1
D18: =+GST!C42 -> INFORMACION Y COMUNICACIONES | G18: =+GST!F42 -> 1
D19: =+GST!C48 -> FORMACION Y DESARROLLO | G19: =+GST!F48 -> 1
D20: =+GST!C52 -> MEDICION Y MEJORA | G20: =+GST!F52 -> 0.86
B21: IDP | C21: 0.3 | D21: =+IDP!C8 -> ABASTECIMIENTO Y RECEPCIÓN | G21: =+IDP!F8 -> 1 | I21: =+IDP!F3 -> 0.97411111 | J21: =+I21*C21 -> 0.29223333
D22: =+IDP!C14 -> ALMACENAMIENTO Y MANIPULEO | G22: =+IDP!F14 -> 0.94444444
D23: =+IDP!C33 -> TRANSPORTE Y REPARTO | G23: =+IDP!F33 -> 1
D24: =+IDP!C42 -> RETORNO Y/O DEVOLUCIONES | G24: =+IDP!F42 -> 1
D25: =+IDP!C49 -> LIMPIEZA | G25: =+IDP!F49 -> 1
D26: =+IDP!C58 -> MANEJO INTEGRADO DE PLAGAS | G26: =+IDP!F58 -> 0.88
D31: 85 % >= Proactivo <= 100 %
D32: 70 % >= Activo < 85 %
D33: 50 % >= Reactivo < 70 %
D34: 0 % >= Inactivo < 50 %

Sheet Condicionales 2.0
B2: # Critico | C2: # Critico | D2: Descripción | F2: # componentes Criticas | L2: Evaluación del cumplimiento
F3: Totales | G3: OK
B5: 1 | C5: CRITICO 1 | D5: =+IFT!C13 -> ENTORNO - ACCESO | F5: =COUNTIF(IFT!H:H,'Condicionales 2.0'!C5) -> 1 | G5: =SUMIF(IFT!H:H,'Condicionales 2.0'!C5,IFT!F:F) -> 1 | H5: =+G5/F5 -> 1 | I5: =+H5 -> 1 | L5: Categoria : Tolerancia sobre el total BPLs
B6: =+B5+1 -> 2 | C6: CRITICO 2 | D6: =+IFT!C22 -> LAY OUT - CAPACIDAD Y MODULACION | F6: =COUNTIF(IFT!H:H,'Condicionales 2.0'!C6) -> 1 | G6: =SUMIF(IFT!H:H,'Condicionales 2.0'!C6,IFT!F:F) -> 1 | H6: =+G6/F6 -> 1 | I6: =+H6 -> 1 | L6: % Adherencia | M6: =+'Resumen - Se oculta 2,0'!B39 -> 0.95677083 | P6: =+"BPLs Críticas Cumplidas "&M10&" de "&M9 -> BPLs Críticas Cumplidas 12 de 12
B7: =+B6+1 -> 3 | C7: CRITICO 3 | D7: =+IFT!C41 -> EPPS Y EXTINGUIDORES | F7: =COUNTIF(IFT!H:H,'Condicionales 2.0'!C7) -> 2 | G7: =SUMIF(IFT!H:H,'Condicionales 2.0'!C7,IFT!F:F) -> 2 | H7: =+G7/F7 -> 1 | I7: =+H7 -> 1 | L7: Categoria | M7: =+'Resumen - Se oculta 2,0'!D39 -> PROACTIVO
B8: =+B7+1 -> 4 | C8: CRITICO 4 | D8: =+IFT!C54 -> EQUIPAMIENTO DE MANIPULEO | F8: =COUNTIF(IFT!H:H,'Condicionales 2.0'!C8) -> 3 | G8: =SUMIF(IFT!H:H,'Condicionales 2.0'!C8,IFT!F:F) -> 3 | H8: =+G8/F8 -> 1 | I8: =+H8 -> 1
B9: =+B8+1 -> 5 | C9: CRITICO 5 | D9: =+PLG!C13 -> COORDINACIÓN DEL ABASTECIMIENTO | F9: =COUNTIF(PLG!H:H,'Condicionales 2.0'!C9) -> 4 | G9: =SUMIF(PLG!H:H,'Condicionales 2.0'!C9,PLG!F:F) -> 4 | H9: =+G9/F9 -> 1 | I9: =+H9 -> 1 | L9: Total | M9: =+F19 -> 12
B10: =+B9+1 -> 6 | C10: CRITICO 6 | D10: =+PLG!C33 -> INVENTARIOS ROTATIVOS | F10: =COUNTIF(PLG!H:H,'Condicionales 2.0'!C10) -> 3 | G10: =SUMIF(PLG!H:H,'Condicionales 2.0'!C10,PLG!F:F) -> 3 | H10: =+G10/F10 -> 1 | I10: =+H10 -> 1 | L10: Cumplidas | M10: =+G19 -> 12
B11: 7 | C11: CRITICO 7 | D11: =+GST!C23 -> PROCESOS DOCUMENTADOS | F11: =COUNTIF(GST!H:H,'Condicionales 2.0'!C11) -> 10 | G11: =SUMIF(GST!H:H,'Condicionales 2.0'!C11,GST!F:F) -> 10 | H11: =+G11/F11 -> 1 | I11: =+H11 -> 1
B12: =+B11+1 -> 8 | C12: CRITICO 8 | D12: =+GST!C55 -> INDICADORES | F12: =COUNTIF(GST!H:H,'Condicionales 2.0'!C12) -> 6 | G12: =SUMIF(GST!H:H,'Condicionales 2.0'!C12,GST!F:F) -> 6 | H12: =+G12/F12 -> 1 | I12: =+H12 -> 1 | L12: Categoria Final (con condicionales)
B13: =+B12+1 -> 9 | C13: CRITICO 9 | D13: =+IDP!C24 -> CONTROL DE TEMPERATURAS | F13: =COUNTIF(IDP!H:H,'Condicionales 2.0'!C13) -> 2 | G13: =SUMIF(IDP!H:H,'Condicionales 2.0'!C13,IDP!F:F) -> 2 | H13: =+G13/F13 -> 1 | I13: =+H13 -> 1 | L13: =+M6 -> 0.95677083 | M13: =+'Resumen - Se oculta 2,0'!B42 -> PROACTIVO
B14: =+B13+1 -> 10 | C14: CRITICO 10 | D14: =+IDP!C43 -> RECHAZOS | F14: =COUNTIF(IDP!H:H,'Condicionales 2.0'!C14) -> 2 | G14: =SUMIF(IDP!H:H,'Condicionales 2.0'!C14,IDP!F:F) -> 2 | H14: =+G14/F14 -> 1 | I14: =+H14 -> 1
B15: =+B14+1 -> 11 | C15: CRITICO 11 | D15: =+IDP!C45 -> DEVOLUCIONES DE PRODUCTOS NO APTOS | F15: =COUNTIF(IDP!H:H,'Condicionales 2.0'!C15) -> 2 | G15: =SUMIF(IDP!H:H,'Condicionales 2.0'!C15,IDP!F:F) -> 2 | H15: =+G15/F15 -> 1 | I15: =+H15 -> 1
B16: =+B15+1 -> 12 | C16: CRITICO 12 | D16: =+IDP!C60 -> CONTROL DE PLAGAS | F16: =COUNTIF(IDP!H:H,'Condicionales 2.0'!C16) -> 5 | G16: =SUMIF(IDP!H:H,'Condicionales 2.0'!C16,IDP!F:F) -> 5 | H16: =+G16/F16 -> 1 | I16: =+H16 -> 1
D18: Total COMPONENTES | F18: =SUM(F5:F16) -> 41 | G18: =SUM(G5:G16) -> 41 | H18: =+G18/F18 -> 1
D19: Total BPLs | F19: =+B16 -> 12 | G19: =COUNTIF(H5:H16,1) -> 12 | H19: =+G19/F19 -> 1

Sheet IFT
Y1: 0
F2: EV25 | K2: AE 25 | Y2: 1
E3: =+B5 -> Area de interés : Infraestructura | F3: =+O8+O19+O40+O58+O61 -> 0.93175 | K3: =+K8*N8+K19*N19+K40*N40+K58*N58+K61*N61 -> 0.992 | N3: AREA en programa | O3: 0.25 | Y3: N/A
E4: Programa | F4: =+F3*O3 -> 0.2329375 | G4: =+F4+PLG!F4+GST!F4+IDP!F4 -> 0.95677083 | K4: =+K3*O3 -> 0.248 | L4: =+K4+PLG!K4+GST!K4+IDP!K4 -> 0.959315 | Y4: NA - 1
B5: Area de interés : Infraestructura | N5: Ponderaciones en Area | Y5: NA - 0
B6: NRO. | C6: Buena Practica Logistica | E6: Componente | F6: EV25 | G6: Declaración de Buena Practica | H6: Critico | I6: Comentarios Evaluación | K6: AE 25 | N6: comp en el atributo | O6: Peso BPL
B8: 1 | C8: EMPLAZAMIENTO | F8: =SUMPRODUCT(F9:F17,N9:N17,O9:O17) -> 0.94 | K8: =SUMPRODUCT(K9:K17,N9:N17,O9:O17) -> 1 | N8: =+[1]MATRIZ!$G$8 -> 0.225 | O8: =+F8*N8 -> 0.2115
A9: 1 | B9: 1.1 | C9: ENTORNO Y SEGURIDAD EXTERNA | D9: 1.1.1 | E9: Predios cerrados, o Zonas industriales o logísticas | F9: 1 | G9: La localización geográfica donde se emplaza el depósito es segura en cuanto riesgos de seguridad patrimonial | K9: =+[2]IFT!F9 -> 1 | N9: 0.15 | O9: 0.5
A10: =A9+1 -> 2 | B10: 1.1 | C10: ENTORNO Y SEGURIDAD EXTERNA | D10: 1.1.2 | E10: Zona segura, con vigilancia de fuerzas públicas o privadas | F10: 1 | K10: =+[2]IFT!F10 -> 1 | N10: 0.35 | O10: 0.5
A11: =A10+1 -> 3 | B11: 1.1 | C11: ENTORNO Y SEGURIDAD EXTERNA | D11: 1.1.3 | E11: Zona provista de iluminación pública o propia. | F11: 1 | K11: =+[2]IFT!F11 -> 1 | N11: 0.3 | O11: 0.5
A12: =A11+1 -> 4 | B12: 1.1 | C12: ENTORNO Y SEGURIDAD EXTERNA | D12: 1.1.4 | E12: Existen cámaras de video externas pública o propia que cubran el ingreso principal o aledaños | F12: 1 | K12: =+[2]IFT!F12 -> 1 | N12: 0.2 | O12: 0.5
A13: =A12+1 -> 5 | B13: 1.2 | C13: ENTORNO - ACCESO | D13: 1.2.1 | E13: Capacidad de recibir unidades de alto tonelaje | F13: 1 | G13: La localización geográfica donde se emplaza el depósito permite / autoriza acceso a vehículos, inclusive de gran porte | H13: CRITICO 1 | K13: =+[2]IFT!F13 -> 1 | N13: 1 | O13: 0.35
A14: =A13+1 -> 6 | B14: 1.3 | C14: PREDIO Y CIRCULACION | D14: 1.3.2 | E14: Entorno sin problemas de congestionamiento de tráfico | F14: 1 | G14: Los accesos / calles internas del predio - o del entorno del depósito o vía pública - permiten la circulación segura de vehículos y otro equipamiento de maniobra. | K14: =+[2]IFT!F14 -> 1 | N14: 0.3 | O14: 0.15
A15: =A14+1 -> 7 | B15: 1.3 | C15: PREDIO Y CIRCULACION | D15: 1.3.3 | E15: Poseen alero o permiten el ingreso de la culata de los vehiculos para la carga/descarga en condiciones climáticas desfavorables | F15: 0 | I15: Sin alero. | K15: =+[2]IFT!F15 -> 1 | N15: 0.2 | O15: 0.15
A16: =A15+1 -> 8 | B16: 1.3 | C16: PREDIO Y CIRCULACION | D16: 1.3.4 | E16: Fácil maniobrabilidad | F16: 1 | K16: =+[2]IFT!F16 -> 1 | N16: 0.3 | O16: 0.15
A17: =A16+1 -> 9 | B17: 1.3 | C17: PREDIO Y CIRCULACION | D17: 1.3.5 | E17: Calles y accesos en buen estado, sin pendientes, consolidados o asfaltados | F17: 0 | I17: Calles de ripio. Usan escolta para cuidar cables y estructuras vecinas. | K17: =+[2]IFT!F17 -> 1 | N17: 0.2 | O17: 0.15
B19: 2 | C19: EDIFICACION | F19: =SUMPRODUCT(F20:F38,N20:N38,O20:O38) -> 0.925 | K19: =SUMPRODUCT(K20:K38,N20:N38,O20:O38) -> 0.98 | N19: =+[1]MATRIZ!$G$9 -> 0.4 | O19: =+F19*N19 -> 0.37
A20: =A17+1 -> 10 | B20: 2.1 | C20: SEGURIDAD INTERNA | D20: 2.1.1 | E20: Sistema de Alarmas en depósito y oficinas | F20: 1 | G20: La seguridad patrimonial se garantiza mediante infraestructura electrónica y/o actividades de vigilancia | K20: =+[2]IFT!F20 -> 1 | N20: 0.6 | O20: 0.05
A21: =A20+1 -> 11 | B21: 2.1 | C21: SEGURIDAD INTERNA | D21: 2.1.2 | E21: Cámaras de Video en distintos sectores, con grabación y registro | F21: 1 | K21: =+[2]IFT!F21 -> 1 | N21: 0.4 | O21: 0.05
A22: =A21+1 -> 12 | B22: 2.2 | C22: LAY OUT - CAPACIDAD Y MODULACION | D22: 2.2.1 | E22: Días hábiles promedio 6 meses de venta almacenados en la bodega (MinImo 21 dias) | F22: 1 | G22: La capacidad del depósito es adecuada para el volumen de ventas , asegura el flujo físico continuo y permite mantener la cobertura de stock definida por Arcor. | H22: CRITICO 2 | I22: Este componente se valida con información provista por ARCOR | K22: =+[2]IFT!F22 -> 1 | N22: 1 | O22: 0.5
A23: =A22+1 -> 13 | B23: 2.3 | C23: TECHOS y PAREDES: ESTADO | D23: 2.3.1 | E23: Techo aislado y/o revestido, bien conservado | F23: 1 | G23: Las paredes y los techos del depósito se encuentran en buen estado y cuentan con elementos que garantizan las condiciones de conservación de los productos , definidos por Arcor. Temperatura 35°C (máxima promedio). | K23: =+[2]IFT!F23 -> 1 | N23: 0.35 | O23: 0.1
A24: =A23+1 -> 14 | B24: 2.3 | C24: TECHOS y PAREDES: ESTADO | D24: 2.3.2 | E24: Paredes aisladas y/o revestidas, bien conservadas, que no permitan la acumulación de tierra o plagas | F24: 1 | K24: =+[2]IFT!F24 -> 1 | N24: 0.35 | O24: 0.1
A25: =A24+1 -> 15 | B25: 2.3 | C25: TECHOS y PAREDES: ESTADO | D25: 2.3.3 | E25: Cuenta con extractores eólicos y/o ventilación forzada | F25: 0 | K25: =+[2]IFT!F25 -> 0 | N25: 0.2 | O25: 0.1
A26: =A25+1 -> 16 | B26: 2.3 | C26: TECHOS y PAREDES: ESTADO | D26: 2.3.4 | E26: Posee termómetro en sector Secos, (no se permiten termometros de mercurio) | F26: 1 | K26: =+[2]IFT!F26 -> 1 | N26: 0.1 | O26: 0.1
A27: =A26+1 -> 17 | B27: 2.4 | C27: PISOS y JUNTAS: ESTADO | D27: 2.4.1 | E27: Posee terminación alisada (a llana) | F27: 1 | G27: Los pisos y juntas interiores del depósito son adecuados, en buen estado, garantizando y asegurando la operación. | K27: =+[2]IFT!F27 -> 1 | N27: 0.15 | O27: 0.225
A28: =A27+1 -> 18 | B28: 2.4 | C28: PISOS y JUNTAS: ESTADO | D28: 2.4.2 | E28: Las juntas poseen relleno (compuesto elástico ) y/o protección metálica que no genere golpes al transito de apiladoras o transpaletas | F28: 0 | I28: Mejorar piso en zona de recepción. Se Visualizan grietas | K28: =+[2]IFT!F28 -> 1 | N28: 0.2 | O28: 0.225
A29: =A28+1 -> 19 | B29: 2.4 | C29: PISOS y JUNTAS: ESTADO | D29: 2.4.3 | E29: No posee desniveles entre los paños | F29: 1 | K29: =+[2]IFT!F29 -> 1 | N29: 0.3 | O29: 0.225
A30: =A29+1 -> 20 | B30: 2.4 | C30: PISOS y JUNTAS: ESTADO | D30: 2.4.4 | E30: El piso no desprende polvillo y/o no se visualizan grietas | F30: 1 | K30: =+[2]IFT!F30 -> 1 | N30: 0.35 | O30: 0.225
A31: =A30+1 -> 21 | B31: 2.5 | C31: ABERTURAS | D31: 2.5.1 | E31: Cuenta con 2 o más portones | F31: 1 | G31: El depósito cuenta con al menos 2 portones e ingreso peatonal independiente | K31: =+[2]IFT!F31 -> 1 | N31: 0.6 | O31: 0.05
A32: =A31+1 -> 22 | B32: 2.5 | C32: =+C31 -> ABERTURAS | D32: 2.5.2 | E32: Posee ingreso de personal independiente de la carga | F32: 1 | K32: =+[2]IFT!F32 -> 1 | N32: 0.4 | O32: 0.05
A33: =A32+1 -> 23 | B33: 2.6 | C33: ILUMNACIÓN | D33: 2.6.1 | E33: Se encuentran por encima del nivel más alto de almacenamiento | F33: 1 | G33: El depósito cuenta con lluminación adecuada para garantizar una operación logística eficaz y segura | K33: =+[2]IFT!F33 -> 1 | N33: 0.4 | O33: 0.05
A34: =A33+1 -> 24 | B34: 2.6 | C34: ILUMNACIÓN | D34: 2.6.2 | E34: Se encuentran centradas a lo largo de los pasillos | F34: 1 | K34: =+[2]IFT!F34 -> 1 | N34: 0.3 | O34: 0.05
A35: =A34+1 -> 25 | B35: 2.6 | C35: ILUMNACIÓN | D35: 2.6.3 | E35: No se perciben sectores oscuros que afecten la operación | F35: 1 | K35: =+[2]IFT!F35 -> 1 | N35: 0.1 | O35: 0.05
A36: =A35+1 -> 26 | B36: 2.6 | C36: ILUMNACIÓN | D36: 2.6.4 | E36: Se aprovecha la luz natural para la operación diurna sin aumento considerable de la temperatura en el interior | F36: 0 | I36: no se visualizan ventanas. Con los portones cerrados se ve oscuro y deben usar luz artificial | K36: =+[2]IFT!F36 -> 1 | N36: 0.2 | O36: 0.05
A37: =A36+1 -> 27 | B37: 2.7 | C37: DESAGUES | D37: 2.7.1 | E37: Se ubican en el exterior del edificio | F37: 1 | G37: El depósito cuenta con desagües que permiten evacuar el agua acumulada por lluvia | K37: =+[2]IFT!F37 -> 1 | N37: 0.5 | O37: 0.025
A38: =A37+1 -> 28 | B38: 2.7 | C38: DESAGUES | D38: 2.7.2 | E38: Se encuentran en buen estado (no se visualizan manchas de humedad), con rejillas de protección | F38: 1 | K38: =+[2]IFT!F38 -> 1 | N38: 0.5 | O38: 0.025
B40: 3 | C40: ALMACENAMIENTO Y MANIPULEO | F40: =SUMPRODUCT(F41:F56,N41:N56,O41:O56) -> 0.91 | K40: =SUMPRODUCT(K41:K56,N41:N56,O41:O56) -> 1 | N40: =+[1]MATRIZ!$G$10 -> 0.275 | O40: =+F40*N40 -> 0.25025
A41: =A38+1 -> 29 | B41: 3.1 | C41: EPPS Y EXTINGUIDORES | D41: 3.1.1 | E41: Uso correcto de EPPS (zapatos o casco según reglamentación local vigente) | F41: 1 | G41: Uso correcto de EPP (zapatos, cascos) y extintores en correctas condiciones | H41: CRITICO 3 | K41: =+[2]IFT!F41 -> 1 | N41: 0.4 | O41: 0.5
A42: =A41+1 -> 30 | B42: 3.1 | C42: EPPS y Extinguidores | D42: 3.1.2 | E42: Extintores bien ubicados y en período de vencimiento | F42: 1 | H42: =+H41 -> CRITICO 3 | K42: =+[2]IFT!F42 -> 1 | N42: 0.6 | O42: 0.5
A43: =A42+1 -> 31 | B43: 3.2 | C43: POP Y MOBILIARIO | D43: 3.2.1 | E43: Los freezers y/o mobiliarios usados se encuentran en condiciones de higiene adecuadas | F43: N/A | G43: La infraestructura del depósito permite el almacenamiento de material promocional y de conservación en punto de venta (POP, mobiliario, freezers, etc) en un lugar aislado de la mercadería y seguro para la conservación y rotación de los mismos. | K43: =+[2]IFT!F43 -> 1 | N43: 0 | O43: 0.3
A44: =A43+1 -> 32 | B44: 3.2 | C44: POP Y MOBILIARIO | D44: 3.2.2 | E44: El material se encuentra inventariado el mueble pesado | F44: 1 | K44: =+[2]IFT!F44 -> 1 | N44: 0.4 | O44: 0.3
A45: =A44+1 -> 33 | B45: 3.2 | C45: POP Y MOBILIARIO | D45: 3.2.3 | E45: El material se encuentra en un sector aislado de la mercadería | F45: 0 | I45: Se visualiza el POP pesado, junto a mercaderia a procesar. | K45: =+[2]IFT!F45 -> 1 | N45: 0.3 | O45: 0.3
A46: =A45+1 -> 34 | B46: 3.2 | C46: POP Y MOBILIARIO | D46: 3.2.4 | E46: El material se encuentra identificado | F46: 1 | K46: =+[2]IFT!F46 -> 1 | N46: 0.3 | O46: 0.3
A47: =A46+1 -> 35 | B47: 3.3 | C47: CAMARA DE REFRIGERADOS | D47: 3.3.1 | E47: Indice nivel de capacidad para productos refrigerados es menor que 1 respecto a su capacidad teorica real | F47: N/A | G47: La cámara de refrigerados cuenta con las condiciones necesarias para cubir las necesidades de almacenamiento y control de temperatura (entre 15°C a 25 °C) garantizando la conservación de la mercadería. | K47: =+[2]IFT!F47 -> N/A | N47: 0.3 | O47: 0
A48: =A47+1 -> 36 | B48: 3.3 | C48: CAMARA DE REFRIGERADOS | D48: 3.3.2 | E48: Posee aislación térmica en paredes laterales, techo y acceso. Paredes aisladas y/o revestidas, bien conservadas, que no permitan la acumulación de tierra o plagas | F48: N/A | K48: =+[2]IFT!F48 -> N/A | N48: 0.3 | O48: 0
A49: =A48+1 -> 37 | B49: 3.3 | C49: CAMARA DE REFRIGERADOS | D49: 3.3.3 | E49: Posee termómetro en Cámara de Refrigerados, (no se permiten termometros de mercurio) | F49: N/A | K49: =+[2]IFT!F49 -> N/A | N49: 0.4 | O49: 0
A50: =A49+1 -> 38 | B50: 3.4 | C50: CAMARA DE CONGELADOS | D50: 3.4.1 | E50: Indice nivel de capacidad para productos congelados es menor que 1 respecto a su capacidad teorica real | F50: N/A | G50: La cámara de congelados cuenta con las condiciones necesarias para cubir las necesidades de almacenamiento y control de temperatura (-18 °C) garantizando la conservación de la mercadería. | K50: =+[2]IFT!F50 -> N/A | N50: 0.1 | O50: 0
A51: =A50+1 -> 39 | B51: 3.4 | C51: CAMARA DE CONGELADOS | D51: 3.4.2 | E51: Su ubicación permite carga / descarga directa desde el transporte | F51: N/A | K51: =+[2]IFT!F51 -> N/A | N51: 0.5 | O51: 0
A52: =A51+1 -> 40 | B52: 3.4 | C52: CAMARA DE CONGELADOS | D52: 3.4.3 | E52: Posee termómetro | F52: N/A | K52: =+[2]IFT!F52 -> N/A | N52: 0.1 | O52: 0
A53: =A52+1 -> 41 | B53: 3.5 | C53: EQUIPAMIENTO DE MANIPULEO | D53: 3.5.1 | E53: Cuenta con un equipo propio que le permite operar dentro del depósito y a su vez realizar la descarga de camiones | F53: 1 | G53: La infraestructura del depósito permite el almacenamiento de material promocional y de conservación en punto de venta (POP, mobiliario, freezers, etc) en un lugar aislado de la mercadería y seguro para la conservación y rotación de los mismos. | H53: CRITICO 4 | K53: =+[2]IFT!F53 -> 1 | N53: 0.3 | O53: 0.2
A54: =A53+1 -> 42 | B54: 3.5 | C54: EQUIPAMIENTO DE MANIPULEO | D54: 3.5.2 | E54: Cuenta con traspallets o "zorritas" | F54: 1 | H54: =+H53 -> CRITICO 4 | K54: =+[2]IFT!F54 -> 1 | N54: 0.3 | O54: 0.2
A55: =A54+1 -> 43 | B55: 3.5 | C55: EQUIPAMIENTO DE MANIPULEO | D55: 3.5.3 | E55: Cuenta con carros para Consolidados/Pedidos | F55: 1 | K55: =+[2]IFT!F55 -> 1 | N55: 0.1 | O55: 0.2
A56: =A55+1 -> 44 | B56: 3.5 | C56: EQUIPAMIENTO DE MANIPULEO | D56: 3.5.4 | E56: El equipo para operar (dentro del depósito) es electrico | F56: 1 | H56: =+H54 -> CRITICO 4 | I56: Tambien manuales | K56: =+[2]IFT!F56 -> 1 | N56: 0.3 | O56: 0.2
B58: 4 | C58: TRANSPORTE Y REPARTO | F58: =SUMPRODUCT(F59:F60,N59:N60,O59:O60) -> 1 | K58: =+K59*N59*O59 -> 1 | N58: =+[1]MATRIZ!$G$11 -> 0.025 | O58: =+F58*N58 -> 0.025
A59: =A56+1 -> 45 | B59: 4.1 | C59: VEHICULOS | D59: 4.1.1 | E59: Se guardan en sectores seguros y aislados de la mercadería | F59: 1 | G59: Los vehiculos son guardados en sectores aislados de la mercaderia | K59: =+[2]IFT!F59 -> 1 | N59: 1 | O59: 1
B61: 5 | C61: INFORMACIÓN Y COMUNICACIONES | F61: =SUMPRODUCT(F62:F66,N62:N66,O62:O66) -> 1 | K61: =SUMPRODUCT(K62:K66,N62:N66,O62:O66) -> 1 | N61: =+[1]MATRIZ!$G$12 -> 0.075 | O61: =+F61*N61 -> 0.075
A62: =A59+1 -> 46 | B62: 5.1 | C62: INFORMÁTICA | D62: 5.1.1 | E62: El personal de logística cuenta con acceso al sistema y/o con usuario propio | F62: 1 | G62: El equipamiento informático es accesible al personal de logística y permite un flujo de información que facilita la operación del depósito | K62: =+[2]IFT!F62 -> 1 | N62: 0.3 | O62: 0.5
A63: =A62+1 -> 47 | B63: 5.1 | C63: INFORMÁTICA | D63: 5.1.2 | E63: El personal de logística cuenta con acceso a correo electrónico y/o con cuenta propia | F63: 1 | K63: =+[2]IFT!F63 -> 1 | N63: 0.4 | O63: 0.5
A64: =A63+1 -> 48 | B64: 5.1 | C64: INFORMÁTICA | D64: 5.1.3 | E64: El personal de logística cuenta con equipamiento informático en su oficina | F64: 1 | K64: =+[2]IFT!F64 -> 1 | N64: 0.3 | O64: 0.5
A65: =A64+1 -> 49 | B65: 5.2 | C65: COMUNICACIONES | D65: 5.2.1 | E65: El personal de logística cuenta con algún dispositivo de comunicación que permita contactarse al interior y exterior de la distribuidora | F65: 1 | G65: El equipamiento de comunicaciones es accesible al personal de logística y permite coordinar actividades operativas con clientes o proveedores, internos o externos | K65: =+[2]IFT!F65 -> 1 | N65: 1 | O65: 0.35
A66: =A65+1 -> 50 | B66: 5.3 | C66: ADQUISICIÓN DE DATOS | D66: 5.3.1 | E66: El personal de logística cuenta cámaras digitales o escáneres, o "smartphones" | F66: 1 | G66: El equipamiento de adquisición de datos es accesible al personal de logística y permite recopilar evidencias o anomalías en la operación | K66: =+[2]IFT!F66 -> 1 | N66: 1 | O66: 0.15

Sheet PLG
Z1: 0
F2: EV25 | K2: AE 25 | Z2: 1
E3: =+B5 -> Area de interés : Procesos Logísticos | F3: =+O8+O18+O28+O36+O48+O56 -> 0.96 | K3: =+K8*N8+K18*N18+K28*N28+K36*N36+K48*N48+K56*N56 -> 0.955 | N3: AREA en programa | O3: 0.25 | Z3: N/A
E4: Programa | F4: =+F3*O3 -> 0.24 | G4: =+F4+IFT!F4+GST!F4+IDP!F4 -> 0.95677083 | K4: =+K3*O3 -> 0.23875 | L4: =+K4+IFT!K4+GST!K4+IDP!K4 -> 0.959315 | Z4: NA - 1
B5: Area de interés : Procesos Logísticos | N5: Ponderaciones en Area | Z5: NA - 0
B6: NRO. | C6: Buena Practica Logistica | E6: Componente | F6: EV25 | G6: Declaración de Buena Practica | H6: Critico | I6: Comentarios Evaluación | K6: AE 25 | N6: comp en el atributo | O6: Peso BPL
B8: 6 | C8: ABASTECIMIENTO Y RECEPCIÓN | F8: =SUMPRODUCT(F9:F16,N9:N16,O9:O16) -> 1 | K8: =SUMPRODUCT(K9:K16,N9:N16,O9:O16) -> 1 | N8: =+[1]MATRIZ!$G$13 -> 0.2 | O8: =+N8*F8 -> 0.2
A9: =+IFT!A66+1 -> 51 | B9: 6.1 | C9: PLANIFICACIÓN DE LAS COMPRAS | D9: 6.1.1 | E9: Se informa/comunica las compras ( de volumen mayor a los normal o excepcionales)a Logística para que pueda planificar la operación de descarga y espacio necesario.(Registro, email, etc) | F9: 1 | G9: Logística interviene en el proceso de planificación de necesidades de Compras. | K9: =+[2]PLG!F9 -> 1 | N9: 0.6 | O9: 0.45
A10: =A9+1 -> 52 | B10: 6.1 | C10: PLANIFICACIÓN DE LAS COMPRAS | D10: 6.1.2 | E10: Realizan compras proporcionales y distribuidas dentro del mes | F10: 1 | K10: =+[2]PLG!F10 -> 1 | N10: 0.4 | O10: 0.45
A11: =A10+1 -> 53 | B11: 6.2 | C11: ACTIVACION DEL ABASTECIMIENTO | D11: 6.2.1 | E11: Logística recibe el IAD | F11: 1 | G11: El proceso de activación del abastecimiento minimiza arribos imprevistos o demoras exageradas. | K11: =+[2]PLG!F11 -> 1 | N11: 1 | O11: 0.3
A12: =A11+1 -> 54 | B12: 6.3 | C12: COORDINACIÓN DEL ABASTECIMIENTO | D12: 6.3.1 | E12: Previsión de espacio para el guardado/almacenamiento y/o reordenamiento de la mercadería | F12: 1 | G12: El proceso de coordinación del abastecimiento permite planificar recursos para la descarga. | H12: CRITICO 5 | K12: =+[2]PLG!F12 -> 1 | N12: 0.3 | O12: 0.15
A13: =A12+1 -> 55 | B13: 6.3 | C13: COORDINACIÓN DEL ABASTECIMIENTO | D13: 6.3.2 | E13: Previsión de personas y equipo (Apilador/Autoelevador) necesarias para la descarga | F13: 1 | H13: CRITICO 5 | K13: =+[2]PLG!F13 -> 1 | N13: 0.3 | O13: 0.15
A14: =A13+1 -> 56 | B14: 6.3 | C14: COORDINACIÓN DEL ABASTECIMIENTO | D14: 6.3.3 | E14: Cuenta con una ventana horaria de 8hs para recepción de mercadería | F14: 1 | H14: CRITICO 5 | K14: =+[2]PLG!F14 -> 1 | N14: 0.2 | O14: 0.15
A15: =A14+1 -> 57 | B15: 6.3 | C15: COORDINACIÓN DEL ABASTECIMIENTO | D15: 6.3.4 | E15: Descarga en lugares definidos | F15: 1 | H15: CRITICO 5 | K15: =+[2]PLG!F15 -> 1 | N15: 0.2 | O15: 0.15
A16: =A15+1 -> 58 | B16: 6.4 | C16: RECEPCION | D16: 6.4.1 | E16: Las novedades se transmiten a Logística de Arcor por correo | F16: 1 | G16: El proceso de control de recepción garantiza integridad de la mercadería y transmisión a Arcor de discrepancias | K16: =+[2]PLG!F16 -> 1 | N16: 1 | O16: 0.1
B18: 7 | C18: ALMACENAMIENTO Y MANIPULEO | F18: =SUMPRODUCT(F19:F26,N19:N26,O19:O26) -> 0.75 | K18: =SUMPRODUCT(K19:K26,N19:N26,O19:O26) -> 1 | N18: =+[1]MATRIZ!$G$14 -> 0.1 | O18: =+N18*F18 -> 0.075
A19: =+A16+1 -> 59 | B19: 7.1 | C19: ORGANIZACIÓN DEL LAY OUT | D19: 7.1.1 | E19: Frecuencia definida documentada de revisión y/o modificación del lay-out (minimo cada 3 meses, maximo cada 6 meses) | F19: 0 | G19: La Organización del lay out optimiza el guardado, rotación, reposición y preparado de mercadería | I19: Lo ordena el sistema Ramdon. No se realiza modificación | K19: =+[2]PLG!F19 -> 1 | N19: 0.5 | O19: 0.5
A20: =A19+1 -> 60 | B20: 7.1 | C20: =+C19 -> ORGANIZACIÓN DEL LAY OUT | D20: 7.1.2 | E20: Pasillos organizados por algun criterio logico (Negocio, ABC, familia, etc) | F20: 1 | K20: =+[2]PLG!F20 -> 1 | N20: 0.5 | O20: 0.5
A21: =A20+1 -> 61 | B21: 7.2 | C21: IDENTIFICACION DEL LAY OUT | D21: 7.2.1 | E21: Cada área del lay out se encuentra demarcada (Zonas pintadas en el piso) | F21: 1 | G21: Se encuentran definidas e identificadas las zonas del lay out | K21: =+[2]PLG!F21 -> 1 | N21: 0.3 | O21: 0.15
A22: =A21+1 -> 62 | B22: 7.2 | C22: IDENTIFICACION DEL LAY OUT | D22: 7.2.2 | E22: Áreas principales identificadas (Recepción-Despacho-Devoluciones-Mercadería no comercializable-picking/almacenamiento) | F22: 1 | K22: =+[2]PLG!F22 -> 1 | N22: 0.4 | O22: 0.15
A23: =A22+1 -> 63 | B23: 7.2 | C23: =+C22 -> IDENTIFICACION DEL LAY OUT | D23: 7.2.3 | E23: No hay superposición entre áreas críticas (Despacho y Recepción por ej) | F23: 1 | K23: =+[2]PLG!F23 -> 1 | N23: 0.3 | O23: 0.15
A24: =A23+1 -> 64 | B24: 7.3 | C24: IDENTIFICACION DEL LAY OUT | D24: 7.3.1 | E24: Control de rotación y vencimientos junto al inventario rotativo y/o auditorias de 5S | F24: 1 | G24: Se garantiza identificación y rotación de la mercadería (FEFO), en sectores de almacenamiento como de preparado | K24: =+[2]PLG!F24 -> 1 | N24: 0.4 | O24: 0.35
A25: =A24+1 -> 65 | B25: 7.3 | C25: ROTACION | D25: 7.3.2 | E25: Se lleva registro de las unidades vencidas | F25: 1 | K25: =+[2]PLG!F25 -> 1 | N25: 0.3 | O25: 0.35
A26: =A25+1 -> 66 | B26: 7.3 | C26: =+C25 -> ROTACION | D26: 7.3.2 | E26: Se informa sobre productos proximos a vencer a fin de tomar acciones | F26: 1 | K26: =+[2]PLG!F26 -> 1 | N26: 0.3 | O26: 0.35
B28: 8 | C28: REPOSICION INVENTARIOS | F28: =SUMPRODUCT(F29:F34,N29:N34,O29:O34) -> 1 | K28: =SUMPRODUCT(K29:K34,N29:N34,O29:O34) -> 1 | N28: =+[1]MATRIZ!$G$15 -> 0.25 | O28: =+N28*F28 -> 0.25
A29: =+A26+1 -> 67 | B29: 8.1 | C29: REPOSICIÓN DE MERCADERIA | D29: 8.1.1 | E29: Logística o personal designado supervisa por turno o por día con algún criterio (Por ej: Productos A) | F29: 1 | G29: Está estandarizado el proceso de reposición de mercadería desde almacenamiento a picking. | K29: =+[2]PLG!F29 -> 1 | N29: 0.3 | O29: 0.2
A30: =A29+1 -> 68 | B30: 8.1 | C30: REPOSICIÓN DE MERCADERIA | D30: 8.1.2 | E30: Posiciones fijas de pickeo con capacidades definidas y/o frecuencias de reposición. | F30: 1 | K30: =+[2]PLG!F30 -> 1 | N30: 0.4 | O30: 0.2
A31: =A30+1 -> 69 | B31: 8.1 | C31: =+C29 -> REPOSICIÓN DE MERCADERIA | D31: 8.1.3 | E31: Se verifica el volumen de la posición de picking con una frecuencia determinada (minimo cada 3 meses, maximo cada 6 meses) | F31: 1 | K31: =+[2]PLG!F31 -> 1 | N31: 0.3 | O31: 0.2
A32: =+A31+1 -> 70 | B32: 8.2 | C32: =+C33 -> INVENTARIOS ROTATIVOS | D32: 8.2.1 | E32: Se analizan causas al finalizar. Se registran acciones | F32: 1 | G32: Se realizan inventarios rotativos para asegurar confiabilidad del stock | H32: CRITICO 6 | K32: =+[2]PLG!F32 -> 1 | N32: 0.4 | O32: 0.8
A33: =A32+1 -> 71 | B33: 8.2 | C33: INVENTARIOS ROTATIVOS | D33: 8.2.2 | E33: Criterio definido de selección de items (ABC, rotativo,negocio, pasillo, etc.). Se toman y/o verifican fechas de vencimientos. | F33: 1 | H33: CRITICO 6 | I33: Viernes por familia. | K33: =+[2]PLG!F33 -> 1 | N33: 0.35 | O33: 0.8
A34: =A33+1 -> 72 | B34: 8.2 | C34: =+C32 -> INVENTARIOS ROTATIVOS | D34: 8.2.3 | E34: Se realizan con una frecuencia definida, mínima mensual | F34: 1 | H34: CRITICO 6 | I34: Se completa en un mes el 100% del deposito | K34: =+[2]PLG!F34 -> 1 | N34: 0.25 | O34: 0.8
B36: 9 | C36: CONSOLIDADOS Y PEDIDOS | F36: =SUMPRODUCT(F37:F46,N37:N46,O37:O46) -> 1 | K36: =SUMPRODUCT(K37:K46,N37:N46,O37:O46) -> 0.88 | N36: =+[1]MATRIZ!$G$16 -> 0.25 | O36: =+N36*F36 -> 0.25
A37: =+A34+1 -> 73 | B37: 9.1 | C37: TRANSMISION DE PEDIDOS | D37: 9.1.1 | E37: Ventana horaria establecida para el corte de pedidos | F37: 1 | G37: Existe una transmisión de pedidos en forma continua o con algún criterio | K37: =+[2]PLG!F37 -> 1 | N37: 0.6 | O37: 0.1
A38: =A37+1 -> 74 | B38: 9.1 | C38: =+C37 -> TRANSMISION DE PEDIDOS | D38: 9.1.2 | E38: Realiza analisis frecuentes relacionado a desvios en el corte de pedidos | F38: 1 | K38: =+[2]PLG!F38 -> 1 | N38: 0.4 | O38: 0.1
A39: =A38+1 -> 75 | B39: 9.2 | C39: ARMADO Y ASIGNACIÓN DE CONSOLIDADOS Y/O PEDIDOS | D39: 9.2.1 | E39: El ordenamiento físico de los productos coincide con el consolidado | F39: 1 | G39: La generación de consolidados se hace por criterios definidos (cortes x $; cant Bultos; reparto, vendedor, etc) optimizando los recursos de la distribuidora | K39: =+[2]PLG!F39 -> 1 | N39: 0.5 | O39: 0.15
A40: =A39+1 -> 76 | B40: 9.2 | C40: =+C39 -> ARMADO Y ASIGNACIÓN DE CONSOLIDADOS Y/O PEDIDOS | D40: 9.2.2 | E40: Se generan los consolidados aplicando criterios (Logísticos)de corte a partir de los pedidos ingresados-Solo para los que trabajan pedido por pedido | F40: 1 | K40: =+[2]PLG!F40 -> 1 | N40: 0.5 | O40: 0.15
A41: =+A40+1 -> 77 | B41: 9.3 | C41: =+C42 -> CONTROL DE CONSOLIDADO | D41: 9.3.1 | E41: Se registran los errores y usuarios para mejorar el proceso | F41: 1 | G41: Existe un control de los consolidados preparados que evita las diferencias entre la orden y la preparación fisica | K41: =+[2]PLG!F41 -> 0 | N41: 0.3 | O41: 0.4
A42: =A41+1 -> 78 | B42: 9.3 | C42: CONTROL DE CONSOLIDADO | D42: 9.3.2 | E42: Se conserva en forma transitoria registro de control del consolidado | F42: 1 | K42: =+[2]PLG!F42 -> 1 | N42: 0.45 | O42: 0.4
A43: =A42+1 -> 79 | B43: 9.3 | C43: =+C41 -> CONTROL DE CONSOLIDADO | D43: 9.3.3 | E43: Existe un metodo de control de consolidado | F43: 1 | K43: =+[2]PLG!F43 -> 1 | N43: 0.25 | O43: 0.4
A44: =+A43+1 -> 80 | B44: 9.4 | C44: =+C45 -> ARMADO DE PEDIDOS | D44: 9.4.1 | E44: El pedido contiene identificación de bultos, cliente, zona de reparto, factura, o alguna identificación que facilite la carga | F44: 1 | G44: El control del armado evita las diferencias entre la orden y la preparación fisica | K44: =+[2]PLG!F44 -> 1 | N44: 0.3 | O44: 0.35
A45: =A44+1 -> 81 | B45: 9.4 | C45: ARMADO DE PEDIDOS | D45: 9.4.2 | E45: Se registran los errores y usuarios para mejorar el proceso en el armado de pedido | F45: 1 | K45: =+[2]PLG!F45 -> 1 | N45: 0.3 | O45: 0.35
A46: =A45+1 -> 82 | B46: 9.4 | C46: =+C44 -> ARMADO DE PEDIDOS | D46: 9.4.3 | E46: El ordenamiento coincide con las facturas/pedido | F46: 1 | K46: =+[2]PLG!F46 -> 1 | N46: 0.4 | O46: 0.35
B48: 10 | C48: TRANSPORTE Y REPARTO | F48: =SUMPRODUCT(F49:F54,N49:N54,O49:O54) -> 0.85 | K48: =SUMPRODUCT(K49:K54,N49:N54,O49:O54) -> 0.85 | N48: =+[1]MATRIZ!$G$17 -> 0.1 | O48: =+N48*F48 -> 0.085
A49: =+A46+1 -> 83 | B49: 10.1 | C49: PEDIDOS LISTOS PARA CARGA | D49: 10.1.1 | E49: La carga en la zona de despacho contiene identificación zona/reparto/fletero. | F49: 1 | G49: Existe un criterio para la organización de los repartos previo a la carga de las unidades | K49: =+[2]PLG!F49 -> 1 | N49: 1 | O49: 0.2
A50: =+A49+1 -> 84 | B50: 10.2 | C50: =+C51 -> CARGA DE PEDIDOS | D50: 10.2.1 | E50: Pedido:La carga se realiza por LIFO de acuerdo al ruteo. Consolidado:La mercadería se carga organizada (manteniendo identificado cada negocio para su pickeo en el punto de venta | F50: 1 | G50: Existe un criterio para la carga de las unidades de transporte que garantice el orden y control de la misma | K50: =+[2]PLG!F50 -> 1 | N50: 0.35 | O50: 0.5
A51: =A50+1 -> 85 | B51: 10.2 | C51: CARGA DE PEDIDOS | D51: 10.2.2 | E51: Cuenta con metodologia o registro de la hoja de ruta y el responsable del armado | F51: 1 | K51: =+[2]PLG!F51 -> 1 | N51: 0.5 | O51: 0.5
A52: =A51+1 -> 86 | B52: 10.2 | C52: =+C50 -> CARGA DE PEDIDOS | D52: 10.2.3 | E52: Fletero controla y realiza la carga, si existe diferencia verifica con logística y realiza un registro de conformidad | F52: 1 | K52: =+[2]PLG!F52 -> 1 | N52: 0.15 | O52: 0.5
A53: =+A52+1 -> 87 | B53: 10.3 | C53: ENTREGA AL CLIENTE | D53: 10.3.1 | E53: Posee registro de reclamos del cliente (Planilla con registro de incidentes) | F53: 0 | G53: La entrega de mercadería (pedidos) al cliente garantiza la integridad de la carga contra el documento de transporte. Se solucionan discrepancias | I53: Quieren implementar una planilla de CRM pero aun no lo hicieron | K53: =+[2]PLG!F53 -> 0 | N53: 0.5 | O53: 0.3
A54: =A53+1 -> 88 | B54: 10.3 | C54: =+C53 -> ENTREGA AL CLIENTE | D54: 10.3.2 | E54: Cuenta con registro de pedidos reasignados | F54: 1 | I54: Tienen zonade Reasiginados. | K54: =+[2]PLG!F54 -> 1 | N54: 0.5 | O54: 0.3
B56: 11 | C56: RETORNO Y/O DEVOLUCIONES | F56: =SUMPRODUCT(F57:F60,N57:N60,O57:O60) -> 1 | K56: =SUMPRODUCT(K57:K60,N57:N60,O57:O60) -> 1 | N56: =+[1]MATRIZ!$G$18 -> 0.1 | O56: =+N56*F56 -> 0.1
A57: =+A54+1 -> 89 | B57: 11.1 | C57: RECHAZOS / DEVOLUCIONES | D57: 11.1.1 | E57: Registro de motivos para posterior analisis y mejora del proceso | F57: 1 | G57: El procesamiento de devoluciones de cualquier tipo, desde el cliente se encuentra estandarizado | K57: =+[2]PLG!F57 -> 1 | N57: 0.3 | O57: 1
A58: =+A57+1 -> 90 | B58: 11.1 | C58: RECHAZOS / DEVOLUCIONES | D58: 11.1.2 | E58: Mercadería ordenada con algún criterio y documentación de respaldo para validacion | F58: 1 | K58: =+[2]PLG!F58 -> 1 | N58: 0.3 | O58: 1
A59: =+A58+1 -> 91 | B59: 11.1 | C59: RECHAZOS / DEVOLUCIONES | D59: 11.1.3 | E59: Mercadería en el sector identificada y controlada | F59: 1 | K59: =+[2]PLG!F59 -> 1 | N59: 0.25 | O59: 1
A60: =+A59+1 -> 92 | B60: 11.1 | C60: RECHAZOS / DEVOLUCIONES | D60: 11.1.4 | E60: Lugar físico identificado y separado para almacenar rechazos/devoluciones | F60: 1 | K60: =+[2]PLG!F60 -> 1 | N60: 0.15 | O60: 1

Sheet GST
Z1: 0
F2: EV25 | K2: AE 25 | Z2: 1
E3: =+B5 -> Area de interés : Gestión | F3: =+O8+O31+O42+O48+O52 -> 0.958 | K3: =+K8*N8+K31*N31+K42*N42+K48*N48+K52*N52 -> 0.9225 | N3: AREA en programa | O3: 0.2 | Z3: N/A
E4: Programa | F4: =+F3*O3 -> 0.1916 | G4: =+IFT!F4+PLG!F4+GST!F4+IDP!F4 -> 0.95677083 | K4: =+K3*O3 -> 0.1845 | L4: =+IFT!K4+PLG!K4+GST!K4+IDP!K4 -> 0.959315 | Z4: NA - 1
B5: Area de interés : Gestión | N5: Ponderaciones en Area | Z5: NA - 0
B6: NRO. | C6: Buena Practica Logistica | E6: Componente | F6: EV25 | G6: Declaración de Buena Practica | H6: Critico | I6: Comentarios Evaluación | K6: AE 25 | N6: comp en el atributo | O6: Peso BPL
B8: 12 | C8: ORGANIZACIÓN | F8: =SUMPRODUCT(F9:F29,N9:N29,O9:O29) -> 1 | K8: =SUMPRODUCT(K9:K29,N9:N29,O9:O29) -> 0.85 | N8: =+[1]MATRIZ!$G$19 -> 0.25 | O8: =+N8*F8 -> 0.25
A9: =+PLG!A60+1 -> 93 | B9: 12.1 | C9: HERRAMIENTAS DE GESTION | D9: 12.1.1 | E9: Dispone de alguna herramienta informatica y la utiliza en el depósito | F9: N/A | G9: Cuenta con herramientas de le permita gestionar las operaciones del depósito (warehouse) , logistica de salida y reversa (Arcortruck) | K9: =+[2]GST!F9 -> N/A | N9: 0.2 | O9: 0
A10: =A9+1 -> 94 | B10: 12.1 | C10: HERRAMIENTAS DE GESTION | D10: 12.1.2 | E10: Cuenta con la aplicación de Arcortrukc para gestionar las entregas , rechazos y/o devoluciones de los clientes | F10: N/A | K10: =+[2]GST!F10 -> N/A | N10: 0.2 | O10: 0
A11: =A10+1 -> 95 | B11: 12.1 | C11: HERRAMIENTAS DE GESTION | D11: 12.1.3 | E11: Utiliza el Modulo Recepción | F11: N/A | K11: =+[2]GST!F11 -> N/A | N11: 0.1 | O11: 0
A12: =A11+1 -> 96 | B12: 12.1 | C12: HERRAMIENTAS DE GESTION | D12: 12.1.4 | E12: Utiliza el Modulo Inventario | F12: N/A | K12: =+[2]GST!F12 -> N/A | N12: 0.1 | O12: 0
A13: =A12+1 -> 97 | B13: 12.1 | C13: HERRAMIENTAS DE GESTION | D13: 12.1.5 | E13: Utiliza el Modulo Picking | F13: N/A | K13: =+[2]GST!F13 -> N/A | N13: 0.2 | O13: 0
A14: =A13+1 -> 98 | B14: 12.1 | C14: HERRAMIENTAS DE GESTION | D14: 12.1.6 | E14: Utiliza el Modulo Control de Consolidados | F14: N/A | K14: =+[2]GST!F14 -> N/A | N14: 0.1 | O14: 0
A15: =A14+1 -> 99 | B15: 12.1 | C15: HERRAMIENTAS DE GESTION | D15: 12.1.7 | E15: Utiliza el Modulo Armado de Pedidos | F15: N/A | K15: =+[2]GST!F15 -> N/A | N15: 0.1 | O15: 0
A16: =+A15+1 -> 100 | B16: 12.2 | C16: ORGANIGRAMAS Y PERFILES | D16: 12.2.1 | E16: Se encuentran comunicados | F16: 1 | G16: Existe un Organigrama que establece funciones y jerarquías en la distribuidora, incluyendo los perfiles de puestos principales | I16: buen manuan de procesos y perfiles. Pedir explicación sobre comunicación | K16: =+[2]GST!F16 -> 0 | N16: 0.3 | O16: 0.3
A17: =+A16+1 -> 101 | B17: 12.2 | C17: ORGANIGRAMAS Y PERFILES | D17: 12.2.2 | E17: Se encuentra definido y documentado el perfil del puesto de MML logística | F17: 1 | K17: =+[2]GST!F17 -> 0 | N17: 0.2 | O17: 0.3
A18: =+A17+1 -> 102 | B18: 12.2 | C18: ORGANIGRAMAS Y PERFILES | D18: 12.2.3 | E18: Se encuentran definidos los perfiles de puestos principales (comercial y administrativo) | F18: 1 | K18: =+[2]GST!F18 -> 1 | N18: 0.15 | O18: 0.3
A19: =+A18+1 -> 103 | B19: 12.2 | C19: ORGANIGRAMAS Y PERFILES | D19: 12.2.4 | E19: El organigrama se encuentra definido y documentado por la distribuidora | F19: 1 | K19: =+[2]GST!F19 -> 1 | N19: 0.35 | O19: 0.3
A20: =+A19+1 -> 104 | B20: 12.3 | C20: PROCESOS DOCUMENTADOS | D20: 12.3.1 | E20: Cuenta con el Procedimiento Proceso de Recepción y Control de Mercadería | F20: 1 | G20: Los procesos logísticos se encuentran documentados y actualizados. Sirven para evaluar desempeño del proceso y para induccion de nuevos recursos | H20: CRITICO 7 | I20: Revisar fecha para actualizar. Completar responsables | K20: =+[2]GST!F20 -> 1 | N20: 0.1 | O20: 0.7
A21: =+A20+1 -> 105 | B21: 12.3 | C21: PROCESOS DOCUMENTADOS | D21: 12.3.2 | E21: Cuenta con el Procedimiento Proceso de Reposición de Productos en Picking | F21: 1 | H21: CRITICO 7 | K21: =+[2]GST!F21 -> 1 | N21: 0.1 | O21: 0.7
A22: =+A21+1 -> 106 | B22: 12.3 | C22: PROCESOS DOCUMENTADOS | D22: 12.3.3 | E22: Cuenta con el Procedimiento Proceso de Almacenamiento de Productos | F22: 1 | H22: CRITICO 7 | K22: =+[2]GST!F22 -> 1 | N22: 0.1 | O22: 0.7
A23: =+A22+1 -> 107 | B23: 12.3 | C23: PROCESOS DOCUMENTADOS | D23: 12.3.4 | E23: Cuenta con el Procedimiento Proceso de Armado y Control de Consolidados | F23: 1 | H23: CRITICO 7 | K23: =+[2]GST!F23 -> 1 | N23: 0.1 | O23: 0.7
A24: =+A23+1 -> 108 | B24: 12.3 | C24: PROCESOS DOCUMENTADOS | D24: 12.3.5 | E24: Cuenta con el Procedimiento Proceso de Armado de Pedidos | F24: 1 | H24: CRITICO 7 | K24: =+[2]GST!F24 -> 1 | N24: 0.1 | O24: 0.7
A25: =+A24+1 -> 109 | B25: 12.3 | C25: PROCESOS DOCUMENTADOS | D25: 12.3.6 | E25: Cuenta con el Procedimiento Proceso de Control de hojas de ruta y carga de pedidos | F25: 1 | H25: CRITICO 7 | K25: =+[2]GST!F25 -> 1 | N25: 0.1 | O25: 0.7
A26: =+A25+1 -> 110 | B26: 12.3 | C26: PROCESOS DOCUMENTADOS | D26: 12.3.7 | E26: Cuenta con el Procedimiento Proceso de Control de Inventario | F26: 1 | H26: CRITICO 7 | K26: =+[2]GST!F26 -> 1 | N26: 0.1 | O26: 0.7
A27: =+A26+1 -> 111 | B27: 12.3 | C27: PROCESOS DOCUMENTADOS | D27: 12.3.8 | E27: Cuenta con el Procedimiento Proceso de Control de Hoja de Ruta y Logistica de Reversa | F27: 1 | H27: CRITICO 7 | K27: =+[2]GST!F27 -> 1 | N27: 0.1 | O27: 0.7
A28: =+A27+1 -> 112 | B28: 12.3 | C28: PROCESOS DOCUMENTADOS | D28: 12.3.9 | E28: Los responsables del proceso conocen el procedimiento, el mismo coincide con el proceso | F28: 1 | H28: CRITICO 7 | K28: =+[2]GST!F28 -> 1 | N28: 0.1 | O28: 0.7
A29: =+A28+1 -> 113 | B29: 12.3 | C29: PROCESOS DOCUMENTADOS | D29: 12.3.10 | E29: El formato del procedimiento se ajusta al modelo estandar propuesto por Arcor | F29: 1 | H29: CRITICO 7 | K29: =+[2]GST!F29 -> 1 | N29: 0.1 | O29: 0.7
B31: 13 | C31: PLANIFICACION | F31: =SUMPRODUCT(F32:F40,N32:N40,O32:O40) -> 1 | K31: =SUMPRODUCT(K32:K40,N32:N40,O32:O40) -> 1 | N31: =+[1]MATRIZ!$G$20 -> 0.25 | O31: =+N31*F31 -> 0.25
A32: =+A29+1 -> 114 | B32: 13.1 | C32: PLANIFICACIÓN TÁCTICA | D32: 13.1.1 | E32: Logistica participa de reuniones con Ventas y Administracion, en las cuales se definen objetivos anuales y/o mensuales | F32: 1 | G32: Se planifican tareas en forma periodica (diarias, semanal, quincenal, mensual) en el sector, distribuyendo actividades y dejando establecidas las responsabilidades para cada uno. | K32: =+[2]GST!F32 -> 1 | N32: 0.4 | O32: 0.45
A33: =A32+1 -> 115 | B33: 13.1 | C33: PLANIFICACIÓN TÁCTICA | D33: 13.1.2 | E33: Se realiza el seguimiento de la planificación en forma períodica (semanal, quincenal o mensual) evaluando el alcance de los resultados. | F33: 1 | I33: Incorporar armado de minuta con detalle de participantes, motivo, y luego plasmar en un plan de acción | K33: =+[2]GST!F33 -> 1 | N33: 0.3 | O33: 0.45
A34: =A33+1 -> 116 | B34: 13.1 | C34: PLANIFICACIÓN TÁCTICA | D34: 13.1.3 | E34: Las acciones surgidas de la planificación quedan plasmadas en un plan de acción | F34: 1 | K34: =+[2]GST!F34 -> 1 | N34: 0.3 | O34: 0.45
A35: =A34+1 -> 117 | B35: 13.2 | C35: PLANIFICACIÓN OPERATIVA | D35: 13.2.1 | E35: Se registran e informan las acciones o novedades en un pizarrón o avisadores. | F35: 1 | G35: Se planifican tareas en forma periodica (diarias, semanal, quincenal, mensual) en el sector, distribuyendo actividades y dejando establecidas las responsabilidades para cada uno. | K35: =+[2]GST!F35 -> 1 | N35: 0.4 | O35: 0.15
A36: =A35+1 -> 118 | B36: 13.2 | C36: =+C35 -> PLANIFICACIÓN OPERATIVA | D36: 13.2.2 | E36: Se realizan reuniones periódicas en el sector registrándose las decisiones en planes de acción | F36: 1 | K36: =+[2]GST!F36 -> 1 | N36: 0.6 | O36: 0.15
A37: =+A36+1 -> 119 | B37: 13.3 | C37: MANTENIMIENTO | D37: 13.3.1 | E37: Se planifica el mantenimiento preventivo de la infraestructura (desagües, portones, racks, techos) | F37: 1 | G37: La Distribuidora posee un plan de mantenimiento preventivo para equipamiento e Infraestructura | I37: Excelente plan | K37: =+[2]GST!F37 -> 1 | N37: 0.5 | O37: 0.4
A38: =+A37+1 -> 120 | B38: 13.3 | C38: MANTENIMIENTO | D38: 13.3.2 | E38: Se planifica el mantenimiento preventivo del grupo electrógeno | F38: N/A | I38: Excelente plan | K38: =+[2]GST!F38 -> N/A | N38: 0 | O38: 0.4
A39: =+A38+1 -> 121 | B39: 13.3 | C39: MANTENIMIENTO | D39: 13.3.3 | E39: Se planifica el mantenimiento preventivos del equipamiento logístico de manipuleo | F39: 1 | I39: Excelente plan | K39: =+[2]GST!F39 -> 1 | N39: 0.25 | O39: 0.4
A40: =+A39+1 -> 122 | B40: 13.3 | C40: MANTENIMIENTO | D40: 13.3.4 | E40: Se planifica el mantenimiento preventivo de flota propia o chequeo de tercerizada | F40: 1 | I40: Excelente plan | K40: =+[2]GST!F40 -> 1 | N40: 0.25 | O40: 0.4
B42: 14 | C42: INFORMACION Y COMUNICACIONES | F42: =SUMPRODUCT(F43:F46,N43:N46,O43:O46) -> 1 | K42: =SUMPRODUCT(K43:K46,N43:N46,O43:O46) -> 1 | N42: =+[1]MATRIZ!$G$21 -> 0.1 | O42: =+N42*F42 -> 0.1
A43: =+A40+1 -> 123 | B43: 14.1 | C43: INFORMACIÓN AL PERSONAL | D43: 14.1.1 | E43: La información en ella se encuentra actualizada | F43: 1 | G43: Existe cartelería en el depósito que permita dar información al personal sobre temas afines a la actividad logística (indicadores, gráficos, actividades, planes, avisos generales) | K43: =+[2]GST!F43 -> 1 | N43: 0.5 | O43: 0.7
A44: =A43+1 -> 124 | B44: 14.1 | C44: INFORMACIÓN AL PERSONAL | D44: 14.1.2 | E44: Existe cartelería informativa en el sector (novedades, indicadores, vacaciones, lanzamientos, informacion relacionada a la operación del depósito, seguridad) | F44: 1 | K44: =+[2]GST!F44 -> 1 | N44: 0.5 | O44: 0.7
A45: =A44+1 -> 125 | B45: 14.2 | C45: SUGERENCIAS DE MEJORA | D45: 14.2.1 | E45: Existe un registro de sugerencias realizadas por parte del personal | F45: 1 | G45: Está definida una metodología para recibir aportes y sugerencias del personal | K45: =+[2]GST!F45 -> 1 | N45: 0.7 | O45: 0.3
A46: =A45+1 -> 126 | B46: 14.2 | C46: INFORMACIÓN AL PERSONAL | D46: 14.2.2 | E46: Queda plasmado un plan de acción/respuesta en base a las sugerencias realizadas | F46: 1 | K46: =+[2]GST!F46 -> 1 | N46: 0.3 | O46: 0.3
B48: 15 | C48: FORMACION Y DESARROLLO | F48: =SUMPRODUCT(F49:F50,N49:N50,O49:O50) -> 1 | K48: =SUMPRODUCT(K49:K50,N49:N50,O49:O50) -> 0.6 | N48: =+[1]MATRIZ!$G$22 -> 0.1 | O48: =+N48*F48 -> 0.1
A49: =+A46+1 -> 127 | B49: 15.1 | C49: CAPACITACION | D49: 15.1.1 | E49: Realizan capacitaciones relacionadas a cambios o mejoras en los procesos o cuentan con un plan de capacitaciones especificas | F49: 1 | G49: Están definidos planes de capacitación al personal. | K49: =+[2]GST!F49 -> 0 | N49: 1 | O49: 0.4
A50: =A49+1 -> 128 | B50: 15.2 | C50: ROTACIÓN Y POLICOMPETENCIAS | D50: 15.2.1 | E50: Están definidas matrices de polivalencia o policompetencia | F50: 1 | G50: Existe un plan de formación al personal que incluya rotación del mismo y polivalencias/competencias del equipo | K50: =+[2]GST!F50 -> 1 | N50: 1 | O50: 0.6
B52: 16 | C52: MEDICION Y MEJORA | F52: =SUMPRODUCT(F53:F63,N53:N63,O53:O63) -> 0.86 | K52: =SUMPRODUCT(K53:K63,N53:N63,O53:O63) -> 1 | N52: =+[1]MATRIZ!$G$23 -> 0.3 | O52: =+N52*F52 -> 0.258
A53: =+A50+1 -> 129 | B53: 16.1 | C53: INDICADORES | D53: 16.1.1 | E53: Diferencia de inventario | F53: 1 | G53: Están definidos indicadores logísticos medidos en forma sistémica y con acciones toamdas de sus resultados | H53: CRITICO 8 | K53: =+[2]GST!F53 -> 1 | N53: 0.2 | O53: 0.6
A54: =A53+1 -> 130 | B54: 16.1 | C54: INDICADORES | D54: 16.1.2 | E54: Costo de transporte | F54: 1 | H54: CRITICO 8 | K54: =+[2]GST!F54 -> 1 | N54: 0.2 | O54: 0.6
A55: =A54+1 -> 131 | B55: 16.1 | C55: INDICADORES | D55: 16.1.3 | E55: Costo Operativo Depósito | F55: 1 | H55: CRITICO 8 | K55: =+[2]GST!F55 -> 1 | N55: 0.1 | O55: 0.6
A56: =A55+1 -> 132 | B56: 16.1 | C56: INDICADORES | D56: 16.1.4 | E56: Productividad global | F56: 1 | H56: CRITICO 8 | K56: =+[2]GST!F56 -> 1 | N56: 0.2 | O56: 0.6
A57: =A56+1 -> 133 | B57: 16.1 | C57: INDICADORES | D57: 16.1.5 | E57: Rechazos | F57: 1 | H57: CRITICO 8 | K57: =+[2]GST!F57 -> 1 | N57: 0.1 | O57: 0.6
A58: =A57+1 -> 134 | B58: 16.1 | C58: INDICADORES | D58: 16.1.6 | E58: Devoluciones | F58: 1 | H58: CRITICO 8 | K58: =+[2]GST!F58 -> 1 | N58: 0.1 | O58: 0.6
A59: =A58+1 -> 135 | B59: 16.1 | C59: INDICADORES | D59: 16.1.7 | E59: Informan mensualmente el tablero logístico a Arcor | F59: 0 | I59: Se envia cada dos meses. Pero red activa no lo recibe. | K59: =+[2]GST!F59 -> 1 | N59: 0.1 | O59: 0.6
A60: =A59+1 -> 136 | B60: 16.2 | C60: 5S | D60: 16.2.1 | E60: Está implementada cada una de las 5Ss, se mantiene en el tiempo y es base para mejoras edilicias, de procesos y de clima laboral | F60: 1 | G60: La Distribuidora tiene implementado el método de 5S | I60: Se observan auditorias de varios meses. | K60: =+[2]GST!F60 -> 1 | N60: 0.4 | O60: 0.4
A61: =A60+1 -> 137 | B61: 16.2 | C61: 5S | D61: 16.2.2 | E61: Se toman acciones sobre los resultados de las auditorias | F61: 0 | I61: No seevidencia el plan de acción por los puntos no cumplidos en la auditoria | K61: =+[2]GST!F61 -> 1 | N61: 0.2 | O61: 0.4
A62: =A61+1 -> 138 | B62: 16.2 | C62: 5S | D62: 16.2.3 | E62: Se auditan con frecuencia determinada (4ta S - AUDITORIA) los niveles de orden y limpieza alcanzados | F62: 1 | K62: =+[2]GST!F62 -> 1 | N62: 0.2 | O62: 0.4
A63: =A62+1 -> 139 | B63: 16.2 | C63: 5S | D63: 16.2.4 | E63: Posee implementadas las 3 primeras "S" (CLASIFICAR - ORDENAR - LIMPIAR) | F63: 1 | K63: =+[2]GST!F63 -> 1 | N63: 0.2 | O63: 0.4

Sheet IDP
Z1: 0
F2: EV25 | K2: AE 25 | Z2: 1
E3: =+B5 -> Area de interés : Integridad del Producto | F3: =+O8+O14+O33+O42+O49+O58 -> 0.97411111 | K3: =+K8*N8+K14*N14+K33*N33+K42*N42+K49*N49+K58*N58 -> 0.96021667 | N3: AREA en programa | O3: 0.3 | Z3: N/A
E4: Programa | F4: =+F3*O3 -> 0.29223333 | G4: =+F4+GST!F4+PLG!F4+IFT!F4 -> 0.95677083 | K4: =+K3*O3 -> 0.288065 | L4: =+K4+GST!K4+PLG!K4+IFT!K4 -> 0.959315 | Z4: NA - 1
B5: Area de interés : Integridad del Producto | N5: Ponderaciones en Area | Z5: NA - 0
B6: NRO. | C6: Buena Practica Logistica | E6: Componente | F6: EV25 | G6: Declaración de Buena Practica | H6: Critico | I6: Comentarios Evaluación | K6: AE 25 | N6: comp en el atributo | O6: Peso BPL
B8: 17 | C8: ABASTECIMIENTO Y RECEPCIÓN | F8: =SUMPRODUCT(F9:F12,N9:N12,O9:O12) -> 1 | K8: =SUMPRODUCT(K9:K12,N9:N12,O9:O12) -> 1 | N8: =+[1]MATRIZ!$G$24 -> 0.15 | O8: =+N8*F8 -> 0.15
A9: =+GST!A63+1 -> 140 | B9: 17.1 | C9: RECEPCION | D9: 17.1.1 | E9: Control general de la carga incluye vencimientos | F9: 1 | G9: Se realizan controles durante la recepción de productos restringiendo el ingresos de aquellos no aptos o en malas condiciones. | K9: =+[2]IDP!F9 -> 1 | N9: 0.5 | O9: 1
A10: =A9+1 -> 141 | B10: 17.1 | C10: RECEPCION | D10: 17.1.2 | E10: Control general de cantidad y estado de bultos recibidos | F10: 1 | K10: =+[2]IDP!F10 -> 1 | N10: 0.5 | O10: 1
A11: =A10+1 -> 142 | B11: 17.1 | C11: RECEPCION | D11: 17.1.3 | E11: Controlan y poseen un registro de la temperatura con la que arriba la carga de Helados | F11: N/A | K11: =+[2]IDP!F11 -> N/A | N11: 0 | O11: 1
A12: =A11+1 -> 143 | B12: 17.1 | C12: RECEPCION | D12: 17.1.4 | E12: Controlan y poseen un registro de la temperatura con la que arriba la carga de Refrigerados | F12: N/A | K12: =+[2]IDP!F12 -> N/A | N12: 0 | O12: 1
B14: 18 | C14: ALMACENAMIENTO Y MANIPULEO | F14: =SUMPRODUCT(F15:F31,N15:N31,O15:O31) -> 0.94444444 | K14: =SUMPRODUCT(K15:K31,N15:N31,O15:O31) -> 0.88886667 | N14: =+[1]MATRIZ!$G$25 -> 0.25 | O14: =+N14*F14 -> 0.23611111
A15: =+A12+1 -> 144 | B15: 18.1 | C15: ALMACENAMIENTO | D15: 18.1.1 | E15: Se identifican claramente los vencimientos. | F15: 1 | G15: Se garantiza la integridad del producto durante su almacenamiento. | K15: =+[2]IDP!F15 -> 1 | N15: 0.4 | O15: 0.16666667
A16: =A15+1 -> 145 | B16: 18.1 | C16: ALMACENAMIENTO | D16: 18.1.2 | E16: Los bultos almacenados se encuentran en buen estado de conservación, apilabilidad y separacion de la estiba contra la pared | F16: 1 | K16: =+[2]IDP!F16 -> 1 | N16: 0.4 | O16: 0.16666667
A17: =A16+1 -> 146 | B17: 18.1 | C17: ALMACENAMIENTO | D17: 18.1.3 | E17: Los productos que requieren acondicionamiento de temperatura (según Maestro de Articulos) se encuentran almacenados dentro de la cámara | F17: N/A | K17: =+[2]IDP!F17 -> N/A | N17: 0 | O17: 0.16666667
A18: =A17+1 -> 147 | B18: 18.1 | C18: ALMACENAMIENTO | D18: 18.1.4 | E18: No se encuentran pallets rotos, deteriorados, dañados almacenando mercadería | F18: 1 | K18: =+[2]IDP!F18 -> 1 | N18: 0.2 | O18: 0.16666667
A19: =+A18+1 -> 148 | B19: 18.2 | C19: CONTAMINACIÓN CRUZADA | D19: 18.2.1 | E19: En el depósito no se perciben olores extraños provenientes de estos químicos. | F19: 1 | G19: El depósito es apto para el almacenamiento seguro de producto sin riesgo de contaminaciones cruzadas con sustancias químicas o aromáticas. | K19: =+[2]IDP!F19 -> 1 | N19: 0.4 | O19: 0.27777778
A20: =A19+1 -> 149 | B20: 18.2 | C20: CONTAMINACIÓN CRUZADA | D20: 18.2.2 | E20: Los productos químicos se almacenan en lugares cerrados (armarios o gabinetes) | F20: 1 | K20: =+[2]IDP!F20 -> 1 | N20: 0.4 | O20: 0.27777778
A21: =A20+1 -> 150 | B21: 18.2 | C21: CONTAMINACIÓN CRUZADA | D21: 18.2.3 | E21: El lugar se encuentra identificado con cartelería | F21: 1 | K21: =+[2]IDP!F21 -> 0 | N21: 0.1 | O21: 0.27777778
A22: =A21+1 -> 151 | B22: 18.2 | C22: CONTAMINACIÓN CRUZADA | D22: 18.2.4 | E22: Se accede al lugar mediante uso de llave u otro elemento que garantice la inviolabilidad y no se evidencia concentración de aromas. | F22: 1 | K22: =+[2]IDP!F22 -> 1 | N22: 0.1 | O22: 0.27777778
A23: =+A22+1 -> 152 | B23: 18.3 | C23: CONTROL DE TEMPERATURAS | D23: 18.3.1 | E23: La temperatura de los productos secos no supera los 30°C (promedio máximo diario) y 35°C máximo y se garantiza mediante elemento de medición y registros | F23: 1 | G23: Se controlan las temperaturas de almacenamiento de los productos. | H23: CRITICO 9 | K23: =+[2]IDP!F23 -> 1 | N23: 0.5 | O23: 0.1111
A24: =A23+1 -> 153 | B24: 18.3 | C24: CONTROL DE TEMPERATURAS | D24: 18.3.2 | E24: Controlan y poseen un registro de la temperatura con la que arriba desde arcor | F24: 1 | H24: CRITICO 9 | K24: =+[2]IDP!F24 -> 1 | N24: 0.5 | O24: 0.1111
A25: =A24+1 -> 154 | B25: 18.3 | C25: CONTROL DE TEMPERATURAS | D25: 18.3.3 | E25: La temperatura de los productos congelados se encuentra en -22°C y se garantiza mediante registros | F25: N/A | K25: =+[2]IDP!F25 -> N/A | N25: 0 | O25: 0.1111
A26: =+A25+1 -> 155 | B26: 18.4 | C26: INSTRUMENTOS MEDICIÓN TEMPERATURA | D26: 18.4.1 | E26: Existe un registro de contrastación y/o calibración de termometros que garantice el correcto funcionamiento | F26: 0 | G26: Se mantiene un correcto mantenimiento de los instrumentos de medición de temperaturas y cuenta con un mecanismo de alerta. | I26: La calibración de la forma mostrada (rudimentaria, no profesional) deberia tener evidenciado regitros historicos. Se busca la implementación del proceso de contrastación. | K26: =+[2]IDP!F26 -> 0 | N26: 0.5 | O26: 0.0556
A27: =A26+1 -> 156 | B27: 18.4 | C27: INSTRUMENTOS MEDICIÓN TEMPERATURA | D27: 18.4.2 | E27: Los instrumentos de medición alertan ante variaciones inaceptables de temperatura | F27: 0 | K27: =+[2]IDP!F27 -> 0 | N27: 0.5 | O27: 0.0556
A28: =+A27+1 -> 157 | B28: 18.5 | C28: ROTACIÓN Y REPOSICIÓN | D28: 18.5.1 | E28: Se garantiza la inocuidad del producto evitando el contacto del envase primario o secundario con la madera u otro material contaminante | F28: 1 | G28: Se evita la contaminación del producto y garantiza su rotación en las tareas de reposición a zona de picking. | K28: =+[2]IDP!F28 -> 1 | N28: 0.5 | O28: 0.3333
A29: =A28+1 -> 158 | B29: 18.5 | C29: ROTACIÓN Y REPOSICIÓN | D29: 18.5.2 | E29: Se garantiza la correcta rotación FEFO por gestión visual o informática. | F29: 1 | K29: =+[2]IDP!F29 -> 1 | N29: 0.5 | O29: 0.3333
A30: =+A29+1 -> 159 | B30: 18.6 | C30: ILUMINACION | D30: 18.6.1 | E30: Las luminarias y aberturas de vidrio estan protegidas ante estallidos | F30: 1 | G30: Cuentan con protección aquellos elementos con materiales suceptibles de producir astillas ante su rotura. | K30: =+[2]IDP!F30 -> 0 | N30: 0.5 | O30: 0.0556
A31: =A30+1 -> 160 | B31: 18.6 | C31: ILUMINACION | D31: 18.6.2 | E31: Existen métodos de prevención de estallido y astillado en aberturas, etc | F31: 1 | K31: =+[2]IDP!F31 -> 1 | N31: 0.5 | O31: 0.0556
B33: 19 | C33: TRANSPORTE Y REPARTO | F33: =SUMPRODUCT(F34:F40,N34:N40,O34:O40) -> 1 | K33: =SUMPRODUCT(K34:K40,N34:N40,O34:O40) -> 1 | N33: =+[1]MATRIZ!$G$26 -> 0.25 | O33: =+N33*F33 -> 0.25
A34: =+A31+1 -> 161 | B34: 19.1 | C34: DESPACHO | D34: 19.1.1 | E34: Cuenta con una check-list para controlar las adecuadas condiciones de higiene, limpieza y acondicionamiento de la unidad contenedora del vehículo | F34: 1 | G34: Se preserva las condiciones del producto en las tareas de despacho y carga del transporte. | K34: =+[2]IDP!F34 -> 1 | N34: 0.4 | O34: 0.7
A35: =A34+1 -> 162 | B35: 19.1 | C35: DESPACHO | D35: 19.1.2 | E35: Se tienen en cuenta las condiciones de carga de los distintos productos (apilabilidad, peso, volumen, fragilidad, condiciones de temperatura, etc.) | F35: 1 | K35: =+[2]IDP!F35 -> 1 | N35: 0.6 | O35: 0.7
A36: =A35+1 -> 163 | B36: 19.1 | C36: DESPACHO | D36: 19.1.3 | E36: El distribuidor controla la temperatura al momento del despacho y durante la distribución en productos refrigerados. | F36: N/A | K36: =+[2]IDP!F36 -> N/A | N36: 0 | O36: 0.7
A37: =A36+1 -> 164 | B37: 19.2 | C37: DESPACHO LEGALES HIGIENE | D37: 19.2.1 | E37: Cuentan con un metodo/planilla de seguimiento de la documentación de los repartidores (Carnet de conducir y sanitario, tarjeta verde o azul, seguros, VTV o ITV, habilitaciones, etc) | F37: 1 | G37: Se tienen en cuenta los requisitos legales, de control e higiene para la flota de vehículos | K37: =+[2]IDP!F37 -> 1 | N37: 0.3 | O37: 0.3
A38: =A37+1 -> 165 | B38: 19.2 | C38: DESPACHO LEGALES HIGIENE | D38: 19.2.2 | E38: Los transportes son de uso exclusivo para alimentos y se encuentran habilitados por la autoridad compentente. | F38: 1 | K38: =+[2]IDP!F38 -> 1 | N38: 0.3 | O38: 0.3
A39: =A38+1 -> 166 | B39: 19.2 | C39: DESPACHO LEGALES HIGIENE | D39: 19.2.3 | E39: Los contenedores utilizados para el reparto conservan la integridad del producto. | F39: 1 | K39: =+[2]IDP!F39 -> 1 | N39: 0.4 | O39: 0.3
A40: =A39+1 -> 167 | B40: 19.2 | C40: DESPACHO LEGALES HIGIENE | D40: 19.2.4 | E40: El vehiculo que transporta helados cuenta con instrumento de medición de temperatura permitiendo su verificación en cabina. | F40: N/A | K40: =+[2]IDP!F40 -> N/A | N40: 0 | O40: 0.3
B42: 20 | C42: RETORNO Y/O DEVOLUCIONES | F42: =SUMPRODUCT(F43:F47,N43:N47,O43:O47) -> 1 | K42: =SUMPRODUCT(K43:K47,N43:N47,O43:O47) -> 1 | N42: =+[1]MATRIZ!$G$27 -> 0.15 | O42: =+N42*F42 -> 0.15
A43: =+A40+1 -> 168 | B43: 20.1 | C43: RECHAZOS | D43: 20.1.1 | E43: Está determinada la frecuencia de procesamiento de productos rechazados | F43: 1 | G43: Está definido el método de control y separación entre productos devueltos por el cliente que están aptos y no aptos. | H43: CRITICO 10 | K43: =+[2]IDP!F43 -> 1 | N43: 0.5 | O43: 0.4
A44: =A43+1 -> 169 | B44: 20.1 | C44: RECHAZOS | D44: 20.1.2 | E44: Los productos rechazados no aptos son rápidamente segregados de los productos aptos | F44: 1 | H44: CRITICO 10 | K44: =+[2]IDP!F44 -> 1 | N44: 0.5 | O44: 0.4
A45: =+A44+1 -> 170 | B45: 20.2 | C45: DEVOLUCIONES DE PRODUCTOS NO APTOS | D45: 20.2.1 | E45: El lugar se encuentra delimitado/identificado con cartelería de manera visual e inequívoca | F45: 1 | G45: Se cuenta con un lugar específico para el almacenamiento de productos para devolución a Arcor. | H45: CRITICO 11 | K45: =+[2]IDP!F45 -> 1 | N45: 0.5 | O45: 0.4
A46: =A45+1 -> 171 | B46: 20.2 | C46: =+C45 -> DEVOLUCIONES DE PRODUCTOS NO APTOS | D46: 20.2.2 | E46: El lugar para almacenamiento de estos productos se encuentra separado del producto apto | F46: 1 | H46: CRITICO 11 | K46: =+[2]IDP!F46 -> 1 | N46: 0.5 | O46: 0.4
A47: =+A46+1 -> 172 | B47: 20.3 | C47: RECALL Y TRAZABILIDAD | D47: 20.3.1 | E47: Cuenta con el Procedimiento Proceso de Recall | F47: 1 | K47: =+[2]IDP!F47 -> 1 | N47: 1 | O47: 0.2
B49: 21 | C49: LIMPIEZA | F49: =SUMPRODUCT(F50:F56,N50:N56,O50:O56) -> 1 | K49: =SUMPRODUCT(K50:K56,N50:N56,O50:O56) -> 0.88 | N49: =+[1]MATRIZ!$G$28 -> 0.1 | O49: =+N49*F49 -> 0.1
A50: =+A47+1 -> 173 | B50: 21.1 | C50: RESIDUOS | D50: 21.1.1 | E50: Dispone de un sector para almacenar los residuos que se mantiene despejado y ordenado compacto y fácilmente lavable. | F50: 1 | G50: El tratamiento de residuos en el depósito garantiza aislamiento e inocuidad. | I50: Cartón se desecha en el cesto interno, el resto, debe ser llevado al exterior por el personal | K50: =+[2]IDP!F50 -> N/A | N50: 0.4 | O50: 0.3
A51: =A50+1 -> 174 | B51: 21.2 | C51: =+C50 -> RESIDUOS | D51: 21.1.2 | E51: Cuenta con contenedores cerrados para depositar residuos. | F51: 1 | K51: =+[2]IDP!F51 -> 1 | N51: 0.6 | O51: 0.3
A52: =A51+1 -> 175 | B52: 21.2 | C52: LIMPIEZA | D52: 21.2.1 | E52: Las oficinas están construidas afuera o separados de las zonas donde se encuentran los productos. | F52: 1 | G52: Se cuenta con baños, vestuarios y comedor aptos para garantizar limpieza e inocuidad. | K52: =+[2]IDP!F52 -> 1 | N52: 0.4 | O52: 0.2
A53: =A52+1 -> 176 | B53: 21.2 | C53: =+C52 -> LIMPIEZA | D53: 21.2.2 | E53: Los baños, vestuarios y/o comedor están en buenas condiciones edilicias, no generan olores y/o contaminación cruzada. | F53: 1 | K53: =+[2]IDP!F53 -> 1 | N53: 0.3 | O53: 0.2
A54: =A53+1 -> 177 | B54: 21.2 | C54: =+C53 -> LIMPIEZA | D54: 21.2.3 | E54: Sector de carga y descarga en buenas condiciones de limpieza, cumple con el plan de limpieza | F54: 1 | K54: =+[2]IDP!F54 -> 1 | N54: 0.3 | O54: 0.2
A55: =A54+1 -> 178 | B55: 21.3 | C55: PLANES DE LIMPIEZA | D55: 21.3.1 | E55: Los productos químicos utilizados cuentan con los certificados de habilitación de la autoridad sanitaria correspondientes. | F55: 1 | G55: Existen planes de limpieza para el depósito y áreas comunes. | K55: =+[2]IDP!F55 -> 1 | N55: 0.3 | O55: 0.5
A56: =A55+1 -> 179 | B56: 21.3 | C56: =+C55 -> PLANES DE LIMPIEZA | D56: 21.3.2 | E56: Existe plan/seguimiento de limpieza documentado. | F56: 1 | K56: =+[2]IDP!F56 -> 1 | N56: 0.7 | O56: 0.5
B58: 22 | C58: MANEJO INTEGRADO DE PLAGAS | F58: =SUMPRODUCT(F59:F66,N59:N66,O59:O66) -> 0.88 | K58: =SUMPRODUCT(K59:K66,N59:N66,O59:O66) -> 1 | N58: =+[1]MATRIZ!$G$29 -> 0.1 | O58: =+N58*F58 -> 0.088
A59: =+A56+1 -> 180 | B59: 22.1 | C59: CONTROL DE PLAGAS | D59: 22.1.1 | E59: Llevan a cabo y existen registros del plan documentado de control de plaga para insectos terrestre, voladores, aves y roedores | F59: 1 | G59: Contrata una empresa especializada en el manejo intregal de plagas. | H59: CRITICO 12 | K59: =+[2]IDP!F59 -> 1 | N59: 0.2 | O59: 0.7
A60: =A59+1 -> 181 | B60: 22.1 | C60: CONTROL DE PLAGAS | D60: 22.1.2 | E60: La empresa cuenta con las habilitaciones vigentes requeridas para realizar todas las tareas del manejo integrado de plagas (incluye la aplicación de plaguicidas). Se deja registro de las aplicaciones (productos, sectores, objetivo,etc) | F60: 1 | H60: CRITICO 12 | K60: =+[2]IDP!F60 -> 1 | N60: 0.3 | O60: 0.7
A61: =A60+1 -> 182 | B61: 22.1 | C61: CONTROL DE PLAGAS | D61: 22.1.3 | E61: Los dispositivos de control de plagas están identificados, protegidos, fijos, razonablemente limpios, no obstruidos y en buenas condiciones para cumplir su función | F61: 1 | H61: CRITICO 12 | K61: =+[2]IDP!F61 -> 1 | N61: 0.3 | O61: 0.7
A62: =A61+1 -> 183 | B62: 22.1 | C62: CONTROL DE PLAGAS | D62: 22.1.4 | E62: Se realiza monitoreo y control de insectos voladores con trampas UV. | F62: 1 | H62: CRITICO 12 | I62: Mejorar ubicación | K62: =+[2]IDP!F62 -> 1 | N62: 0.1 | O62: 0.7
A63: =A62+1 -> 184 | B63: 22.1 | C63: CONTROL DE PLAGAS | D63: 22.1.5 | E63: Se realiza monitoreo y control de gorgojos / carcoma con feromonas | F63: 1 | H63: CRITICO 12 | I63: Se solicita implementar AEREAS para mejorar cobertura | K63: =+[2]IDP!F63 -> 1 | N63: 0.1 | O63: 0.7
A64: =A63+1 -> 185 | B64: 22.2 | C64: INFRAESTRUCTURA | D64: 22.2.1 | E64: El depósito cuenta con aberturas (puertas, portones y ventanas) que garantizan hermeticidad y se mantienen cerradas | F64: 0 | G64: Las condiciones edilicias del depósito y del predio externo garantizan la exclusión de plagas en la zona donde se encuentra el producto | I64: Mejorar cerramientos en algunos portones (parte inferior) | K64: =+[2]IDP!F64 -> 1 | N64: 0.4 | O64: 0.3
A65: =A64+1 -> 186 | B65: 22.2 | C65: INFRAESTRUCTURA | D65: 22.2.2 | E65: El exterior del depósito se encuentra despejado, con el pasto corto, sin acumulación de desechos. No hay equipos/estructuras/POP etc en desuso que favorezcan el anidamiento de plagas. (exterior e interior) | F65: 1 | K65: =+[2]IDP!F65 -> 1 | N65: 0.4 | O65: 0.3
A66: =A65+1 -> 187 | B66: 22.2 | C66: INFRAESTRUCTURA | D66: 22.2.3 | E66: No hay evidencia de presencia de mascotas dentro del predio (perros, gatos, etc.) | F66: 1 | K66: =+[2]IDP!F66 -> 1 | N66: 0.2 | O66: 0.3

Sheet Guia de Evidencias 2,0
A1: Area de Interes | B1: Atributo | C1: BPL | D1: Critico | E1: Declaración de Buena Practica | F1: Comentarios sobre evidencias | G1: # | H1: Componente
A2: IFT | B2: EMPLAZAMIENTO | C2: ENTORNO Y SEGURIDAD EXTERNA | E2: La localización geográfica donde se emplaza el depósito es segura en cuanto riesgos de seguridad patrimonial | F2: Inspección visual o entrevista al distribuidor o empleados | G2: 1.1.1 | H2: Predios cerrados, o Zonas industriales o logísticas | I2: =COUNTA(G2:G188) -> 187
G3: 1.1.2 | H3: Zona segura, con vigilancia de fuerzas públicas o privadas
G4: 1.1.3 | H4: Zona provista de iluminación pública o propia.
G5: 1.1.4 | H5: Existen cámaras de video externas pública o propia que cubran el ingreso principal o aledaños
A6: IFT | B6: EMPLAZAMIENTO | C6: ENTORNO - ACCESO | D6: X | E6: La localización geográfica donde se emplaza el depósito permite / autoriza acceso a vehículos, inclusive de gran porte | F6: Verificar ingreso o medir dimensiones del acceso y consultar restricciones municipales, constrastar con info de CRM | G6: 1.2.1 | H6: Capacidad de recibir unidades de alto tonelaje
A7: IFT | B7: EMPLAZAMIENTO | C7: PREDIO Y CIRCULACION | E7: Los accesos / calles internas del predio - o del entorno del depósito o vía pública - permiten la circulación segura de vehículos y otro equipamiento de maniobra | F7: Inspección visual y entrevista al distribuidor o empleados, validar que los vehiculos al momento de la carga/decarga no obstaculicen el trafico | G7: 1.3.2 | H7: Entorno sin problemas de congestionamiento de tráfico
G8: 1.3.3 | H8: Poseen alero o permiten el ingreso de la culata de los vehiculos para la carga/descarga en condiciones climáticas desfavorables
G9: 1.3.4 | H9: Fácil maniobrabilidad
G10: 1.3.5 | H10: Calles y accesos en buen estado, sin pendientes, consolidados o asfaltados
A11: IFT | B11: EDIFICACIÓN | C11: SEGURIDAD INTERNA | E11: La seguridad patrimonial se garantiza mediante infraestructura electrónica y/o actividades de vigilancia | F11: Inspección visual | G11: 2.1.1 | H11: Sistema de Alarmas en depósito y oficinas
G12: 2.1.2 | H12: Cámaras de Video en distintos sectores, con grabación y registro
A13: IFT | B13: EDIFICACIÓN | C13: LAY OUT - CAPACIDAD Y MODULACION | D13: X | E13: La capacidad del depósito es adecuada para el volumen de ventas , asegura el flujo físico continuo y permite mantener la cobertura de stock definida por Arcor. | F13: Analisis de stock vs capacidad. Documentos y entrevista con personal | G13: 2.2.1 | H13: Días hábiles promedio 6 meses de venta almacenados en la bodega (MinImo 21 dias)
A14: IFT | B14: EDIFICACIÓN | C14: TECHOS y PAREDES: ESTADO | E14: Las paredes y los techos del depósito se encuentran en buen estado y cuentan con elementos que garantizan las condiciones de conservación de los productos , definidos por Arcor. Temperatura 35°C (máxima promedio). | F14: Inspección Visual | G14: 2.3.1 | H14: Techo aislado y/o revestido, bien conservado
F15: Respecto de las paredes se validará que todas las paredes de la Distribuidora se encuentra revocadas o revestidas con material liso que no permita la acumulación de tierra o plagas | G15: 2.3.2 | H15: Paredes aisladas y/o revestidas, bien conservadas, que no permitan la acumulación de tierra o plagas
F16: Sino cuenta con extractores eolicos, pero se comprueba una temperatura adecuada en base a registros el componente se cumple. | G16: 2.3.3 | H16: Cuenta con extractores eólicos y/o ventilación forzada
F17: Inspección Visual. Verificar que no sean de mercurio | G17: 2.3.4 | H17: Posee termómetro en sector Secos, (no se permiten termometros de mercurio)
A18: IFT | B18: EDIFICACIÓN | C18: PISOS y JUNTAS: ESTADO | E18: Los pisos y juntas interiores del depósito son adecuados, en buen estado, garantizando y asegurando la operación. | F18: Inspección visual | G18: 2.4.1 | H18: Posee terminación alisada (a llana)
G19: 2.4.2 | H19: Las juntas poseen relleno (compuesto elástico ) y/o protección metálica que no genere golpes al transito de apiladoras o transpaletas
G20: 2.4.3 | H20: No posee desniveles entre los paños
G21: 2.4.4 | H21: El piso no desprende polvillo y/o no se visualizan grietas
A22: IFT | B22: EDIFICACIÓN | C22: ABERTURAS | E22: El depósito cuenta con al menos 2 portones e ingreso peatonal independiente | F22: Inspección visual | G22: 2.5.1 | H22: Cuenta con 2 o más portones
G23: 2.5.2 | H23: Posee ingreso de personal independiente de la carga
A24: IFT | B24: EDIFICACIÓN | C24: ILUMNACIÓN | E24: El depósito cuenta con lluminación adecuada para garantizar una operación logística eficaz y segura | F24: Inspección visual | G24: 2.6.1 | H24: Se encuentran por encima del nivel más alto de almacenamiento
G25: 2.6.2 | H25: Se encuentran centradas a lo largo de los pasillos
G26: 2.6.3 | H26: No se perciben sectores oscuros que afecten la operación
G27: 2.6.4 | H27: Se aprovecha la luz natural para la operación diurna sin aumento considerable de la temperatura en el interior
A28: IFT | B28: EDIFICACIÓN | C28: DESAGÛES | E28: El depósito cuenta con desagües que permiten evacuar el agua acumulada por lluvia | F28: Inspección visual y entrevista al distribuidor o empleados | G28: 2.7.1 | H28: Se ubican en el exterior del edificio
G29: 2.7.2 | H29: Se encuentran en buen estado (no se visualizan manchas de humedad), con rejillas de protección
A30: IFT | B30: ALMACENAMIENTO Y MANIPULEO | C30: EPPS y Extinguidores | D30: X | E30: Uso correcto de EPP (zapatos, cascos) y extintores en correctas condiciones | F30: Visual: verificar que se usen según reglamentación o evaluación de riesgos. Verificar si cuentan con stock para visitas. Ver area de guardado | G30: 3.1.1 | H30: Uso correcto de EPPS (zapatos o casco según reglamentación local vigente)
F31: Visual: verificar la ubicación de los extintores y su fecha de vencimiento | G31: 3.1.2 | H31: Extintores bien ubicados y en período de vencimiento
A32: IFT | B32: ALMACENAMIENTO Y MANIPULEO | C32: POP Y MOBILIARIO | E32: La infraestructura del depósito permite el almacenamiento de material promocional y de conservación en punto de venta (POP, mobiliario, freezers, etc) en un lugar aislado de la mercadería y seguro para la conservación y rotación de los mismos. | F32: Inspección visual y solicitar inventario en sistema o planilla | G32: 3.2.1 | H32: Los freezers y/o mobiliarios usados se encuentran en condiciones de higiene adecuadas
G33: 3.2.2 | H33: El material se encuentra inventariado el mueble pesado
G34: 3.2.3 | H34: El material se encuentra en un sector aislado de la mercadería
G35: 3.2.4 | H35: El material se encuentra identificado
A36: IFT | B36: ALMACENAMIENTO Y MANIPULEO | C36: CAMARA DE REFRIGERADOS | E36: La cámara de refrigerados cuenta con las condiciones necesarias para cubir las necesidades de almacenamiento y control de temperatura (entre 15°C a 25 °C) garantizando la conservación de la mercadería. | F36: Inspección visual, de registros, y análisis contra picos de temporada de mercadería que requiere cámara. Respecto de las paredes se validará que todas las paredes de la camara se encuentra con aislación termica. Los únicos termómetros que no se permiten tener colocados son los que contienen mercurio | G36: 3.3.1 | H36: Indice nivel de capacidad para productos refrigerados es menor que 1 respecto a su capacidad teorica real
G37: 3.3.2 | H37: Posee aislación térmica en paredes laterales, techo y acceso. Paredes aisladas y/o revestidas, bien conservadas, que no permitan la acumulación de tierra o plagas
G38: 3.3.3 | H38: Posee termómetro en Cámara de Refrigerados, (no se permiten termometros de mercurio)
A39: IFT | B39: ALMACENAMIENTO Y MANIPULEO | C39: CAMARA DE CONGELADOS | E39: La cámara de congelados cuenta con las condiciones necesarias para cubir las necesidades de almacenamiento y control de temperatura (-18 °C) garantizando la conservación de la mercadería. | F39: Inspección visual, de registros, y análisis contra picos de temporada de mercadería que requiere cámara.Verificar que la ubicación de la cámara a la zona de descarga no supere los 15min haciendo el recorrido caminando.Verifcar cuantos pallets recibe | G39: 3.3.1 | H39: Indice nivel de capacidad para productos congelados es menor que 1 respecto a su capacidad teorica real
G40: 3.3.2 | H40: Su ubicación permite carga / descarga directa desde el transporte
G41: 3.3.3 | H41: Posee termómetro
A42: IFT | B42: ALMACENAMIENTO Y MANIPULEO | C42: EQUIPAMIENTO DE MANIPULEO | D42: X | E42: El equipamiento de manipuleo (apiladora, zorras, carros) permite una operación logística que aprovecha la volumetría del depósito y el nivel de operación que la distribuidora necesita | F42: Verificación visual y de funcionalidad. Revisar cantidad y características tales como: alcance en altura, ancho de pasillos, pesos y cargas, tipo de propulsión, ruedas, y aspectos constructivos) | G42: 3.4.1 | H42: Cuenta con un equipo propio que le permite operar dentro del depósito y a su vez realizar la descarga de camiones
G43: 3.4.2 | H43: Cuenta con traspallets o "zorritas"
G44: 3.4.3 | H44: Cuenta con carros para Consolidados/Pedidos
G45: 3.4.4 | H45: El equipo para operar (dentro del depósito) es electrico
A46: IFT | B46: TRANSPORTE Y REPARTO | C46: VEHÍCULOS | E46: Los vehiculos son guardados en sectores aislados de la mercaderia | F46: Verificación visual del sector de guardado de vehículos | G46: 4.1.1 | H46: Se guardan en sectores seguros y aislados de la mercadería
A47: IFT | B47: INFORMACIÓN Y COMUNICACIONES | C47: INFORMÁTICA | E47: El equipamiento informático es accesible al personal de logística y permite un flujo de información que facilita la operación del depósito | F47: Verificación de equipamiento y accesibilidad | G47: 5.1.1 | H47: El personal de logística cuenta con acceso al sistema y/o con usuario propio
G48: 5.1.2 | H48: El personal de logística cuenta con acceso a correo electrónico y/o con cuenta propia
G49: 5.1.3 | H49: El personal de logística cuenta con equipamiento informático en su oficina
A50: IFT | B50: INFORMACIÓN Y COMUNICACIONES | C50: COMUNICACIONES | E50: El equipamiento de comunicaciones es accesible al personal de logística y permite coordinar actividades operativas con clientes o proveedores, internos o externos | F50: Verificación de equipamiento y accesibilidad | G50: 5.2.1 | H50: El personal de logística cuenta con algún dispositivo de comunicación que permita contactarse al interior y exterior de la distribuidora
A51: IFT | B51: INFORMACIÓN Y COMUNICACIONES | C51: ADQUISICIÓN DE DATOS | E51: El equipamiento de adquisición de datos es accesible al personal de logística y permite recopilar evidencias o anomalías en la operación | F51: Verificación de equipamiento y accesibilidad | G51: 5.3.1 | H51: El personal de logística cuenta cámaras digitales o escáneres, o "smartphones"
A52: PLG | B52: ABASTECIMIENTO Y RECEPCIÓN | C52: PLANIFICACIÓN DE COMPRAS | E52: Logística interviene en el proceso de planificación de necesidades de Compras. | F52: Distribucion de compra, en las primeras dos semanas no superior al 70% y no inferior al 60%; y las ultimas dos semana no superiror al 40% y no inferior al 30% de la compra total | G52: 6.1.1 | H52: Se informa/comunica las compras ( de volumen mayor a los normal o excepcionales)a Logística para que pueda planificar la operación de descarga y espacio necesario.(Registro , email, etc)
G53: 6.1.2 | H53: Realizan compras proporcionales y distribuidas dentro del mes
A54: PLG | B54: ABASTECIMIENTO Y RECEPCIÓN | C54: ACTIVACIÓN DEL ABASTECIMIENTO | E54: El proceso de activación del abastecimiento minimiza arribos imprevistos o demoras exageradas. | F54: Revisar correos recibidos por el logístico y cualquier contacto proactivo con Arcor desde el Informe Avanzado de Despacho (IAD), con el transporte para prever horarios de arribo, administrar demoras o adelantos, incluyendo la logística de "última milla" | G54: 6.2.1 | H54: Logística recibe el IAD
A55: PLG | B55: ABASTECIMIENTO Y RECEPCIÓN | C55: COORDINACIÓN DEL ABASTECIMIENTO | D55: X | E55: El proceso de coordinación del abastecimiento permite planificar recursos para la descarga. | F55: Revisar sectores de descarga, su ubicación y tamaño. | G55: 6.3.1 | H55: Previsión de espacio para el guardado/almacenamiento y/o reordenamiento de la mercadería
F56: Hablar con la gente para ver si se planifica. Quienes estan a cargo de la descarga, cuantas personas son. En caso de equipos alquilados para descarga, consultar sobre como aseguran la disponibilidad del mismo | G56: 6.3.2 | H56: Previsión de personas y equipo (Apilador/Autoelevador) necesarias para la descarga
F57: Se consulta al distribuidor cual es la ventana horaria para la recepcion | G57: 6.3.3 | H57: Cuenta con una ventana horaria de 8hs para recepción de mercadería
F58: Revisar sectores de descarga, su ubicación y tamaño. La zona debe estar bien identificada | G58: 6.3.4 | H58: Descarga en lugares definidos
A59: PLG | B59: ABASTECIMIENTO Y RECEPCIÓN | C59: RECEPCIÓN | E59: El proceso de control de recepción garantiza integridad de la mercadería y transmisión a Arcor de discrepancias | F59: Contar con el procedimiento documentado enviado por Arcor. El personal responsable de enviar los reclamos deben conocer su existencia y contenido. Los últimos reclamos enviados deben tener el formato establecido. | G59: 6.4.1 | H59: Las novedades se transmiten a Logística de Arcor por correo
A60: PLG | B60: ALMACENAMIENTO Y MANIPULEO | C60: ORGANIZACIÓN LAY OUT | E60: La Organización del lay out optimiza el guardado, rotación, reposición y preparado de mercadería | F60: planilla de calculo por medio de la cual analiza el ordenamietno del lay-out | G60: 7.1.1 | H60: Frecuencia definida documentada de revisión y/o modificación del lay-out (minimo cada 3 meses, maximo cada 6 meses)
G61: 7.1.2 | H61: Pasillos organizados por algun criterio logico (Negocio, ABC, familia, etc)
A62: PLG | B62: ALMACENAMIENTO Y MANIPULEO | C62: IDENTIFICACIÓN LAY OUT | E62: Se encuentran definidas e identificadas las zonas del lay out | F62: Revisión del lay out si las zonas estan delimitadas y demarcadas. Área de recepción 40 mts2 o 30 pallets en rack disponibles solo para descarga | G62: 7.2.1 | H62: Cada área del lay out se encuentra demarcada (Zonas pintadas en el piso)
G63: 7.2.2 | H63: Áreas principales identificadas (Recepción-Despacho-Devoluciones-Mercadería no comercializable-picking/almacenamiento)
G64: 7.2.3 | H64: No hay superposición entre áreas críticas (Despacho y Recepción por ej)
A65: PLG | B65: ALMACENAMIENTO Y MANIPULEO | C65: ROTACIÓN | E65: Se garantiza identificación y rotación de la mercadería (FEFO), en sectores de almacenamiento como de preparado | F65: Revisar que utilicen un correcto control de Stock. Verificar que las unidades en Picking son las proximas a vencer | G65: 7.3.1 | H65: Control de rotación y vencimientos junto al inventario rotativo y/o auditorias de 5S
F66: Evidenciar el registro (escrito o digital) con las unidades vencidas. Detallar cantidad y productos | G66: 7.3.2 | H66: Se lleva registro de las unidades vencidas
F67: Consultar metodo de informar. Debe contar con una gestion de stock instalada o colocar debajo del film stretch el vencimiento de los productos | G67: 7.3.2 | H67: Se informa sobre productos proximos a vencer a fin de tomar acciones
A68: PLG | B68: REPOSICIÓN E INVENTARIOS | C68: REPOSICIÓN DE MERCADERIA | E68: Está estandarizado el proceso de reposición de mercadería desde almacenamiento a picking. | F68: Revisar método y eventuales documentos o pantallas. Sugerido: Productos C todo el stock en picking, productos A y B 7 dias de venta y corte por pallet completo | G68: 8.1.1 | H68: Logística o personal designado supervisa por turno o por día con algún criterio (Por ej: Productos A)
G69: 8.1.2 | H69: Posiciones fijas de pickeo con capacidades definidas y/o frecuencias de reposición.
G70: 8.1.3 | H70: Se verifica el volumen de la posición de picking con una frecuencia determinada (minimo cada 3 meses, maximo cada 6 meses)
A71: PLG | B71: REPOSICIÓN E INVENTARIOS | C71: INVENTARIOS ROTATIVOS | D71: X | E71: Se realizan inventarios rotativos para asegurar confiabilidad del stock | F71: Revisar registros de inventarios, su frecuencia y las acciones que surjan | G71: 8.2.1 | H71: Se analizan causas al finalizar. Se registran acciones
G72: 8.2.2 | H72: Criterio definido de selección de items (ABC, rotativo,negocio, pasillo, etc.). Se toman y/o verifican fechas de vencimientos.
G73: 8.2.3 | H73: Se realizan con una frecuencia definida, mínima mensual
A74: PLG | B74: CONSOLIDADOS Y PEDIDOS | C74: TRANSMISIÓN DE PEDIDOS | E74: Existe una transmisión de pedidos en forma continua o con algún criterio | F74: Esquema de corte de pedidos (horario hasta el que los pedidos pueden ser procesados y entregados a 24hs) | G74: 9.1.1 | H74: Ventana horaria establecida para el corte de pedidos
G75: 9.1.2 | H75: Realiza analisis frecuentes relacionado a desvios en el corte de pedidos
A76: PLG | B76: CONSOLIDADOS Y PEDIDOS | C76: ARMADO Y ASIGNACIÓN DE CONSOLIDADOS Y/O PEDIDOS | E76: La generación de consolidados se hace por criterios definidos (cortes x $; cant Bultos; reparto, vendedor, etc) optimizando los recursos de la distribuidora | F76: Revisar listas de consolidados y definición de criterios El listado de preparacion debe coincidir con el ordenamiento fisico | G76: 9.2.1 | H76: El ordenamiento físico de los productos coincide con el consolidado
G77: 9.2.2 | H77: Se generan los consolidados aplicando criterios (Logísticos)de corte a partir de los pedidos ingresados-Solo para los que trabajan pedido por pedido
A78: PLG | B78: CONSOLIDADOS Y PEDIDOS | C78: CONTROL DE CONSOLIDADO | E78: Existe un control de los consolidados preparados que evita las diferencias entre la orden y la preparación fisica | F78: metodo de control de consolidado: el control de consolidado como tarea previo al armado de pedidos o bien un control durante el armado de pedidos (para que esto sea valido cuando se detecta un error debemos identificar la procedencia: revisar los pedidos armados donde el producto se solicita) | G78: 9.3.1 | H78: Se registran los errores y usuarios para mejorar el proceso
G79: 9.3.2 | H79: Se conserva en forma transitoria registro de control del consolidado
G80: 9.3.3 | H80: Existe un metodo de control de consolidado
A81: PLG | B81: CONSOLIDADOS Y PEDIDOS | C81: ARMADO DE PEDIDOS | E81: El control del armado evita las diferencias entre la orden y la preparación fisica | F81: Revision visual de los pedidos. | G81: 9.4.1 | H81: El pedido contiene identificación de bultos, cliente, zona de reparto, factura, o alguna identificación que facilite la carga
F82: Revisar documentacion. Verificar si utilizan control cruzado en mesa de armado. Consultar acciones destinadas a reducir los errores | G82: 9.4.2 | H82: Se registran los errores y usuarios para mejorar el proceso en el armado de pedido
F83: Revision visual de los pedidos. | G83: 9.4.3 | H83: El ordenamiento coincide con las facturas/pedido
A84: PLG | B84: TRANSPORTE Y REPARTO | C84: PEDIDOS LISTOS PARA CARGA | E84: Existe un criterio para la organización de los repartos previo a la carga de las unidades | F84: Revisar pedidos listos para despacho, estado, lugar, documentación | G84: 10.1.1 | H84: La carga en la zona de despacho contiene identificación zona/reparto/fletero.
A85: PLG | B85: TRANSPORTE Y REPARTO | C85: CARGA DE PEDIDOS | E85: Existe un criterio para la carga de las unidades de transporte que garantice el orden y control de la misma | F85: procedimiento de ruteo, que incluye el responsable y registro. Verificar mediante consultas como se carga la unidad | G85: 10.2.1 | H85: Pedido:La carga se realiza por LIFO de acuerdo al ruteo. Consolidado:La mercadería se carga organizada (manteniendo identificado cada negocio para su pickeo en el punto de venta
G86: 10.2.2 | H86: Cuenta con metodologia o registro de la hoja de ruta y el responsable del armado
G87: 10.2.3 | H87: Fletero controla y realiza la carga, si existe diferencia verifica con logística y realiza un registro de conformidad
A88: PLG | B88: TRANSPORTE Y REPARTO | C88: ENTREGA AL CLIENTE | E88: La entrega de mercadería (pedidos) al cliente garantiza la integridad de la carga contra el documento de transporte. Se solucionan discrepancias | F88: Revisar documentación. Hablar con fleteros o logísticos | G88: 10.3.1 | H88: Posee registro de reclamos del cliente (Planilla con registro de incidentes)
G89: 10.3.2 | H89: Cuenta con registro de pedidos reasignados
A90: PLG | B90: RETORNO Y/O DEVOLUCIONES | C90: RECHAZOS / DEVOLUCIONES | E90: El procesamiento de devoluciones de cualquier tipo, desde el cliente se encuentra estandarizado | F90: Revisar sector y proceso documentado. Debera presentar documentación con el registro de los rechazos / devoluciones y el motivo | G90: 11.1.1 | H90: Registro de motivos para posterior analisis y mejora del proceso
G91: 11.1.2 | H91: Mercadería ordenada con algún criterio y documentación de respaldo para validacion
G92: 11.1.3 | H92: Mercadería en el sector identificada y controlada
G93: 11.1.4 | H93: Lugar físico identificado y separado para almacenar rechazos/devoluciones
A94: GST | B94: ORGANIZACIÓN | C94: HERRAMIENTAS DE GESTION | E94: Cuenta con herramientas de le permita gestionar las operaciones del depósito (warehouse) , logistica de salida y reversa (Arcortruck) | F94: Revisión de la herramienta que posea el distribuidor (Módulo logístico América, Order Manager o Block).Para validar Arcortruck se considera si lo tiene funcionando o si lo tiene coordinado a la imprementación del mismo. Utilizar los módulos disponibles de los software para el depósito | G94: 12.1.1 | H94: Dispone de alguna herramienta informatica y la utiliza en el depósito
G95: 12.1.2 | H95: Cuenta con la aplicación de Arcortrukc para gestionar las entregas , rechazos y/o devoluciones de los clientes
G96: 12.1.3 | H96: Utiliza el Modulo Recepción
G97: 12.1.4 | H97: Utiliza el Modulo Inventario
G98: 12.1.5 | H98: Utiliza el Modulo Picking
G99: 12.1.6 | H99: Utiliza el Modulo Control de Consolidados
G100: 12.1.7 | H100: Utiliza el Modulo Armado de Pedidos
...

Sheet Plan de Acción
C3: PLAN DE ACCION - AUDITORIA RED ACTIVA 2.0
F4: PROGRESO | J4: FECHA DE REVISION
F5: VACIO | J5: 45302
F6: COMPLETO | G6: =+COUNTIF($I$12:$I$33,F6) -> 0 | H6: =IFERROR(G6/$G$9,0) -> 0
F7: EN CURSO | G7: =+COUNTIF($I$12:$I$33,F7) -> 0 | H7: =IFERROR(G7/$G$9,0) -> 0
F8: DEMORADO | G8: =+COUNTIF($I$12:$I$33,F8) -> 0 | H8: =IFERROR(G8/$G$9,0) -> 0
F9: TOTAL | G9: =+SUM(G6:G8) -> 0 | H9: =IFERROR(G9/$G$9,0) -> 0
B11: Atributo | C11: Buena Práctica Logística | D11: Componente | E11: Accion | F11: Responsable | G11: Fecha Inicio | H11: Fecha Fin | I11: Status | J11: Observaciones
I12: VACIO
I13: VACIO
I14: VACIO
I15: VACIO
I16: VACIO
I17: VACIO
I18: VACIO
I19: VACIO
I20: VACIO
I21: VACIO
I22: VACIO
I23: VACIO
... I33: VACIO

Sheet 5.0>>>

Sheet Dashboard Gral
B5: SEGURIDAD | D5: =+'Resumen - Se oculta 5,0'!I6 -> 0.35294118 | F5: =+'Resumen - Se oculta 5,0'!I5 -> 0.30436169
B6: CALIDAD | D6: =+'Resumen - Se oculta 5,0'!I18 -> 0.78378378
B7: INFRAESTRUCTURA LAYOUT Y FLOTA | D7: =+'Resumen - Se oculta 5,0'!I23 -> 0.66666667
B8: ORGANIZACIÓN Y CULTURA | D8: =+'Resumen - Se oculta 5,0'!I44 -> 0.28
B9: 5S | D9: =+'Resumen - Se oculta 5,0'!I54 -> 0.75
B10: PROCESOS LOGISTICOS | D10: =+'Resumen - Se oculta 5,0'!I58 -> 0.96153846 | F10: =+'Resumen - Se oculta 5,0'!I57 -> 0.2267094
B11: ESTANDARIZACION | D11: =+'Resumen - Se oculta 5,0'!I72 -> 0.91666667
B12: RUTINA E INDICADORES | D12: =+'Resumen - Se oculta 5,0'!I80 -> 0.44444444
B13: NIVEL DE SERVICIO Y TECNOLOGIA | D13: =+'Resumen - Se oculta 5,0'!I88 -> 0.22222222
B14: GESTION DE PROVEEDORES | D14: =+'Resumen - Se oculta 5,0'!I95 -> 0
B15: RELACIONES Y DESARROLLO DE LA COMUNIDAD | D15: =+'Resumen - Se oculta 5,0'!I98 -> 0
B16: GESTION AMBIENTAL | D16: =+'Resumen - Se oculta 5,0'!I101 -> 0 | J16: =Condicionales!$Q$6 -> Condición 1: No OK
B17: PLANEAMIENTO ESTRATEGICO | D17: =+'Resumen - Se oculta 5,0'!I105 -> 0.5 | F17: =+'Resumen - Se oculta 5,0'!I104 -> 0.045 | J17: =+Condicionales!$Q$10 -> Condición 2: OK
B18: GERENCIAMIENTO Y MEJORA CONTINUA | D18: =+'Resumen - Se oculta 5,0'!I108 -> 0.4 | J18: =+Condicionales!$Q$14 -> Condición 3: No Aplica
B22: 85 % >= Proactivo <= 100 %
B23: 70 % >= Activo < 85 %
B24: 50 % >= Reactivo < 70 %
B25: 25 % >= Inactivo < 50 %
B26: 0 % >= No Aplica < 25 %

Sheet Operacional
AO1: 0
F2: EV25 | G2: =+F4+Estandarización!F4+Mejora!F4 -> 0.57607109 | K2: AE 25 | M2: =+M6 -> EV24 | AO2: 1
E3: Nivel | F3: =+F8*$AB$8+F64*$AB$64+F111*$AB$111+F186*$AB$186+F212*$AB$212 -> 0.60872337 | G3: =+"Resultado acumulado "&" "&ROUND(G2*100,1)&"%" -> Resultado acumulado 57,6% | K3: =+K8*$AB$8+K64*$AB$64+K111*$AB$111+K186*$AB$186+K212*$AB$212 -> 0 | M3: =+M8*AB8+M64*AB64+M111*AB111+M186*AB186+M212*AB212 -> 0 | AA3: Nivel | AB3: =+AA8+AA64+AA111+AA186+AA212 -> 0.5 | AO3: N/A
E4: Programa | F4: =+F8*$AA$8+F64*$AA$64+F111*$AA$111+F186*$AA$186+F212*$AA$212 -> 0.30436169 | K4: =+K8*$AA$8+K64*$AA$64+K111*$AA$111+K186*$AA$186+K212*$AA$212 -> 0 | M4: =+M8*AA8+M64*AA64+M111*AA111+M186*AA186+M212*AA212 -> 0 | AO4: NA - 1
B5: Nivel OPERACIONAL | I5: =90000/13 -> 6923.0769 | AA5: Ponderaciones 2025 | AO5: NA - 0
B6: NRO. | C6: Buena Practica Logistica | E6: Componente | F6: EV25 | G6: Foco | H6: Zoom | I6: Comentarios Evaluación | K6: AE 25 | M6: EV24 | N6: Comentarios Evaluación 2024 | AA6: Comp
B8: 1 | C8: SEGURIDAD | F8: =IFERROR(SUMIF(F9:F63,1,F9:F63)/SUM(COUNTIF(F9:F63,1),COUNTIF(F9:F63,0)),0) -> 0.35294118 | K8: =IFERROR(SUMIF(K9:K63,1,K9:K63)/SUM(COUNTIF(K9:K63,1),COUNTIF(K9:K63,0)),0) -> 0 | M8: =IFERROR(SUMIF(M9:M63,1,M9:M63)/SUM(COUNTIF(M9:M63,1),COUNTIF(M9:M63,0)),0) -> 0 | AA8: 0.1 | AB8: =+AA8/$AB$3 -> 0.2
A9: 1 | B9: 1.1 | C9: Permisos y Habilitaciones | D9: 1.1.1 | E9: Habilitación de negocios Municipal (Verificar vencimiento) | F9: 1 | G9: MAHPI
A10: =A9+1 -> 2 | B10: 1.1 | C10: Permisos y Habilitaciones | D10: 1.1.2 | E10: Planos de edificio habilitados por autoridad competente | F10: 1
A11: =A10+1 -> 3 | B11: 1.1 | C11: Permisos y Habilitaciones | D11: 1.1.3 | E11: Planos eléctricos e instalaciones habilitados de acuerdo a normativa (firma de profesional habilitado) | F11: 1 | G11: MAHPI
A12: =A11+1 -> 4 | B12: 1.1 | C12: Permisos y Habilitaciones | D12: 1.1.4 | E12: Habilitación de bomberos. Solicitar estudio de Carga de Fuego en caso de no aplicar la habilitación (tema municipal) | F12: 1 | G12: MAHPI
A13: =A12+1 -> 5 | B13: 1.1 | C13: Permisos y Habilitaciones | D13: 1.1.5 | E13: Habilitación de Secretaría de energía (si aplica) | F13: N/A | G13: MAHPI
A14: =A13+1 -> 6 | B14: 1.2 | C14: Cumplimiento de Resoluciones H&S | D14: 1.2.1 | E14: Cuenta con un profesional de H&S y sus funciones son realización de las evaluaciones, planes de trabajo y capacitación | F14: 1 | G14: MAHPI
A15: =A14+1 -> 7 | B15: 1.2 | C15: Cumplimiento de Resoluciones H&S | D15: 1.2.2 | E15: El distribuidor cuenta con servicio Médico | F15: 0 | G15: MAHPI
A16: =A15+1 -> 8 | B16: 1.2 | C16: Cumplimiento de Resoluciones H&S | D16: 1.2.3 | E16: ART (Horas de servicio Médico, análisis médicos pre-ocupacionales y periódicos) | F16: 0 | G16: MAHPI
A17: =A16+1 -> 9 | B17: 1.2 | C17: Cumplimiento de Resoluciones H&S | D17: 1.2.4 | E17: ITVs de flota: el distribuidor evidencia documentación vigente, para vehículos propios y terceros | F17: 1 | G17: MAHPI
A18: =A17+1 -> 10 | B18: 1.2 | C18: Cumplimiento de Resoluciones H&S | D18: 1.2.5 | E18: Cuenta con permiso de manejo para autoelevadores y equipo de manipuleo. Hace uso de las protecciones de seguridad correspondientes. | F18: 0
A19: =A18+1 -> 11 | B19: 1.3 | C19: Evaluacion de Riesgo y Plan de Gestion | D19: 1.3.1 | E19: Están los principales riesgos identificados basandose en las 9 causas de accidentes consideradas de mayor significación por Grupo Arcor (ver PG-MHP02-9900-00001-2010) | F19: 0 | G19: MAHPI
A20: =A19+1 -> 12 | B20: 1.3 | C20: Evaluacion de Riesgo y Plan de Gestion | D20: 1.3.2 | E20: A cada riesgo identificado, se le asoció que EPPs o procedimiento se debe utilizar para reducir la exposición o disminuir su impacto | F20: 0
A21: =A20+1 -> 13 | B21: 1.4 | C21: Gestion de las Personas | D21: 1.4.1 | E21: Se cuenta con un Procedimiento documentado donde se detalla el proceso de reporte de accidentes | F21: 0
A22: =A21+1 -> 14 | B22: 1.4 | C22: Gestion de las Personas | D22: 1.4.2 | E22: Se clasifican y llevan estadísticas que permitan medir tendencias | F22: 0
A23: =A22+1 -> 15 | B23: 1.4 | C23: Gestion de las Personas | D23: 1.4.3 | E23: Indicador de accidentabilidad de transporte | F23: 0 | G23: MAHPI
A24: =A23+1 -> 16 | B24: 1.5 | C24: Gestion del Comportamiento | D24: 1.5.1 | E24: El personal logístico registra los comportamientos inseguros y toma acciones | F24: 0
A25: =A24+1 -> 17 | B25: 1.5 | C25: Gestion del Comportamiento | D25: 1.5.2 | E25: La lideranza del personal de logística tiene objetivos vinculados a la seguridad (monitoreo de seguridad, capacitaciones, etc.) | F25: 0
A26: =A25+1 -> 18 | B26: 1.5 | C26: Gestion del Comportamiento | D26: 1.5.3 | E26: Brinda capacitaciones sobre riesgo para la salud del personal con relación a temas como: obesidad, tabaquismo, consumo de alcohol y drogas, estrés excesivo, ludopatías, etc. y para asegurar un abordaje adecuado. | F26: 1 | H26: SUST
A27: =A26+1 -> 19 | B27: 1.5 | C27: Gestion del Comportamiento | D27: 1.5.4 | E27: Incorpora buenas prácticas e incentiva hábitos de vida saludables y de bienestar como: pausas activas, consumo de alimentos y bebidas beneficiosas para la salud, capacitaciones con nutricionistas y especialistas, etc. | F27: 1 | H27: SUST
A28: =A27+1 -> 20 | B28: 1.6 | C28: Capacitacion y Entrenamiento | D28: 1.6.1 | E28: Cuentan con un plan de capacitación y entrenamiento, en relación a los riesgos identificados por puesto y de los procedimientos de seguridad establecidos. | F28: =+GST!F49 -> 1 | G28: MAHPI
A29: =A28+1 -> 21 | B29: 1.6 | C29: Capacitacion y Entrenamiento | D29: 1.6.2 | E29: El establecimiento posee inducción de ingreso para visitas y contratistas | F29: 0
A30: =A29+1 -> 22 | B30: 1.6 | C30: Capacitacion y Entrenamiento | D30: 1.6.3 | E30: El establecimiento cuenta con un procedimiento para trabajos en altura y el personal se encuentra capacitado | F30: 0
A31: =A30+1 -> 23 | B31: 1.6 | C31: Capacitacion y Entrenamiento | D31: 1.6.4 | E31: El establecimiento cuenta con un procedimiento de trabajo en caliente y el personal esta capacitado | F31: 0 | G31: MAHPI
A32: =A31+1 -> 24 | B32: 1.7 | C32: Interaccion Hombre-Maquina | D32: 1.7.1 | E32: El establecimiento cuenta con medidas para prevenir la interacción de Hombre – Máquina | F32: 0
A33: =A32+1 -> 25 | B33: 1.7 | C33: Interaccion Hombre-Maquina | D33: 1.7.2 | E33: Cuentan con demarcaciones de circulación para evitar el riesgo de atropellos por vehículo. (Ej: Sendas Peatonales, Cruces Peligrosos) | F33: 1 | G33: MAHPI
A34: =A33+1 -> 26 | B34: 1.8 | C34: Instalaciones y Equipos | D34: 1.8.1 | E34: Se cuenta con un Check list para verificación de los RACKS y se toman acciones con personal calificado | F34: 0
A35: =A34+1 -> 27 | B35: 1.8 | C35: Instalaciones y Equipos | D35: 1.8.2 | E35: Zona de carga de combustible (si aplica). En caso de existir surtidores la misma está habilitada por la secretaría de energía, Cuenta con las auditorías y con un plan de acción sobre los desvíos. | F35: N/A | G35: MAHPI
A36: =A35+1 -> 28 | B36: 1.8 | C36: Instalaciones y Equipos | D36: 1.8.3 | E36: El establecimiento posee equipos para prevención y protección contra incendios y demuestra un control de estos. | F36: =+IFT!F42 -> 1
A37: =A36+1 -> 29 | B37: 1.8 | C37: Instalaciones y Equipos | D37: 1.8.4 | E37: Cuenta con Cámaras de Temperatura Controladas segregadas o separada del Edificio | F37: N/A | G37: MAHPI
A38: =A37+1 -> 30 | B38: 1.8 | C38: Instalaciones y Equipos | D38: 1.8.5 | E38: Están los cables eléctricos canalizados sin estar en contacto con la panelería. | F38: 0 | G38: MAHPI
A39: =A38+1 -> 31 | B39: 1.8 | C39: Instalaciones y Equipos | D39: 1.8.6 | E39: Cuenta con Sistema de Iluminacion colgante, separado de la paneleria en caso de aplicar. | F39: 0 | G39: MAHPI
A40: =A39+1 -> 32 | B40: 1.8 | C40: Instalaciones y Equipos | D40: 1.8.7 | E40: Evitar artefactos con balasto ( sistemas capacitivos) en contacto con la panelería. | F40: 0 | G40: MAHPI
A41: =A40+1 -> 33 | C41: Instalaciones y Equipos | D41: 1.8.8 | E41: La totalidad de las aberturas para pases debe estar sellada con material aislante no combustible. | F41: 0 | G41: MAHPI
A42: =A41+1 -> 34 | B42: 1.8 | C42: Instalaciones y Equipos | D42: 1.8.9 | E42: Los paneles están libres de golpes y roturas que exponga el material de relleno combustible ( poliuretano y/o tergopol). | F42: 0 | G42: MAHPI
A43: =A42+1 -> 35 | B43: 1.8 | C43: Instalaciones y Equipos | D43: 1.8.10 | E43: Todo elemento capaz de producir una fuente de ignición debe estar separado del panel ( baterías, tableros, motores, etc). | F43: 0 | G43: MAHPI
A44: =A43+1 -> 36 | B44: 1.8 | C44: Instalaciones y Equipos | D44: 1.8.11 | E44: No deben existir cañerías de gas natural o licuado en contacto con la cámara. | F44: 0 | G44: MAHPI
A45: =A44+1 -> 37 | B45: 1.8 | C45: Instalaciones y Equipos | D45: 1.8.12 | E45: Ejecutan Checklist de Seguridad diario: Checklist de preuso para equipo de manipuleo | F45: N/A | K45: N/A
A46: =A45+1 -> 38 | B46: 1.9 | C46: Conexiones Electricas y Tableros | D46: 1.9.1 | E46: Tableros y conexiones eléctricas en buen estado | F46: 1
A47: =A46+1 -> 39 | B47: 1.9 | C47: Conexiones Electricas y Tableros | D47: 1.9.2 | E47: Se realizan mediciones a puesta a tierra y continuidad. Res 911 | F47: 0 | G47: MAHPI
A48: =A47+1 -> 40 | B48: 1.9 | C48: Conexiones Electricas y Tableros | D48: 1.9.3 | E48: Se realizan termografías a tableros y cableados de potencia. | F48: 0 | G48: MAHPI
A49: =A48+1 -> 41 | B49: 1.9 | C49: Conexiones Electricas y Tableros | D49: 1.9.4 | E49: El distribuidor cuenta con protección para descargas atmosféricas. | F49: 0 | G49: MAHPI
A50: =A49+1 -> 42 | B50: 1.9 | C50: Conexiones Electricas y Tableros | D50: 1.9.5 | E50: Se cuenta con banco de capacitores para corrección de potencia. Si es correcto lo mismo están bajo rutina de mantenimiento. Están dentro de su periodo de vida útil. | F50: 0 | G50: MAHPI
A51: =A50+1 -> 43 | B51: 1.9 | C51: Conexiones Electricas y Tableros | D51: 1.9.6 | E51: Se encuentra el interior de los tableros electricos libres de materiales extranos, cerrados con candado, bajo llave para evitar contactato directo con elementos de tension. | F51: 0 | G51: MAHPI
A52: =A51+1 -> 44 | B52: 1.9 | C52: Conexiones Electricas y Tableros | D52: 1.9.7 | E52: Se encuentra la iluminaria separadas de los materiales almacenados, no hay riesgo que el material encendido caiga sobre materiales combustibles. | F52: 0 | G52: MAHPI
A53: =A52+1 -> 45 | B53: 1.9 | C53: Conexiones Electricas y Tableros | D53: 1.9.8 | E53: Existe una política de remplazo de iluminación por LED. El Distribuidor presenta estudio de medición de iluminación en ambiente laboral | F53: 0 | G53: MAHPI
A54: =A53+1 -> 46 | B54: 1.10 | C54: Emergencias | D54: 1.10.1 | E54: Se cuenta con una evaluación de los principales escenarios de una emergencia, tiene definido un plan con roles específicos y comunicado el plan de evacuación | F54: 0 | G54: MAHPI
A55: =A54+1 -> 47 | B55: 1.10 | C55: Emergencias | D55: 1.10.2 | E55: Se cuenta con una brigada de emergencia con un plan de capacitación adecuado | F55: 1 | G55: MAHPI
A56: =A55+1 -> 48 | B56: 1.10 | C56: Emergencias | D56: 1.10.3 | E56: Manejo de los sistemas de combate de incendio ( extintores, hidrantes, etc) | F56: =+IFT!F42 -> 1 | G56: MAHPI
A57: =A56+1 -> 49 | B57: 1.10 | C57: Emergencias | D57: 1.10.4 | E57: El personal de logística cuenta con un botiquín adecuado a las tareas en su depósito y flota. Se realizan chequeos periódicos que garanticen el estado de los botiquines | F57: 1
A58: =A57+1 -> 50 | B58: 1.10 | C58: Emergencias | D58: 1.10.5 | E58: ¿Existe stock suficiente de EPPs para empleados, visitas y contratistas? Se realizan chequeos periódicos que garanticen el estado de los EPPs | F58: =+IFT!F41 -> 1
A59: =A58+1 -> 51 | B59: 1.10 | C59: Emergencias | D59: 1.10.6 | E59: Se realizan capacitaciones específicas en temas de Salud y Seguridad, especialmente Primeros Auxilios, RCP y Protocolos de Emergencia (Incendios, derrumbes, inundaciones, apagones etc.), Manejo Seguro, etc. | F59: 0 | H59: SUST
A60: =A59+1 -> 52 | B60: 1.11 | C60: Riesgos Durante la Entrega | D60: 1.11.1 | E60: Ejecutan Check list de Seguridad del vehículo previo al despacho | F60: 1
A61: =A60+1 -> 53 | B61: 1.11 | C61: Riesgos Durante la Entrega | D61: 1.11.2 | E61: El establecimiento posee un plan de evaluación de riesgos en el momento de la entrega en sus PDVs (modalidad de entrega, matriz de riesgo, uso de EPPS) | F61: 0
A62: =A61+1 -> 54 | B62: 1.11 | C62: Riesgos Durante la Entrega | D62: 1.11.3 | E62: Los vehículos cuentan con un sistema monitoreo satelital; y se realiza un seguimiento de la forma de manejo, considerando aspectos como velocidad, maniobras bruscas, frenados de emergencia, conductor al volante, etc. | F62: 1 | H62: SUST
A63: =A62+1 -> 55 | B63: 1.11 | C63: Riesgos Durante la Entrega | D63: 1.11.4 | E63: Se cuenta con un análisis de las rutas peligrosas (ej. riesgos de robo, curvas peligrosas, etc.) | F63: 0
B64: 2 | C64: CALIDAD | F64: =IFERROR(SUMIF(F65:F110,1,F65:F110)/SUM(COUNTIF(F65:F110,1),COUNTIF(F65:F110,0)),0) -> 0.78378378 | K64: =IFERROR(SUMIF(K65:K110,1,K65:K110)/SUM(COUNTIF(K65:K110,1),COUNTIF(K65:K110,0)),0) -> 0 | M64: =IFERROR(SUMIF(M65:M110,1,M65:M110)/SUM(COUNTIF(M65:M110,1),COUNTIF(M65:M110,0)),0) -> 0 | AA64: 0.15 | AB64: =+AA64/$AB$3 -> 0.3
A65: =+A63+1 -> 56 | B65: 2.1 | C65: Control de Temperaturas | D65: 2.1.1 | E65: La temperatura de los productos secos no supera los 30°C (promedio máximo diario) y 35°C máximo y se garantiza mediante elemento de medición y registros | F65: =+IDP!F23 -> 1 | H65: QA
A66: =+A65+1 -> 57 | B66: 2.1 | C66: Control de Temperaturas | D66: 2.1.2 | E66: La temperatura de los productos refrigerados se encuentra comprendida entre 15°C y 25°C y se garantiza mediante registros | F66: N/A | G66: CRITICO.14 | H66: QA
A67: =+A66+1 -> 58 | B67: 2.1 | C67: Control de Temperaturas | D67: 2.1.3 | E67: La temperatura de los productos congelados se encuentra en -18°C y -22°C y se garantiza mediante registros | F67: =+IDP!F25 -> N/A | G67: CRITICO.14 | H67: QA
A68: =+A67+1 -> 59 | B68: 2.1 | C68: Control de Temperaturas | D68: 2.1.4 | E68: Existe un registro de contrastación y/o calibración de termómetros que garantice el correcto funcionamiento (verificar aplicación de estandar de calibración de termohigrómetros) | F68: =+IDP!F26 -> 0 | H68: QA
A69: =+A68+1 -> 60 | B69: 2.1 | C69: Control de Temperaturas | D69: 2.1.5 | E69: Los instrumentos de medición alertan ante variaciones inaceptables de temperatura o fallas en el equipo de refrigeración | F69: =+IDP!F27 -> 0 | H69: QA
A70: =+A69+1 -> 61 | B70: 2.2 | C70: Cuidado del producto durante las distintas etapas | D70: 2.2.1 | E70: Control general de la carga incluye vencimientos | F70: =+IDP!F9 -> 1 | H70: QA
A71: =+A70+1 -> 62 | B71: 2.2 | C71: Cuidado del producto durante las distintas etapas | D71: 2.2.2 | E71: Control general de cantidad y estado de bultos recibidos | F71: =+IDP!F10 -> 1 | H71: QA
A72: =+A71+1 -> 63 | B72: 2.2 | C72: Cuidado del producto durante las distintas etapas | D72: 2.2.3 | E72: Controlan y poseen un registro de la temperatura con la que arriba la carga de Helados. Se da aviso y se toman acciones en caso de desvios. | F72: =+IDP!F11 -> N/A | H72: QA
A73: =+A72+1 -> 64 | B73: 2.2 | C73: Cuidado del producto durante las distintas etapas | D73: 2.2.4 | E73: Controlan y poseen un registro de la temperatura con la que arriba la carga de Refrigerados. Se da aviso y se toman acciones en caso de desvios | F73: =+IDP!F12 -> N/A | H73: QA
A74: =+A73+1 -> 65 | B74: 2.2 | C74: Cuidado del producto durante las distintas etapas | D74: 2.2.5 | E74: Se identifican claramente los vencimientos | F74: =+IDP!F15 -> 1 | H74: QA
A75: =+A74+1 -> 66 | B75: 2.2 | C75: Cuidado del producto durante las distintas etapas | D75: 2.2.6 | E75: Los bultos almacenados se encuentran en buen estado de conservación, apilabilidad y separación de la estiba contra la pared | F75: =+IDP!F16 -> 1 | H75: QA
A76: =+A75+1 -> 67 | B76: 2.2 | C76: Cuidado del producto durante las distintas etapas | D76: 2.2.7 | E76: Los productos que requieren acondicionamiento de temperatura (según Maestro de Artículos) se encuentran almacenados dentro de la cámara desde el momento de la recepción | F76: =+IDP!F17 -> N/A | H76: QA
A77: =+A76+1 -> 68 | B77: 2.2 | C77: Cuidado del producto durante las distintas etapas | D77: 2.2.8 | E77: No se encuentran pallets rotos, deteriorados, dañados almacenando mercadería | F77: =+IDP!F18 -> 1 | H77: QA
A78: =+A77+1 -> 69 | B78: 2.2 | C78: Cuidado del producto durante las distintas etapas | D78: 2.2.9 | E78: Se garantiza la correcta rotación FEFO por gestión visual o informática | F78: =+IDP!F29 -> 1 | H78: QA
A79: =+A78+1 -> 70 | B79: 2.2 | C79: Cuidado del producto durante las distintas etapas | D79: 2.2.10 | E79: El depósito cuenta con aberturas (puertas, portones y ventanas) que garantizan hermeticidad y se mantienen cerradas | F79: =+IDP!F64 -> 0 | H79: QA
A80: =+A79+1 -> 71 | B80: 2.2 | C80: Cuidado del producto durante las distintas etapas | D80: 2.2.11 | E80: En el depósito no se perciben olores extraños provenientes de estos químicos. | F80: =+IDP!F19 -> 1 | H80: QA
A81: =+A80+1 -> 72 | B81: 2.2 | C81: Cuidado del producto durante las distintas etapas | D81: 2.2.12 | E81: Se tienen en cuenta y se controlan las condiciones de carga de los distintos productos: apilabilidad, peso, volumen, fragilidad, condiciones de temperatura (refrigerados o congelado según Maestro Artículos) | F81: 0 | H81: QA
A82: =+A81+1 -> 73 | B82: 2.2 | C82: Cuidado del producto durante las distintas etapas | D82: 2.2.13 | E82: El distribuidor controla la temperatura al momento del despacho y durante la distribución en productos refrigerados y congelados y deja registros de los controles | F82: 0 | H82: QA
A83: =+A82+1 -> 74 | B83: 2.2 | C83: Cuidado del producto durante las distintas etapas | D83: 2.2.14 | E83: Los contenedores utilizados para el reparto conservan la integridad del producto. | F83: =+IDP!F39 -> 1 | H83: QA
A84: =+A83+1 -> 75 | B84: 2.2 | C84: Cuidado del producto durante las distintas etapas | D84: 2.2.15 | E84: El vehículo que transporta helados cuenta con instrumento de medición de temperatura permitiendo su verificación en cabina | F84: =+IDP!F40 -> N/A | H84: QA
A85: =+A84+1 -> 76 | B85: 2.2 | C85: Cuidado del producto durante las distintas etapas | D85: 2.2.16 | E85: Cuenta con herramientas para registrar las roturas producidas en toda la cadena de suministro | F85: 0 | H85: QA
A86: =+A85+1 -> 77 | B86: 2.2 | C86: Cuidado del producto durante las distintas etapas | D86: 2.2.17 | E86: Está determinada la frecuencia de procesamiento de productos rechazados. Se almacenan según el maestro de articulos | F86: =+IDP!F43 -> 1 | G86: CRITICO.12 | H86: QA
A87: =+A86+1 -> 78 | B87: 2.2 | C87: Cuidado del producto durante las distintas etapas | D87: 2.2.18 | E87: Los productos rechazados no aptos son rápidamente segregados de los productos aptos | F87: =+IDP!F44 -> 1 | G87: CRITICO.12 | H87: QA
A88: =+A87+1 -> 79 | B88: 2.2 | C88: Cuidado del producto durante las distintas etapas | D88: 2.2.19 | E88: El sector de Productos no aptos se encuentra delimitado, confinado e identificado con cartelería de manera visual e inequívoca. Se debe evidenciar visualmente Oden y Limpieza del Area. | F88: =+IDP!F45 -> 1 | G88: CRITICO.11 | H88: QA
A89: =+A88+1 -> 80 | B89: 2.2 | C89: Cuidado del producto durante las distintas etapas | D89: 2.2.20 | E89: El lugar para almacenamiento de estos productos se encuentra separado del producto apto. El sector cuenta con Control de Plagas correspondiente. | F89: =+IDP!F46 -> 1 | G89: CRITICO.11 | H89: QA
A90: =+A89+1 -> 81 | B90: 2.2 | C90: Cuidado del producto durante las distintas etapas | D90: 2.2.21 | E90: Cuenta con el Procedimiento para la Devolución a Planta de Productos NO APTOS y cumple con el estándar sugerido. Además cuenta con un Registro detallado de los productos de devolución, a fin de llevar un Indicador de Gestión de Devoluciones | F90: 0 | H90: QA
A91: =+A90+1 -> 82 | B91: 2.2 | C91: Cuidado del producto durante las distintas etapas | D91: 2.2.22 | E91: Se cuenta con un procedimiento para evitar el decomiso, a través de donaciones, de productos que, siendo no aptos para la comercialización, son aptos para consumo (productos con vencimiento próximo, productos con empaques dañados, entre otros). | F91: 0 | H91: SUST
A92: =+A91+1 -> 83 | B92: 2.3 | C92: Limpieza | D92: 2.3.1 | E92: Las oficinas están construidas afuera o separados de las zonas donde se encuentran los productos | F92: =+IDP!F52 -> 1 | H92: QA
A93: =+A92+1 -> 84 | B93: 2.3 | C93: Limpieza | D93: 2.3.2 | E93: Los baños, vestuarios y/o comedor están en buenas condiciones edilicias, no generan olores y/o contaminación cruzada | F93: =+IDP!F53 -> 1 | H93: QA
A94: =+A93+1 -> 85 | B94: 2.3 | C94: Limpieza | D94: 2.3.3 | E94: Sector de carga y descarga en buenas condiciones de limpieza, cumple con el plan de limpieza | F94: =+IDP!F54 -> 1 | H94: QA
A95: =+A94+1 -> 86 | B95: 2.3 | C95: Limpieza | D95: 2.3.4 | E95: Dispone de un sector para almacenar los residuos que se mantiene despejado y ordenado compacto y fácilmente lavable | F95: =+IDP!F50 -> 1 | H95: QA
A96: =+A95+1 -> 87 | B96: 2.3 | C96: Limpieza | D96: 2.3.5 | E96: Cuenta con contenedores cerrados para depositar residuos | F96: =+IDP!F51 -> 1 | H96: QA
A97: =+A96+1 -> 88 | B97: 2.3 | C97: Limpieza | D97: 2.3.6 | E97: Existe plan/seguimiento de limpieza documentado | F97: =+IDP!F56 -> 1 | H97: QA
A98: =+A97+1 -> 89 | B98: 2.3 | C98: Limpieza | D98: 2.3.7 | E98: Los productos químicos se almacenan en lugares cerrados (armarios o gabinetes) bajo llave, rotulados correctamente. | F98: =+IDP!F20 -> 1 | H98: QA
A99: =+A98+1 -> 90 | B99: 2.3 | C99: Limpieza | D99: 2.3.8 | E99: Se garantiza la inocuidad del producto evitando el contacto del envase primario o secundario con la madera u otro material contaminante | F99: =+IDP!F28 -> 1 | H99: QA
A100: =+A99+1 -> 91 | B100: 2.3 | C100: Limpieza | D100: 2.3.9 | E100: No hay evidencia de presencia de mascotas (perros, gatos, etc.) y/o aves dentro del depósito. | F100: =+IDP!F66 -> 1 | H100: QA
A101: =+A100+1 -> 92 | B101: 2.3 | C101: Limpieza | D101: 2.3.10 | E101: Los productos químicos utilizados cuentan con los certificados de habilitación de la autoridad sanitaria correspondientes | F101: =+IDP!F55 -> 1 | H101: QA
...

Sheet Estandarización
AO1: 0
F2: EV25 | K2: AE 25 | M2: =+M6 -> EV24 | AO2: 1
E3: Nivel | F3: =+F8*$AB$8+F35*$AB$35+F67*$AB$67+F96*$AB$96+F108*$AB$108+F111*$AB$111+F115*$AB$115 -> 0.5667735 | K3: =+K8*$AB$8+K35*$AB$35+K67*$AB$67+K96*$AB$96+K108*$AB$108+K111*$AB$111+K115*$AB$115 -> 0 | M3: =+M8*$AB$8+M35*$AB$35+M67*$AB$67+M96*$AB$96+M108*$AB$108+M111*$AB$111+M115*$AB$115 -> 0 | AA3: Nivel | AB3: =+AA8+AA35+AA67+AA96+AA108+AA111+AA115 -> 0.4 | AO3: N/A
E4: Programa | F4: =+F8*$AA$8+F35*$AA$35+F67*$AA$67+F96*$AA$96+F108*$AA$108+F111*$AA$111+F115*$AA$115 -> 0.2267094 | K4: =+K8*$AA$8+K35*$AA$35+K67*$AA$67+K96*$AA$96+K108*$AA$108+K111*$AA$111+K115*$AA$115 -> 0 | M4: =+M8*$AA$8+M35*$AA$35+M67*$AA$67+M96*$AA$96+M108*$AA$108+M111*$AA$111+M115*$AA$115 -> 0 | AO4: NA - 1
B5: Nivel ESTANDARIZACIÓN | AA5: Ponderaciones 2025 | AO5: NA - 0
B6: NRO. | C6: Buena Practica Logistica | E6: Componente | F6: EV25 | G6: Foco | H6: Zoom | I6: Comentarios Evaluación | K6: AE25 | M6: EV24 | N6: Comentarios Evaluación 2024 | AA6: Comp | AB6: BPL
B8: 6 | C8: PROCESOS LOGISTICOS | F8: =IFERROR(SUMIF(F9:F34,1,F9:F34)/SUM(COUNTIF(F9:F34,1),COUNTIF(F9:F34,0)),0) -> 0.96153846 | K8: =IFERROR(SUMIF(K9:K34,1,K9:K34)/SUM(COUNTIF(K9:K34,1),COUNTIF(K9:K34,0)),0) -> 0 | M8: =IFERROR(SUMIF(M9:M34,1,M9:M34)/SUM(COUNTIF(M9:M34,1),COUNTIF(M9:M34,0)),0) -> 0 | AA8: 0.1 | AB8: =+AA8/$AB$3 -> 0.25
A9: =+Operacional!A217+1 -> 206 | B9: 6.1 | C9: Planificación de Compras | D9: 6.1.1 | E9: Se informa/comunica las compras (de volumen mayor a los normal o excepcionales) a Logística para que pueda planificar la operación de descarga y espacio necesario (Registro, email, etc.) | F9: =+PLG!F9 -> 1 | K9: N/A
A10: =A9+1 -> 207 | B10: 6.1 | C10: Planificación de Compras | D10: 6.1.2 | E10: Realizan compras proporcionales y distribuidas dentro del mes | F10: =+PLG!F10 -> 1 | K10: N/A
A11: =A10+1 -> 208 | B11: 6.2 | C11: Activación del Abastecimiento | D11: 6.2.1 | E11: Logística recibe el IAD (Informe Avanzado de Despacho) | F11: =+PLG!F11 -> 1
A12: =A11+1 -> 209 | B12: 6.3 | C12: Recepción | D12: 6.3.1 | E12: Las novedades se transmiten a CRM Logístico de ARCOR por correo, teniendo en cuenta el instructivo establecido para el envío de la documentación de respaldo | F12: =+PLG!F16 -> 1
A13: =A12+1 -> 210 | B13: 6.4 | C13: Organización del Layout | D13: 6.4.1 | E13: Frecuencia definida documentada de revisión y/o modificación del lay-out (mínimo cada 3 meses, máximo cada 6 meses) | F13: =+PLG!F19 -> 0
A14: =A13+1 -> 211 | B14: 6.4 | C14: Organización del Layout | D14: 6.4.2 | E14: Pasillos organizados por algún criterio lógico (Negocio, ABC, familia, etc.) | F14: =+PLG!F20 -> 1
A15: =A14+1 -> 212 | B15: 6.5 | C15: Identificación | D15: 6.5.1 | E15: Cada área del lay out se encuentra demarcada (Zonas pintadas en el piso) | F15: =+PLG!F21 -> 1
A16: =A15+1 -> 213 | B16: 6.5 | C16: Identificación | D16: 6.5.2 | E16: Áreas principales identificadas (Recepción-Despacho-Devoluciones-Mercadería no comercializable-picking/almacenamiento) | F16: =+PLG!F22 -> 1
A17: =A16+1 -> 214 | B17: 6.5 | C17: Identificación | D17: 6.5.3 | E17: No hay superposición entre áreas críticas (Despacho y Recepción por ej.) | F17: =+PLG!F23 -> 1
A18: =A17+1 -> 215 | B18: 6.5 | C18: Identificación | D18: 6.5.4 | E18: El lugar se encuentra identificado con cartelería | F18: 1
A19: =A18+1 -> 216 | B19: 6.6 | C19: Rotación | D19: 6.6.1 | E19: Control de rotación y vencimientos junto al inventario rotativo y/o auditorias de 5S | F19: =+PLG!F24 -> 1
A20: =A19+1 -> 217 | B20: 6.6 | C20: Rotación | D20: 6.6.2 | E20: Se lleva registro de las unidades vencidas | F20: =+PLG!F25 -> 1
A21: =A20+1 -> 218 | B21: 6.6 | C21: Rotación | D21: 6.6.3 | E21: Se informa sobre productos próximos a vencer a fin de tomar acciones | F21: =+PLG!F26 -> 1
A22: =A21+1 -> 219 | B22: 6.7 | C22: Inventarios Rotativos | D22: 6.7.1 | E22: Se analizan causas al finalizar. Se registran acciones | F22: =+PLG!F32 -> 1 | G22: CRITICO.7
A23: =A22+1 -> 220 | B23: 6.7 | C23: Inventarios Rotativos | D23: 6.7.2 | E23: Criterio definido de selección de ítems (ABC, rotativo, negocio, pasillo, etc.). Se toman y/o verifican fechas de vencimientos. | F23: =+PLG!F33 -> 1 | G23: CRITICO.7
A24: =A23+1 -> 221 | B24: 6.7 | C24: Inventarios Rotativos | D24: 6.7.3 | E24: Se realizan con una frecuencia definida, máxima trimestral, detallada en el Procedimiento de Gestión de Inventarios | F24: =+PLG!F34 -> 1 | G24: CRITICO.7
A25: =A24+1 -> 222 | B25: 6.8 | C25: Asignación de Consolidados | D25: 6.8.1 | E25: El ordenamiento físico de los productos coincide con el consolidado | F25: =+PLG!F39 -> 1
A26: =A25+1 -> 223 | B26: 6.9 | C26: Control de Consolidado | D26: 6.9.1 | E26: Existe un método de control de consolidado | F26: =+PLG!F43 -> 1
A27: =A26+1 -> 224 | B27: 6.9 | C27: Control de Consolidado | D27: 6.9.2 | E27: Se registran los errores y usuarios para mejorar el proceso de consolidado | F27: =+PLG!F41 -> 1
A28: =A27+1 -> 225 | B28: 6.10 | C28: Armado de Pedidos | D28: 6.10.1 | E28: El pedido contiene identificación de bultos, cliente, zona de reparto, factura, o alguna identificación que facilite la carga | F28: =+PLG!F44 -> 1
A29: =A28+1 -> 226 | B29: 6.10 | C29: Armado de Pedidos | D29: 6.10.2 | E29: El ordenamiento coincide con las facturas/pedido | F29: =+PLG!F46 -> 1
A30: =A29+1 -> 227 | B30: 6.10 | C30: Armado de Pedidos | D30: 6.10.3 | E30: Se registran los errores y usuarios para mejorar el proceso en el armado de pedido | F30: =+PLG!F45 -> 1
A31: =A30+1 -> 228 | B31: 6.11 | C31: Pedidos Listos Para Carga | D31: 6.11.1 | E31: La carga en la zona de despacho contiene identificación zona/reparto/fletero. | F31: =+PLG!F49 -> 1
A32: =A31+1 -> 229 | B32: 6.12 | C32: Carga de Pedidos | D32: 6.12.1 | E32: Pedido: La carga se realiza por LIFO de acuerdo al ruteo. Consolidado: La mercadería se carga organizada (manteniendo identificado cada negocio para su pickeo en el punto de venta | F32: =+PLG!F50 -> 1
A33: =A32+1 -> 230 | B33: 6.12 | C33: Carga de Pedidos | D33: 6.12.2 | E33: Cuenta con metodología o registro de la hoja de ruta y el responsable del armado | F33: =+PLG!F51 -> 1
A34: =A33+1 -> 231 | B34: 6.13 | C34: Rechazos / Devoluciones | D34: 6.13.1 | E34: Registro de motivos para posterior análisis y mejora del proceso de rechazos | F34: =+PLG!F57 -> 1
B35: 7 | C35: ESTANDARIZACION | F35: =IFERROR(SUMIF(F36:F66,1,F36:F66)/SUM(COUNTIF(F36:F66,1),COUNTIF(F36:F66,0)),0) -> 0.91666667 | K35: =IFERROR(SUMIF(K36:K66,1,K36:K66)/SUM(COUNTIF(K36:K66,1),COUNTIF(K36:K66,0)),0) -> 0 | M35: =IFERROR(SUMIF(M36:M66,1,M36:M66)/SUM(COUNTIF(M36:M66,1),COUNTIF(M36:M66,0)),0) -> 0 | AA35: 0.1 | AB35: =+AA35/$AB$3 -> 0.25
A36: =A34+1 -> 232 | B36: 7.1 | C36: Politica de Manejo de Vidrio | D36: 7.1.1 | E36: Cuenta con la Política de manejo de vidrio | F36: =+IDP!F30 -> 1
A37: =A36+1 -> 233 | B37: 7.2 | C37: Coordinación del Abastecimiento | D37: 7.2.1 | E37: Previsión de espacio para el guardado/almacenamiento y/o reordenamiento de la mercadería | F37: =+PLG!F12 -> 1 | G37: CRITICO.6
A38: =A37+1 -> 234 | B38: 7.2 | C38: Coordinación del Abastecimiento | D38: 7.2.2 | E38: Previsión de personas y equipo (Apilador/Autoelevador) necesarias para la descarga | F38: =+PLG!F13 -> 1 | G38: CRITICO.6
A39: =A38+1 -> 235 | B39: 7.2 | C39: Coordinación del Abastecimiento | D39: 7.2.3 | E39: Cuenta con una ventana horaria de 8hs para recepción de mercadería | F39: =+PLG!F14 -> 1 | G39: CRITICO.6
A40: =A39+1 -> 236 | B40: 7.2 | C40: Coordinación del Abastecimiento | D40: 7.2.4 | E40: El distribuidor tiene zonas definidas para la descarga | F40: =+PLG!F15 -> 1 | G40: CRITICO.6
A41: =A40+1 -> 237 | B41: 7.3 | C41: Despacho | D41: 7.3.1 | E41: Cuenta con una check-list para controlar las adecuadas condiciones de higiene, limpieza y acondicionamiento de la unidad contenedora del vehículo | F41: =+IDP!F34 -> 1
A42: =A41+1 -> 238 | B42: 7.3 | C42: Despacho | D42: 7.3.2 | E42: Cuenta con una estrategia de ruteo por sistema que minimiza los km recorridos y con ello el uso de combustible para la entrega de producto. | F42: 0 | H42: SUST
A43: =A42+1 -> 239 | B43: 7.4 | C43: Herramientas de Gestion | D43: 7.4.1 | E43: Dispone de alguna herramienta informática y la utiliza en las tareas/procesos del depósito | F43: =+GST!F9 -> N/A | G43: CRITICO.9
A44: =A43+1 -> 240 | B44: 7.4 | C44: Herramientas de Gestion | D44: 7.4.2 | E44: Cuenta con la aplicación de Arcortruck para gestionar las entregas, rechazos y/o devoluciones de los clientes | F44: =+GST!F10 -> N/A | K44: N/A
A45: =A44+1 -> 241 | B45: 7.4 | C45: Herramientas de Gestion | D45: 7.4.3 | E45: Utiliza el Módulo de Recepción | F45: =+GST!F11 -> N/A
A46: =A45+1 -> 242 | B46: 7.4 | C46: Herramientas de Gestion | D46: 7.4.4 | E46: Utiliza el Módulo Inventario | F46: =+GST!F12 -> N/A
A47: =A46+1 -> 243 | B47: 7.4 | C47: Herramientas de Gestion | D47: 7.4.5 | E47: Utiliza el Módulo de Picking | F47: =+GST!F13 -> N/A | G47: CRITICO.9
A48: =A47+1 -> 244 | B48: 7.4 | C48: Herramientas de Gestion | D48: 7.4.6 | E48: Utiliza el Módulo Control de Consolidados | F48: =+GST!F14 -> N/A | G48: CRITICO.9
A49: =A48+1 -> 245 | B49: 7.4 | C49: Herramientas de Gestion | D49: 7.4.7 | E49: Utiliza el Módulo Armado de Pedidos | F49: =+GST!F15 -> N/A | G49: CRITICO.9
A50: =A49+1 -> 246 | B50: 7.5 | C50: Rechazos / Devoluciones | D50: 7.5.1 | E50: Mercadería ordenada con algún criterio y documentación de respaldo para validación | F50: =+PLG!F58 -> 1
A51: =A50+1 -> 247 | B51: 7.5 | C51: Rechazos / Devoluciones | D51: 7.5.2 | E51: Mercadería en el sector correspondiente, identificada y controlada | F51: =+PLG!F59 -> 1
A52: =A51+1 -> 248 | B52: 7.5 | C52: Rechazos / Devoluciones | D52: 7.5.3 | E52: Lugar físico identificado y separado para almacenar rechazos/devoluciones | F52: =+PLG!F60 -> 1
A53: =A52+1 -> 249 | B53: 7.6 | C53: Reposición de Mercaderia | D53: 7.6.1 | E53: Se tiene una política de stock estándar definida por categoría de productos | F53: =+PLG!F31 -> 1
A54: =A53+1 -> 250 | B54: 7.7 | C54: Procesos Documentados | D54: 7.7.1 | E54: Cuenta con el Procedimiento Proceso de Recepción y Control de Mercadería | F54: =+GST!F20 -> 1 | G54: CRITICO.8
A55: =A54+1 -> 251 | B55: 7.7 | C55: Procesos Documentados | D55: 7.7.2 | E55: Cuenta con el Procedimiento Proceso de Reposición de Productos en Picking | F55: =+GST!F21 -> 1 | G55: CRITICO.8
A56: =A55+1 -> 252 | B56: 7.7 | C56: Procesos Documentados | D56: 7.7.3 | E56: Cuenta con el Procedimiento Proceso de Almacenamiento de Productos | F56: =+GST!F22 -> 1 | G56: CRITICO.8
A57: =A56+1 -> 253 | B57: 7.7 | C57: Procesos Documentados | D57: 7.7.4 | E57: Cuenta con el Procedimiento Proceso de Armado y Control de Consolidados | F57: =+GST!F23 -> 1 | G57: CRITICO.8
A58: =A57+1 -> 254 | B58: 7.7 | C58: Procesos Documentados | D58: 7.7.5 | E58: Cuenta con el Procedimiento Proceso de Armado de Pedidos | F58: =+GST!F24 -> 1 | G58: CRITICO.8
A59: =+A58+1 -> 255 | B59: 7.7 | C59: Procesos Documentados | D59: 7.7.6 | E59: Cuenta con el Procedimiento Proceso de Control de hojas de ruta y carga de pedidos | F59: =+GST!F25 -> 1 | G59: CRITICO.8
A60: =+A59+1 -> 256 | B60: 7.7 | C60: Procesos Documentados | D60: 7.7.7 | E60: Cuenta con el Procedimiento Proceso de Control de Inventario | F60: =+GST!F26 -> 1 | G60: CRITICO.8
A61: =+A60+1 -> 257 | B61: 7.7 | C61: Procesos Documentados | D61: 7.7.8 | E61: Cuenta con el Procedimiento Proceso de Control de Hojas de Ruta y Logística de Reversa | F61: =+GST!F27 -> 1
A62: =+A61+1 -> 258 | B62: 7.7 | C62: Procesos Documentados | D62: 7.7.9 | E62: El formato del procedimiento se ajusta al modelo estándar propuesto por Arcor | F62: =+GST!F29 -> 1
A63: =+A62+1 -> 259 | B63: 7.7 | C63: Procesos Documentados | D63: 7.7.10 | E63: Los responsables del proceso conocen el procedimiento, el mismo coincide con el proceso | F63: =+GST!F29 -> 1 | G63: CRITICO.8
A64: =+A63+1 -> 260 | B64: 7.7 | C64: Procesos Documentados | D64: 7.7.11 | E64: Cuenta con un procedimiento escrito estandarizado para la realización de la entrega contemplando: navegación, ejecución y cierre. Se incluye el proceso posterior a la ruta (cierre físico / financiero, documentación, rechazos, devoluciones, etc.) | F64: 1
A65: =+A64+1 -> 261 | B65: 7.7 | C65: Procesos Documentados | D65: 7.7.12 | E65: Se cuenta con un procedimiento escrito para identificar si el producto está en condiciones para ser entregado y el personal que realizan la entrega tiene conocimiento del mismo | F65: 0
A66: =+A65+1 -> 262 | B66: 7.7 | C66: Procesos Documentados | D66: 7.7.13 | E66: El procedimiento de auxilio en ruta está documentado y divulgado para la operación | F66: 1
B67: 8 | C67: RUTINA E INDICADORES | F67: =IFERROR(SUMIF(F68:F95,1,F68:F95)/SUM(COUNTIF(F68:F95,1),COUNTIF(F68:F95,0)),0) -> 0.44444444 | K67: =IFERROR(SUMIF(K68:K95,1,K68:K95)/SUM(COUNTIF(K68:K95,1),COUNTIF(K68:K95,0)),0) -> 0 | M67: =IFERROR(SUMIF(M68:M95,1,M68:M95)/SUM(COUNTIF(M68:M95,1),COUNTIF(M68:M95,0)),0) -> 0 | AA67: 0.075 | AB67: =+AA67/$AB$3 -> 0.1875
A68: =+A66+1 -> 263 | B68: 8.1 | C68: Indicadores - Financieros | D68: 8.1.1 | E68: Llevan un seguimiento de Diferencia de Inventario | F68: =+GST!F53 -> 1 | G68: CRITICO.10
A69: =+A68+1 -> 264 | B69: 8.1 | C69: Indicadores - Financieros | D69: 8.1.2 | E69: Llevan un seguimiento de Costo de Flete | F69: =+GST!F54 -> 1 | G69: CRITICO.10
A70: =+A69+1 -> 265 | B70: 8.1 | C70: Indicadores - Financieros | D70: 8.1.3 | E70: Llevan un seguimiento del Costo Operativo del Deposito | F70: =+GST!F55 -> 1 | G70: CRITICO.10
A71: =+A70+1 -> 266 | B71: 8.2 | C71: Indicadores - Procesos Logísticos | D71: 8.2.1 | E71: Llevan el indicador de Productividad Global | F71: =+GST!F56 -> 1 | G71: CRITICO.10
A72: =+A71+1 -> 267 | B72: 8.2 | C72: Indicadores - Procesos Logísticos | D72: 8.2.2 | E72: Llevan un Seguimiento de Rechazos (cantidad) | F72: =+GST!F57 -> 1 | G72: CRITICO.10 | H72: QA
A73: =+A72+1 -> 268 | B73: 8.2 | C73: Indicadores - Procesos Logísticos | D73: 8.2.3 | E73: Llevan un Seguimiento de Devoluciones | F73: =+GST!F58 -> 1 | G73: CRITICO.10 | H73: QA
A74: =+A73+1 -> 269 | B74: 8.2 | C74: Indicadores - Procesos Logísticos | D74: 8.2.4 | E74: Llevan un Seguimiento del indicador de Roturas, aperturado en Roturas dentro de depósito y en reparto | F74: 0 | H74: QA
A75: =+A74+1 -> 270 | B75: 8.2 | C75: Indicadores - Procesos Logísticos | D75: 8.2.5 | E75: Informan mensualmente el tablero al controller | F75: =+GST!F59 -> 0
A76: =+A75+1 -> 271 | B76: 8.2 | C76: Indicadores - Procesos Logísticos | D76: 8.2.6 | E76: Se mide y gestiona el tiempo en ruta y el tiempo en atención por PDV | F76: 0
A77: =+A76+1 -> 272 | B77: 8.2 | C77: Indicadores - Procesos Logísticos | D77: 8.2.8 | E77: Cuentan con un histórico de mantenimiento por unidad indicando KM (vehículos), tiempo de uso (equipos de elevación y manipulación), servicio realizado e importe abonado. | F77: 0
A78: =+A77+1 -> 273 | B78: 8.2 | C78: Indicadores - Procesos Logísticos | D78: 8.2.9 | E78: Se cuenta con un archivo consolidado donde se mide y gestiona por unidad, el consumo de combustible, neumáticos, multas/infracciones, tacómetro. | F78: 0 | H78: SUST
A79: =+A78+1 -> 274 | B79: 8.3 | C79: Indicadores - Sustentabilidad & MAHPI | D79: 8.3.1 | E79: Se cuenta con indicadores de accidentabilidad | F79: 0 | G79: MAHPI
A80: =+A79+1 -> 275 | B80: 8.3 | C80: Indicadores - Sustentabilidad & MAHPI | D80: 8.3.2 | E80: Se mide el consumo de energia y lleva un registro mensual (con apertura de cantidad de energía renovable en caso de que aplique). | F80: 0 | H80: SUST
A81: =+A80+1 -> 276 | B81: 8.3 | C81: Indicadores - Sustentabilidad & MAHPI | D81: 8.3.3 | E81: Se mide el volumen de residuos generados, considerando distintos tipos y materiales. | F81: 0 | H81: SUST
A82: =+A81+1 -> 277 | B82: 8.3 | C82: Indicadores - Sustentabilidad & MAHPI | D82: 8.3.4 | E82: Se cuenta con un inventario de emisiones de gases de efecto invernadero (GEI) que considera por lo menos los Alcances 1 y 2. | F82: 0 | H82: SUST
A83: =+A82+1 -> 278 | B83: 8.3 | C83: Indicadores - Sustentabilidad & MAHPI | D83: 8.3.5 | E83: Se mide la cantidad total de horas de capacitación general ofrecidas al personal. Se lleva un registro de temas / horas abordados. | F83: 0 | H83: SUST
A84: =+A83+1 -> 279 | B84: 8.3 | C84: Indicadores - Sustentabilidad & MAHPI | D84: 8.3.6 | E84: Se cuenta con indicadores que demuestren la proporción existente en términos de diversidad de género e inclusión social (discapacidad, mayores de 45 años, mujeres en situación de vulnerabilidad, jóvenes con primeras experiencias laborales, etc.). | F84: 0 | H84: SUST
A85: =+A84+1 -> 280 | B85: 8.3 | C85: Indicadores - Sustentabilidad & MAHPI | D85: 8.3.7 | E85: Se cuenta con un Procedimiento de donaciones que incluya un Registro de los Productos Entregados como Donación (alimentos, recursos financieros, horas de personal, equipamiento, etc.) | F85: 0 | H85: SUST
A86: =+A85+1 -> 281 | B86: 8.4 | C86: Información al Personal | D86: 8.4.1 | E86: La información en ella se encuentra actualizada | F86: =+GST!F43 -> 1
A87: =+A86+1 -> 282 | B87: 8.4 | C87: Información al Personal | D87: 8.4.2 | E87: Existe cartelería informativa en el sector (Ejemplo: novedades, indicadores, vacaciones, lanzamientos, información relacionada a la operación del depósito, seguridad, sustentabilidad, etc.) | F87: =+GST!F44 -> 1
A88: =+A87+1 -> 283 | B88: 8.4 | C88: Información al Personal | D88: 8.4.3 | E88: El distribuidor hace uso de diferentes soportes, formatos y canales de comunicación (Ejemplo: WhatsApp, intranet, mails, reuniones, etc.) para compartir información de interés para los colaboradores, y para influir positivamente con mensajes y contenidos dirigidos a su sensibilización, concientización y capacitación con relación a diferentes temáticas. | F88: 0 | H88: SUST
A89: =+A88+1 -> 284 | B89: 8.5 | C89: Planificación Operativa | D89: 8.5.1 | E89: Se registran e informan las acciones o novedades en un pizarrón o avisadores | F89: =+GST!F35 -> 1
A90: =+A89+1 -> 285 | B90: 8.5 | C90: Planificación Operativa | D90: 8.5.2 | E90: Se realiza reuniones en Depósito, una vez por semana. Se controla el presentismo y se siguen indicadores de desempeño (ej. Ausentismo, Accidentes, Productividad, 5S, Roturas) | F90: 0
A91: =+A90+1 -> 286 | B91: 8.6 | C91: Mantenimiento | D91: 8.6.1 | E91: Se planifica y se documenta/registra el mantenimiento preventivo de la infraestructura (desagües, portones, racks, techos) | F91: =+GST!F37 -> 1 | H91: QA
A92: =+A91+1 -> 287 | B92: 8.6 | C92: Mantenimiento | D92: 8.6.2 | E92: Se planifica y se documenta/registra el mantenimiento preventivo del grupo electrógeno | F92: =+GST!F38 -> N/A | H92: QA
A93: =+A92+1 -> 288 | B93: 8.6 | C93: Mantenimiento | D93: 8.6.3 | E93: Se planifica y se documenta/registra el mantenimiento preventivos del equipamiento logístico de manipuleo | F93: =+GST!F39 -> 1 | H93: QA
A94: =+A93+1 -> 289 | B94: 8.6 | C94: Mantenimiento | D94: 8.6.4 | E94: Se planifica y se documenta/registra el mantenimiento preventivo de flota propia o chequeo de tercerizada | F94: =+GST!F40 -> 1 | H94: QA
A95: =+A94+1 -> 290 | B95: 8.7 | C95: Rutina de reuniones y seguimiento de indicadores | D95: 8.7.1 | E95: Se realiza reuniones matinales de Entrega, una vez por semana. Se controla el presentismo y se siguen indicadores de desempeño (ej. Ausentismo, Accidentes, tiempo medio de liberación de camiones, Rechazo, Reclamos, Roturas) | F95: 0
B96: 9 | C96: NIVEL DE SERVICIO Y TECNOLOGIA | F96: =IFERROR(SUMIF(F97:F107,1,F97:F107)/SUM(COUNTIF(F97:F107,1),COUNTIF(F97:F107,0)),0) -> 0.22222222 | K96: =IFERROR(SUMIF(K97:K107,1,K97:K107)/SUM(COUNTIF(K97:K107,1),COUNTIF(K97:K107,0)),0) -> 0 | M96: =IFERROR(SUMIF(M97:M107,1,M97:M107)/SUM(COUNTIF(M97:M107,1),COUNTIF(M97:M107,0)),0) -> 0 | AA96: 0.025 | AB96: =+AA96/$AB$3 -> 0.0625
A97: =+A95+1 -> 291 | B97: 9.1 | C97: Información al Cliente | D97: 9.1.1 | E97: Existe una herramienta digital que muestre que el pedido está en camino. | F97: N/A | K97: N/A
A98: =+A97+1 -> 292 | B98: 9.1 | C98: Información al Cliente | D98: 9.1.2 | E98: La herramienta debe notificar al PDV información relevante sobre el pedido (productos, cantidades e importe de la factura) | F98: N/A | K98: N/A
A99: =+A98+1 -> 293 | B99: 9.2 | C99: Ventanas Horarias | D99: 9.2.1 | E99: Verificar si el Distribuidor es capaz de acordar a nivel PDV una ventana horaria de entrega | F99: 0
A100: =+A99+1 -> 294 | B100: 9.2 | C100: Ventanas Horarias | D100: 9.2.2 | E100: Verificar si las ventanas horarias son posibles de cumplir en base al tamaño de las entregas y a las restricciones del modelo actual de entrega | F100: 0
A101: =+A100+1 -> 295 | B101: 9.2 | C101: Ventanas Horarias | D101: 9.2.3 | E101: Si la información de la ventana horaria surge de un sistema y está disponible para el equipo de ruteo. | F101: 0
...

Sheet Mejora
AO1: 0
F2: EV25 | K2: AE 25 | M2: =+M6 -> EV24 | AO2: 1
E3: Nivel | F3: =+F8*AB8+F19*AB19 -> 0.45 | K3: =+K8*AB8+K19*AB19 -> 0 | M3: =+M8*AB8+M19*AB19 -> 0 | AA3: Nivel | AB3: =+AA8+AA19 -> 0.1 | AO3: N/A
E4: Programa | F4: =+F8*AA8+F19*AA19 -> 0.045 | K4: =+K8*AA8+K19*AA19 -> 0 | M4: =+M8*AA8+M19*AA19 -> 0 | AO4: NA - 1
B5: Nivel MEJORA CONTINUA | AA5: Ponderaciones 2025 | AO5: NA - 0
B6: NRO. | C6: Buena Practica Logistica | E6: Componente | F6: EV25 | G6: Foco | H6: Zoom | I6: Comentarios Evaluación | K6: AE25 | M6: EV24 | N6: Comentarios Evaluación 2024 | AA6: Comp | AB6: BPL
B8: 13 | C8: PLANEAMIENTO ESTRATEGICO | F8: =IFERROR(SUMIF(F9:F18,1,F9:F18)/SUM(COUNTIF(F9:F18,1),COUNTIF(F9:F18,0)),0) -> 0.5 | K8: =IFERROR(SUMIF(K9:K18,1,K9:K18)/SUM(COUNTIF(K9:K18,1),COUNTIF(K9:K18,0)),0) -> 0 | M8: =IFERROR(SUMIF(M9:M18,1,M9:M18)/SUM(COUNTIF(M9:M18,1),COUNTIF(M9:M18,0)),0) -> 0 | AA8: 0.05 | AB8: =+AA8/$AB$3 -> 0.5
A9: =+Estandarización!A121+1 -> 313 | B9: 13.1 | C9: Planificación Estratégica | D9: 13.1.1 | E9: La Distribuidora cuenta con un plan donde se establecen objetivos y metas que permiten identificar y medir sus compromisos de sustentabilidad | F9: 0 | H9: SUST
A10: =A9+1 -> 314 | B10: 13.1 | C10: Planificación Estratégica | D10: 13.1.2 | E10: Se cuenta con un plan de reemplazo de flota considerando opciones de nuevas tecnologías y necesidades de dimensionamiento. | F10: 0 | H10: SUST
A11: =A10+1 -> 315 | B11: 13.1 | C11: Planificación Estratégica | D11: 13.1.3 | E11: La distribuidora tiene un plan de largo plazo para dimensionar su estructura | F11: 0
A12: =A11+1 -> 316 | B12: 13.1 | C12: Planificación Estratégica | D12: 13.1.4 | E12: La estrategia comercial-logística de crecimiento está en plena implementación y se miden los avances (Plan de Crecimiento de 3 Años de ARCOR) | F12: 0
A13: =A12+1 -> 317 | B13: 13.1 | C13: Planificación Estratégica | D13: 13.1.5 | E13: Se realiza un análisis de FODA anual y con definición de estrategias | F13: 1
A14: =A13+1 -> 318 | B14: 13.1 | C14: Planificación Estratégica | D14: 13.1.6 | E14: El presupuesto se construye considerando mejoras en la productividad y eficiencia de los KPIs | F14: 1
A15: =A14+1 -> 319 | B15: 13.2 | C15: Planificación Estratégica | D15: 13.2.1 | E15: Logistica participa de reuniones con Ventas y Administración, en las cuales se definen objetivos anuales y/o mensuales | F15: =+GST!F32 -> 1
A16: =A15+1 -> 320 | B16: 13.2 | C16: Planificación Táctica | D16: 13.2.2 | E16: Se realiza el seguimiento de la planificación en forma periódica (semanal, quincenal o mensual) evaluando el alcance de los resultados. | F16: =+GST!F33 -> 1
A17: =A16+1 -> 321 | B17: 13.2 | C17: Planificación Táctica | D17: 13.2.3 | E17: Las acciones surgidas de la planificación quedan plasmadas en un plan de acción | F17: =+GST!F34 -> 1
A18: =A17+1 -> 322 | B18: 13.2 | C18: Planificación Táctica | D18: 13.2.4 | E18: Se han establecido mecanismos, como reuniones, comités y/o comunicaciones específicas, para informar e involucrar a líderes y equipos de distintas áreas de la Distribuidora en la gestión de los desafíos relacionados con la sustentabilidad. | F18: 0
B19: 14 | C19: GERENCIAMIENTO Y MEJORA CONTINUA | F19: =IFERROR(SUMIF(F20:F24,1,F20:F24)/SUM(COUNTIF(F20:F24,1),COUNTIF(F20:F24,0)),0) -> 0.4 | K19: =IFERROR(SUMIF(K20:K24,1,K20:K24)/SUM(COUNTIF(K20:K24,1),COUNTIF(K20:K24,0)),0) -> 0 | M19: =IFERROR(SUMIF(M20:M24,1,M20:M24)/SUM(COUNTIF(M20:M24,1),COUNTIF(M20:M24,0)),0) -> 0 | AA19: 0.05 | AB19: =+AA19/$AB$3 -> 0.5
A20: =A18+1 -> 323 | B20: 14.1 | C20: Introducción a la Mejora Continúa | D20: 14.1.1 | E20: Se realiza reuniones de equipo nivel gerencial, se discuten indicadores versus plan y se buscan mejoras (incluyendo seguimiento de indicadores de sustentabilidad). | F20: 0
A21: =A20+1 -> 324 | B21: 14.1 | C21: Introducción a la Mejora Continúa | D21: 14.1.2 | E21: Se realiza periódicamente un plan de ruteo mas optimo en base a la planificación territorial | F21: 0
A22: =A21+1 -> 325 | B22: 14.1 | C22: Introducción a la Mejora Continúa | D22: 14.1.3 | E22: Se mide la cantidad de PDVs abiertos en área de influencia. Se categorizan en atendido regularmente, no comprador o punto de venta potencial y se establecen acciones para captarlos | F22: 0
A23: =A22+1 -> 326 | B23: 14.2 | C23: Sugerencias de Mejora | D23: 14.2.1 | E23: Existe un registro de sugerencias realizadas por parte del personal. | F23: =+GST!F45 -> 1 | H23: SUST
A24: =A23+1 -> 327 | B24: 14.2 | C24: Sugerencias de Mejora | D24: 14.2.2 | E24: Queda plasmado un plan de acción/respuesta en base a las sugerencias realizadas | F24: =+GST!F46 -> 1 | H24: SUST

Sheet Condicionales
B2: # Critico | C2: # Critico | D2: Descripción | F2: # componentes Criticas | L2: Evaluación del cumplimiento
F3: Totales | G3: OK
B5: 1 | C5: CRITICO.1 | D5: LAY OUT - CAPACIDAD Y MODULACIÓN | F5: =COUNTIF(Operacional!G:G,Condicionales!C5) -> 2 | G5: =SUMIF(Operacional!G:G,Condicionales!C5,Operacional!F:F) -> 2 | H5: =+G5/F5 -> 1 | I5: =+H5 -> 1 | L5: Condición 1: Tolerancia sobre el total de componentes
B6: =+B5+1 -> 2 | C6: CRITICO.2 | D6: ENTORNO - ACCESO | F6: =COUNTIF(Operacional!G:G,Condicionales!C6) -> 1 | G6: =SUMIF(Operacional!G:G,Condicionales!C6,Operacional!F:F) -> 1 | H6: =+G6/F6 -> 1 | I6: =+H6 -> 1 | M6: Total | N6: =+F21 -> 50 | O6: 0.1 | Q6: =+"Condición 1: "&Q7 -> Condición 1: No OK
B7: =+B6+1 -> 3 | C7: CRITICO.3 | D7: CAMARA DE REFRIGERADOS | F7: =COUNTIF(Operacional!G:G,Condicionales!C7) -> 3 | G7: =SUMIF(Operacional!G:G,Condicionales!C7,Operacional!F:F) -> 0 | H7: =+G7/F7 -> 0 | I7: =+H7 -> 0 | M7: Cumplidas | N7: =+G21 -> 38 | Q7: =IF(N7>=N6*(1-O6),"OK","No OK") -> No OK
B8: =+B7+1 -> 4 | C8: CRITICO.4 | D8: CAMARA DE CONGELADOS | F8: =COUNTIF(Operacional!G:G,Condicionales!C8) -> 3 | G8: =SUMIF(Operacional!G:G,Condicionales!C8,Operacional!F:F) -> 0 | H8: =+G8/F8 -> 0 | I8: =+H8 -> 0
B9: =+B8+1 -> 5 | C9: CRITICO.5 | D9: EQUIPAMIENTO DE MANIPULEO | F9: =COUNTIF(Operacional!G:G,Condicionales!C9) -> 3 | G9: =SUMIF(Operacional!G:G,Condicionales!C9,Operacional!F:F) -> 3 | H9: =+G9/F9 -> 1 | I9: =+H9 -> 1 | L9: Condición 2: 100% de cumplimiento de las Criticas de calidad
B10: =+B9+1 -> 6 | C10: CRITICO.6 | D10: COORDINACIÓN DEL ABASTECIMIENTO | F10: =COUNTIF(Estandarización!G:G,Condicionales!C10) -> 4 | G10: =SUMIF(Estandarización!G:G,Condicionales!C10,Estandarización!F:F) -> 4 | H10: =+G10/F10 -> 1 | I10: =+H10 -> 1 | M10: Total | N10: =+F15+F16+F17 -> 9 | Q10: =+"Condición 2: "&Q11 -> Condición 2: OK
B11: =+B10+1 -> 7 | C11: CRITICO.7 | D11: INVENTARIOS ROTATIVOS | F11: =COUNTIF(Estandarización!G:G,Condicionales!C11) -> 3 | G11: =SUMIF(Estandarización!G:G,Condicionales!C11,Estandarización!F:F) -> 3 | H11: =+G11/F11 -> 1 | I11: =+H11 -> 1 | M11: Cumplidas | N11: =+G15+G16+G17 -> 9 | Q11: =IF(N11=N10,"OK","No OK") -> OK
B12: =+B11+1 -> 8 | C12: CRITICO.8 | D12: PROCESOS DOCUMENTADOS | F12: =COUNTIF(Estandarización!G:G,Condicionales!C12) -> 8 | G12: =SUMIF(Estandarización!G:G,Condicionales!C12,Estandarización!F:F) -> 8 | H12: =+G12/F12 -> 1 | I12: =+H12 -> 1
B13: =+B12+1 -> 9 | C13: CRITICO.9 | D13: HERRAMIENTAS DE GESTIÓN | F13: =COUNTIF(Estandarización!G:G,Condicionales!C13) -> 4 | G13: =SUMIF(Estandarización!G:G,Condicionales!C13,Estandarización!F:F) -> 0 | H13: =+G13/F13 -> 0 | I13: =+H13 -> 0 | L13: Condición 3 para PROACTIVOS: 100% de cumplimiento de las BLPs Criticas
B14: =+B13+1 -> 10 | C14: CRITICO.10 | D14: INDICADORES | F14: =COUNTIF(Estandarización!G:G,Condicionales!C14) -> 6 | G14: =SUMIF(Estandarización!G:G,Condicionales!C14,Estandarización!F:F) -> 6 | H14: =+G14/F14 -> 1 | I14: =+H14 -> 1 | M14: Calificación | N14: =+'Resumen - Se oculta 5,0'!B131 -> 0.57607109 | Q14: =+"Condición 3: "&Q15 -> Condición 3: No Aplica
B15: =+B14+1 -> 11 | C15: CRITICO.11 | D15: DEVOLUCIONES DE PRODUCTOS NO APTOS | F15: =COUNTIF(Operacional!G:G,Condicionales!C15) -> 2 | G15: =SUMIF(Operacional!G:G,Condicionales!C15,Operacional!F:F) -> 2 | H15: =+G15/F15 -> 1 | I15: =+H15 -> 1 | M15: Categoria | N15: =+'Resumen - Se oculta 5,0'!D134 -> INACTIVO | Q15: =IF(N15="PROACTIVO",IF(H21=100%,"OK","No OK"),"No Aplica") -> No Aplica
B16: =+B15+1 -> 12 | C16: CRITICO.12 | D16: RECHAZOS | F16: =COUNTIF(Operacional!G:G,Condicionales!C16) -> 2 | G16: =SUMIF(Operacional!G:G,Condicionales!C16,Operacional!F:F) -> 2 | H16: =+G16/F16 -> 1 | I16: =+H16 -> 1
B17: =+B16+1 -> 13 | C17: CRITICO.13 | D17: CONTROL DE PLAGAS | F17: =COUNTIF(Operacional!G:G,Condicionales!C17) -> 5 | G17: =SUMIF(Operacional!G:G,Condicionales!C17,Operacional!F:F) -> 5 | H17: =+G17/F17 -> 1 | I17: =+H17 -> 1 | O17: ="BPLs Condicionales: "&G21&" Cumplidas"&" de "&F21 -> BPLs Condicionales: 38 Cumplidas de 50
B18: =+B17+1 -> 14 | C18: CRITICO.14 | D18: CONTROL DE TEMPERATURAS | F18: =COUNTIF(Operacional!G:G,Condicionales!C18) -> 2 | G18: =SUMIF(Operacional!G:G,Condicionales!C18,Operacional!F:F) -> 0 | H18: =+G18/F18 -> 0 | I18: =+H18 -> 0 | O18: =IF('Resumen - Se oculta 5,0'!D131="PROACTIVO",IF(Condicionales!H21=100%,"MANTIENE ESTADIO","CAE 1 ESTADIO"),IF(Q11="No OK","CAE 1 ESTADIO",IF(Q7="OK","MANTIENE ESTADIO","CAE 1 ESTADIO"))) -> CAE 1 ESTADIO
B19: =+B18+1 -> 15 | C19: CRITICO.15 | D19: INFRAESTRUCTURA - PISOS Y PAREDES | F19: =COUNTIF(Operacional!G:G,Condicionales!C19) -> 2 | G19: =SUMIF(Operacional!G:G,Condicionales!C19,Operacional!F:F) -> 2 | H19: =+G19/F19 -> 1 | I19: =+H19 -> 1
D21: Totales | F21: =SUM(F5:F20) -> 50 | G21: =SUM(G5:G20) -> 38 | H21: =+G21/F21 -> 0.76

Sheet Zoom QA
B2: Nivel | C2: Módulo | D2: BPL | F2: # componentes
F3: Totales | G3: OK
B5: Nivel Operacional | C5: Calidad | D5: Control de Temperaturas | F5: =COUNTIFS(Operacional!H:H,"QA",Operacional!C:C,'Zoom QA'!D5) -> 5 | G5: =SUMIFS(Operacional!F:F,Operacional!H:H,"QA",Operacional!C:C,'Zoom QA'!D5) -> 1 | H5: =+G5/F5 -> 0.2
D6: Cuidado del producto durante las distintas etapas | F6: =COUNTIFS(Operacional!H:H,"QA",Operacional!C:C,'Zoom QA'!D6) -> 21 | G6: =SUMIFS(Operacional!F:F,Operacional!H:H,"QA",Operacional!C:C,'Zoom QA'!D6) -> 12 | H6: =+G6/F6 -> 0.57142857
D7: Limpieza | F7: =COUNTIFS(Operacional!H:H,"QA",Operacional!C:C,'Zoom QA'!D7) -> 10 | G7: =SUMIFS(Operacional!F:F,Operacional!H:H,"QA",Operacional!C:C,'Zoom QA'!D7) -> 10 | H7: =+G7/F7 -> 1
D8: Manejo Integrado de Plagas | F8: =COUNTIFS(Operacional!H:H,"QA",Operacional!C:C,'Zoom QA'!D8) -> 6 | G8: =SUMIFS(Operacional!F:F,Operacional!H:H,"QA",Operacional!C:C,'Zoom QA'!D8) -> 6 | H8: =+G8/F8 -> 1 | V8: Estandarización | W8: =+Y8/X8 -> 0.71428571 | X8: =SUM(F18:F19) -> 7 | Y8: =SUM(G18:G19) -> 5
C9: Infraestructura | D9: Techos y Paredes: Estado | F9: =COUNTIFS(Operacional!H:H,"QA",Operacional!C:C,'Zoom QA'!D9) -> 4 | G9: =SUMIFS(Operacional!F:F,Operacional!H:H,"QA",Operacional!C:C,'Zoom QA'!D9) -> 3 | H9: =+G9/F9 -> 0.75 | V9: Operacional | W9: =+Y9/X9 -> 0.64179104 | X9: =+SUM(F5:F17) -> 67 | Y9: =+SUM(G5:G17) -> 43
D10: Pisos y Juntas: Estado | F10: =COUNTIFS(Operacional!H:H,"QA",Operacional!C:C,'Zoom QA'!D10) -> 4 | G10: =SUMIFS(Operacional!F:F,Operacional!H:H,"QA",Operacional!C:C,'Zoom QA'!D10) -> 3 | H10: =+G10/F10 -> 0.75 | V10: Total ZOOM | W10: =+Y10/X10 -> 0.64864865 | X10: =SUM(X7:X9) -> 74 | Y10: =SUM(Y7:Y9) -> 48
D11: Equipamiento de Manipuleo | F11: =COUNTIFS(Operacional!H:H,"QA",Operacional!C:C,'Zoom QA'!D11) -> 1 | G11: =SUMIFS(Operacional!F:F,Operacional!H:H,"QA",Operacional!C:C,'Zoom QA'!D11) -> 1 | H11: =+G11/F11 -> 1
D12: Pop y Mobiliario | F12: =COUNTIFS(Operacional!H:H,"QA",Operacional!C:C,'Zoom QA'!D12) -> 3 | G12: =SUMIFS(Operacional!F:F,Operacional!H:H,"QA",Operacional!C:C,'Zoom QA'!D12) -> 1 | H12: =+G12/F12 -> 0.33333333
D13: Camara de Refrigerados | F13: =COUNTIFS(Operacional!H:H,"QA",Operacional!C:C,'Zoom QA'!D13) -> 3 | G13: =SUMIFS(Operacional!F:F,Operacional!H:H,"QA",Operacional!C:C,'Zoom QA'!D13) -> 0 | H13: =+G13/F13 -> 0
D14: Camara de Congelados | F14: =COUNTIFS(Operacional!H:H,"QA",Operacional!C:C,'Zoom QA'!D14) -> 3 | G14: =SUMIFS(Operacional!F:F,Operacional!H:H,"QA",Operacional!C:C,'Zoom QA'!D14) -> 0 | H14: =+G14/F14 -> 0
D15: Grupo Electrógeno | F15: =COUNTIFS(Operacional!H:H,"QA",Operacional!C:C,'Zoom QA'!D15) -> 2 | G15: =SUMIFS(Operacional!F:F,Operacional!H:H,"QA",Operacional!C:C,'Zoom QA'!D15) -> 2 | H15: =+G15/F15 -> 1
C16: Org y Cultura | D16: Cultura de Buenas prácticas de manufactura | F16: =COUNTIFS(Operacional!H:H,"QA",Operacional!C:C,'Zoom QA'!D16) -> 1 | G16: =SUMIFS(Operacional!F:F,Operacional!H:H,"QA",Operacional!C:C,'Zoom QA'!D16) -> 1 | H16: =+G16/F16 -> 1
C17: 5S | D17: Método de 5"S" | F17: =COUNTIFS(Operacional!H:H,"QA",Operacional!C:C,'Zoom QA'!D17) -> 4 | G17: =SUMIFS(Operacional!F:F,Operacional!H:H,"QA",Operacional!C:C,'Zoom QA'!D17) -> 3 | H17: =+G17/F17 -> 0.75
B18: Nivel Estandarización | C18: Indicadores | D18: Indicadores - Procesos Logísticos | F18: =COUNTIFS(Estandarización!H:H,"QA",Estandarización!C:C,'Zoom QA'!D18) -> 3 | G18: =SUMIFS(Estandarización!F:F,Estandarización!H:H,"QA",Estandarización!C:C,'Zoom QA'!D18) -> 2 | H18: =+G18/F18 -> 0.66666667
D19: Mantenimiento | F19: =COUNTIFS(Estandarización!H:H,"QA",Estandarización!C:C,'Zoom QA'!D19) -> 4 | G19: =SUMIFS(Estandarización!F:F,Estandarización!H:H,"QA",Estandarización!C:C,'Zoom QA'!D19) -> 3 | H19: =+G19/F19 -> 0.75
D21: Totales | F21: =SUM(F5:F19) -> 74 | G21: =SUM(G5:G19) -> 48 | H21: =+G21/F21 -> 0.64864865
G41: Indicadores - Procesos Logísticos
G42: Indicadores - Procesos Logísticos
G43: Indicadores - Procesos Logísticos
G44: Mantenimiento
G45: Mantenimiento
G46: Mantenimiento
G47: Mantenimiento

Sheet Zoom SUST
B2: Nivel | C2: Módulo | D2: BPL | F2: # componentes
F3: Totales | G3: OK
B5: Nivel Operacional | C5: Seguridad | D5: Gestion del Comportamiento | F5: =COUNTIFS(Operacional!H:H,"SUST",Operacional!C:C,'Zoom SUST'!D5) -> 2 | G5: =SUMIFS(Operacional!F:F,Operacional!H:H,"SUST",Operacional!C:C,'Zoom SUST'!D5) -> 2 | H5: =+G5/F5 -> 1
D6: Emergencias | F6: =COUNTIFS(Operacional!H:H,"SUST",Operacional!C:C,'Zoom SUST'!D6) -> 1 | G6: =SUMIFS(Operacional!F:F,Operacional!H:H,"SUST",Operacional!C:C,'Zoom SUST'!D6) -> 0 | H6: =+G6/F6 -> 0
D7: Riesgos Durante la Entrega | F7: =COUNTIFS(Operacional!H:H,"SUST",Operacional!C:C,'Zoom SUST'!D7) -> 1 | G7: =SUMIFS(Operacional!F:F,Operacional!H:H,"SUST",Operacional!C:C,'Zoom SUST'!D7) -> 1 | H7: =+G7/F7 -> 1 | V7: Mejora | W7: =+Y7/X7 -> 0.5 | X7: =+F33+F34 -> 4 | Y7: =+G33+G34 -> 2
C8: Calidad | D8: Cuidado del producto durante las distintas etapas | F8: =COUNTIFS(Operacional!H:H,"SUST",Operacional!C:C,'Zoom SUST'!D8) -> 1 | G8: =SUMIFS(Operacional!F:F,Operacional!H:H,"SUST",Operacional!C:C,'Zoom SUST'!D8) -> 0 | H8: =+G8/F8 -> 0 | V8: Estandarización | W8: =+Y8/X8 -> 0 | X8: =SUM(F24:F32) -> 17 | Y8: =SUM(G24:G32) -> 0
C9: Infraestructura | D9: Predio, Accesibilidad y Circulacion | F9: =COUNTIFS(Operacional!H:H,"SUST",Operacional!C:C,'Zoom SUST'!D9) -> 1 | G9: =SUMIFS(Operacional!F:F,Operacional!H:H,"SUST",Operacional!C:C,'Zoom SUST'!D9) -> 0 | H9: =+G9/F9 -> 0 | V9: Operacional | W9: =+Y9/X9 -> 0.25 | X9: =+SUM(F5:F23) -> 36 | Y9: =+SUM(G5:G23) -> 9
D10: Aberturas | F10: =COUNTIFS(Operacional!H:H,"SUST",Operacional!C:C,'Zoom SUST'!D10) -> 1 | G10: =SUMIFS(Operacional!F:F,Operacional!H:H,"SUST",Operacional!C:C,'Zoom SUST'!D10) -> 0 | H10: =+G10/F10 -> 0 | V10: Total ZOOM | W10: =+Y10/X10 -> 0.19298246 | X10: =SUM(X7:X9) -> 57 | Y10: =SUM(Y7:Y9) -> 11
D11: Iluminación | F11: =COUNTIFS(Operacional!H:H,"SUST",Operacional!C:C,'Zoom SUST'!D11) -> 4 | G11: =SUMIFS(Operacional!F:F,Operacional!H:H,"SUST",Operacional!C:C,'Zoom SUST'!D11) -> 2 | H11: =+G11/F11 -> 0.5
D12: Desagües | F12: =COUNTIFS(Operacional!H:H,"SUST",Operacional!C:C,'Zoom SUST'!D12) -> 1 | G12: =SUMIFS(Operacional!F:F,Operacional!H:H,"SUST",Operacional!C:C,'Zoom SUST'!D12) -> 0 | H12: =+G12/F12 -> 0
D13: Equipamiento de Manipuleo | F13: =COUNTIFS(Operacional!H:H,"SUST",Operacional!C:C,'Zoom SUST'!D13) -> 1 | G13: =SUMIFS(Operacional!F:F,Operacional!H:H,"SUST",Operacional!C:C,'Zoom SUST'!D13) -> 1 | H13: =+G13/F13 -> 1
D14: Camara de Refrigerados | F14: =COUNTIFS(Operacional!H:H,"SUST",Operacional!C:C,'Zoom SUST'!D14) -> 1 | G14: =SUMIFS(Operacional!F:F,Operacional!H:H,"SUST",Operacional!C:C,'Zoom SUST'!D14) -> 0 | H14: =+G14/F14 -> 0
D15: Camara de Congelados | F15: =COUNTIFS(Operacional!H:H,"SUST",Operacional!C:C,'Zoom SUST'!D15) -> 1 | G15: =SUMIFS(Operacional!F:F,Operacional!H:H,"SUST",Operacional!C:C,'Zoom SUST'!D15) -> 0 | H15: =+G15/F15 -> 0
D16: Grupo Electrógeno | F16: =COUNTIFS(Operacional!H:H,"SUST",Operacional!C:C,'Zoom SUST'!D16) -> 1 | G16: =SUMIFS(Operacional!F:F,Operacional!H:H,"SUST",Operacional!C:C,'Zoom SUST'!D16) -> 0 | H16: =+G16/F16 -> 0
D17: Informática | F17: =COUNTIFS(Operacional!H:H,"SUST",Operacional!C:C,'Zoom SUST'!D17) -> 3 | G17: =SUMIFS(Operacional!F:F,Operacional!H:H,"SUST",Operacional!C:C,'Zoom SUST'!D17) -> 0 | H17: =+G17/F17 -> 0
D18: Vehículos | F18: =COUNTIFS(Operacional!H:H,"SUST",Operacional!C:C,'Zoom SUST'!D18) -> 3 | G18: =SUMIFS(Operacional!F:F,Operacional!H:H,"SUST",Operacional!C:C,'Zoom SUST'!D18) -> 1 | H18: =+G18/F18 -> 0.33333333
D19: Gestión de Residuos | F19: =COUNTIFS(Operacional!H:H,"SUST",Operacional!C:C,'Zoom SUST'!D19) -> 3 | G19: =SUMIFS(Operacional!F:F,Operacional!H:H,"SUST",Operacional!C:C,'Zoom SUST'!D19) -> 1 | H19: =+G19/F19 -> 0.33333333
C20: Org y Cultura | D20: Gobernanza (Ética y Cultura) | F20: =COUNTIFS(Operacional!H:H,"SUST",Operacional!C:C,'Zoom SUST'!D20) -> 4 | G20: =SUMIFS(Operacional!F:F,Operacional!H:H,"SUST",Operacional!C:C,'Zoom SUST'!D20) -> 1 | H20: =+G20/F20 -> 0.25
D21: Selección de Personal | F21: =COUNTIFS(Operacional!H:H,"SUST",Operacional!C:C,'Zoom SUST'!D21) -> 2 | G21: =SUMIFS(Operacional!F:F,Operacional!H:H,"SUST",Operacional!C:C,'Zoom SUST'!D21) -> 0 | H21: =+G21/F21 -> 0
D22: Remuneración y beneficios | F22: =COUNTIFS(Operacional!H:H,"SUST",Operacional!C:C,'Zoom SUST'!D22) -> 3 | G22: =SUMIFS(Operacional!F:F,Operacional!H:H,"SUST",Operacional!C:C,'Zoom SUST'!D22) -> 0 | H22: =+G22/F22 -> 0
D23: Capacitación y desarrollo de los RH | F23: =COUNTIFS(Operacional!H:H,"SUST",Operacional!C:C,'Zoom SUST'!D23) -> 2 | G23: =SUMIFS(Operacional!F:F,Operacional!H:H,"SUST",Operacional!C:C,'Zoom SUST'!D23) -> 0 | H23: =+G23/F23 -> 0
B24: Nivel Estandarización | C24: Procesos Logisticos | D24: Despacho | F24: =COUNTIFS(Estandarización!H:H,"SUST",Estandarización!C:C,'Zoom SUST'!D24) -> 1 | G24: =SUMIFS(Estandarización!F:F,Estandarización!H:H,"SUST",Estandarización!C:C,'Zoom SUST'!D24) -> 0 | H24: =+G24/F24 -> 0
C25: Indicadores | D25: Indicadores - Sustentabilidad & MAHPI | F25: =COUNTIFS(Estandarización!H:H,"SUST",Estandarización!C:C,'Zoom SUST'!D25) -> 6 | G25: =SUMIFS(Estandarización!F:F,Estandarización!H:H,"SUST",Estandarización!C:C,'Zoom SUST'!D25) -> 0 | H25: =+G25/F25 -> 0
D26: Indicadores - Procesos Logísticos | F26: =COUNTIFS(Estandarización!H:H,"SUST",Estandarización!C:C,'Zoom SUST'!D26) -> 1 | G26: =SUMIFS(Estandarización!F:F,Estandarización!H:H,"SUST",Estandarización!C:C,'Zoom SUST'!D26) -> 0 | H26: =+G26/F26 -> 0
D27: Información al Personal | F27: =COUNTIFS(Estandarización!H:H,"SUST",Estandarización!C:C,'Zoom SUST'!D27) -> 1 | G27: =SUMIFS(Estandarización!F:F,Estandarización!H:H,"SUST",Estandarización!C:C,'Zoom SUST'!D27) -> 0 | H27: =+G27/F27 -> 0
C28: Proveedores | D28: Cumplimiento y Gestión de Riesgos con Proveedores | F28: =COUNTIFS(Estandarización!H:H,"SUST",Estandarización!C:C,'Zoom SUST'!D28) -> 1 | G28: =SUMIFS(Estandarización!F:F,Estandarización!H:H,"SUST",Estandarización!C:C,'Zoom SUST'!D28) -> 0 | H28: =+G28/F28 -> 0
D29: Abastecimiento con Criterios de Sustentabilidad | F29: =COUNTIFS(Estandarización!H:H,"SUST",Estandarización!C:C,'Zoom SUST'!D29) -> 1 | G29: =SUMIFS(Estandarización!F:F,Estandarización!H:H,"SUST",Estandarización!C:C,'Zoom SUST'!D29) -> 0 | H29: =+G29/F29 -> 0
C30: Relaciones con la comunidad | D30: Gestión de Impactos de la Operación en la Comunidad | F30: =COUNTIFS(Estandarización!H:H,"SUST",Estandarización!C:C,'Zoom SUST'!D30) -> 2 | G30: =SUMIFS(Estandarización!F:F,Estandarización!H:H,"SUST",Estandarización!C:C,'Zoom SUST'!D30) -> 0 | H30: =+G30/F30 -> 0
D31: Involucramiento y Desarrollo de la Comunidad | F31: =COUNTIFS(Estandarización!H:H,"SUST",Estandarización!C:C,'Zoom SUST'!D31) -> 1 | G31: =SUMIFS(Estandarización!F:F,Estandarización!H:H,"SUST",Estandarización!C:C,'Zoom SUST'!D31) -> 0 | H31: =+G31/F31 -> 0
C32: Gestion Ambiental | D32: Gestión Ambiental | F32: =COUNTIFS(Estandarización!H:H,"SUST",Estandarización!C:C,'Zoom SUST'!D32) -> 3 | G32: =SUMIFS(Estandarización!F:F,Estandarización!H:H,"SUST",Estandarización!C:C,'Zoom SUST'!D32) -> 0 | H32: =+G32/F32 -> 0
B33: Nivel Mejora | C33: Planeamiento estrategico | D33: Planificación estratégica | F33: =COUNTIFS(Mejora!H:H,"SUST",Mejora!C:C,'Zoom SUST'!D33) -> 2 | G33: =SUMIFS(Mejora!F:F,Mejora!H:H,"SUST",Mejora!C:C,'Zoom SUST'!D33) -> 0 | H33: =+G33/F33 -> 0
C34: Mejora Continua | D34: Sugerencias de mejora | F34: =COUNTIFS(Mejora!H:H,"SUST",Mejora!C:C,'Zoom SUST'!D34) -> 2 | G34: =SUMIFS(Mejora!F:F,Mejora!H:H,"SUST",Mejora!C:C,'Zoom SUST'!D34) -> 2 | H34: =+G34/F34 -> 1
D36: Totales | F36: =SUM(F5:F35) -> 57 | G36: =SUM(G5:G35) -> 11 | H36: =+G36/F36 -> 0.19298246

Sheet Summary BPL
A2: MODULO | B2: BPL | C2: Puntos posibles | D2: Puntos Logrados | E2: % Adherencia
A3: SEGURIDAD | B3: Permisos y Habilitaciones | C3: =COUNTIF(Operacional!C:C,'Summary BPL'!B3)-COUNTIFS(Operacional!C:C,'Summary BPL'!B3,Operacional!F:F,"N/A")-COUNTIFS(Operacional!C:C,'Summary BPL'!B3,Operacional!F:F,"NA - 1")-COUNTIFS(Operacional!C:C,'Summary BPL'!B3,Operacional!F:F,"NA - 0") -> 4 | D3: =SUMIFS(Operacional!F:F,Operacional!C:C,'Summary BPL'!B3) -> 4 | E3: =+IFERROR(D3/C3,0) -> 1
A4: SEGURIDAD | B4: Cumplimiento de Resoluciones H&S | C4: =COUNTIF(Operacional!C:C,'Summary BPL'!B4)-COUNTIFS(Operacional!C:C,'Summary BPL'!B4,Operacional!F:F,"N/A")-COUNTIFS(Operacional!C:C,'Summary BPL'!B4,Operacional!F:F,"NA - 1")-COUNTIFS(Operacional!C:C,'Summary BPL'!B4,Operacional!F:F,"NA - 0") -> 5 | D4: =SUMIFS(Operacional!F:F,Operacional!C:C,'Summary BPL'!B4) -> 2 | E4: =+IFERROR(D4/C4,0) -> 0.4
A5: SEGURIDAD | B5: Evaluacion de Riesgo y Plan de Gestion | C5: =COUNTIF(Operacional!C:C,'Summary BPL'!B5)-COUNTIFS(Operacional!C:C,'Summary BPL'!B5,Operacional!F:F,"N/A")-COUNTIFS(Operacional!C:C,'Summary BPL'!B5,Operacional!F:F,"NA - 1")-COUNTIFS(Operacional!C:C,'Summary BPL'!B5,Operacional!F:F,"NA - 0") -> 2 | D5: =SUMIFS(Operacional!F:F,Operacional!C:C,'Summary BPL'!B5) -> 0 | E5: =+IFERROR(D5/C5,0) -> 0
A6: SEGURIDAD | B6: Gestion de las Personas | C6: =COUNTIF(Operacional!C:C,'Summary BPL'!B6)-COUNTIFS(Operacional!C:C,'Summary BPL'!B6,Operacional!F:F,"N/A")-COUNTIFS(Operacional!C:C,'Summary BPL'!B6,Operacional!F:F,"NA - 1")-COUNTIFS(Operacional!C:C,'Summary BPL'!B6,Operacional!F:F,"NA - 0") -> 3 | D6: =SUMIFS(Operacional!F:F,Operacional!C:C,'Summary BPL'!B6) -> 0 | E6: =+IFERROR(D6/C6,0) -> 0
A7: SEGURIDAD | B7: Gestion del Comportamiento | C7: =COUNTIF(Operacional!C:C,'Summary BPL'!B7)-COUNTIFS(Operacional!C:C,'Summary BPL'!B7,Operacional!F:F,"N/A")-COUNTIFS(Operacional!C:C,'Summary BPL'!B7,Operacional!F:F,"NA - 1")-COUNTIFS(Operacional!C:C,'Summary BPL'!B7,Operacional!F:F,"NA - 0") -> 4 | D7: =SUMIFS(Operacional!F:F,Operacional!C:C,'Summary BPL'!B7) -> 2 | E7: =+IFERROR(D7/C7,0) -> 0.5
A8: SEGURIDAD | B8: Capacitacion y Entrenamiento | C8: =COUNTIF(Operacional!C:C,'Summary BPL'!B8)-COUNTIFS(Operacional!C:C,'Summary BPL'!B8,Operacional!F:F,"N/A")-COUNTIFS(Operacional!C:C,'Summary BPL'!B8,Operacional!F:F,"NA - 1")-COUNTIFS(Operacional!C:C,'Summary BPL'!B8,Operacional!F:F,"NA - 0") -> 4 | D8: =SUMIFS(Operacional!F:F,Operacional!C:C,'Summary BPL'!B8) -> 1 | E8: =+IFERROR(D8/C8,0) -> 0.25
A9: SEGURIDAD | B9: Interaccion Hombre-Maquina | C9: =COUNTIF(Operacional!C:C,'Summary BPL'!B9)-COUNTIFS(Operacional!C:C,'Summary BPL'!B9,Operacional!F:F,"N/A")-COUNTIFS(Operacional!C:C,'Summary BPL'!B9,Operacional!F:F,"NA - 1")-COUNTIFS(Operacional!C:C,'Summary BPL'!B9,Operacional!F:F,"NA - 0") -> 2 | D9: =SUMIFS(Operacional!F:F,Operacional!C:C,'Summary BPL'!B9) -> 1 | E9: =+IFERROR(D9/C9,0) -> 0.5
A10: SEGURIDAD | B10: Instalaciones y Equipos | C10: =COUNTIF(Operacional!C:C,'Summary BPL'!B10)-COUNTIFS(Operacional!C:C,'Summary BPL'!B10,Operacional!F:F,"N/A")-COUNTIFS(Operacional!C:C,'Summary BPL'!B10,Operacional!F:F,"NA - 1")-COUNTIFS(Operacional!C:C,'Summary BPL'!B10,Operacional!F:F,"NA - 0") -> 9 | D10: =SUMIFS(Operacional!F:F,Operacional!C:C,'Summary BPL'!B10) -> 1 | E10: =+IFERROR(D10/C10,0) -> 0.11111111
A11: SEGURIDAD | B11: Conexiones Electricas y Tableros | C11: =COUNTIF(Operacional!C:C,'Summary BPL'!B11)-COUNTIFS(Operacional!C:C,'Summary BPL'!B11,Operacional!F:F,"N/A")-COUNTIFS(Operacional!C:C,'Summary BPL'!B11,Operacional!F:F,"NA - 1")-COUNTIFS(Operacional!C:C,'Summary BPL'!B11,Operacional!F:F,"NA - 0") -> 8 | D11: =SUMIFS(Operacional!F:F,Operacional!C:C,'Summary BPL'!B11) -> 1 | E11: =+IFERROR(D11/C11,0) -> 0.125
A12: SEGURIDAD | B12: Emergencias | C12: =COUNTIF(Operacional!C:C,'Summary BPL'!B12)-COUNTIFS(Operacional!C:C,'Summary BPL'!B12,Operacional!F:F,"N/A")-COUNTIFS(Operacional!C:C,'Summary BPL'!B12,Operacional!F:F,"NA - 1")-COUNTIFS(Operacional!C:C,'Summary BPL'!B12,Operacional!F:F,"NA - 0") -> 6 | D12: =SUMIFS(Operacional!F:F,Operacional!C:C,'Summary BPL'!B12) -> 4 | E12: =+IFERROR(D12/C12,0) -> 0.66666667
A13: SEGURIDAD | B13: Riesgos Durante la Entrega | C13: =COUNTIF(Operacional!C:C,'Summary BPL'!B13)-COUNTIFS(Operacional!C:C,'Summary BPL'!B13,Operacional!F:F,"N/A")-COUNTIFS(Operacional!C:C,'Summary BPL'!B13,Operacional!F:F,"NA - 1")-COUNTIFS(Operacional!C:C,'Summary BPL'!B13,Operacional!F:F,"NA - 0") -> 4 | D13: =SUMIFS(Operacional!F:F,Operacional!C:C,'Summary BPL'!B13) -> 2 | E13: =+IFERROR(D13/C13,0) -> 0.5
C14: =COUNTIF(Operacional!C:C,'Summary BPL'!B14)-COUNTIFS(Operacional!C:C,'Summary BPL'!B14,Operacional!F:F,"N/A")-COUNTIFS(Operacional!C:C,'Summary BPL'!B14,Operacional!F:F,"NA - 1")-COUNTIFS(Operacional!C:C,'Summary BPL'!B14,Operacional!F:F,"NA - 0") -> 0 | D14: =SUMIFS(Operacional!F:F,Operacional!C:C,'Summary BPL'!B14) -> 0 | E14: =+IFERROR(D14/C14,0) -> 0
A15: CALIDAD | B15: Control de Temperaturas | C15: =COUNTIF(Operacional!C:C,'Summary BPL'!B15)-COUNTIFS(Operacional!C:C,'Summary BPL'!B15,Operacional!F:F,"N/A")-COUNTIFS(Operacional!C:C,'Summary BPL'!B15,Operacional!F:F,"NA - 1")-COUNTIFS(Operacional!C:C,'Summary BPL'!B15,Operacional!F:F,"NA - 0") -> 3 | D15: =SUMIFS(Operacional!F:F,Operacional!C:C,'Summary BPL'!B15) -> 1 | E15: =+IFERROR(D15/C15,0) -> 0.33333333
A16: CALIDAD | B16: Cuidado del producto durante las distintas etapas | C16: =COUNTIF(Operacional!C:C,'Summary BPL'!B16)-COUNTIFS(Operacional!C:C,'Summary BPL'!B16,Operacional!F:F,"N/A")-COUNTIFS(Operacional!C:C,'Summary BPL'!B16,Operacional!F:F,"NA - 1")-COUNTIFS(Operacional!C:C,'Summary BPL'!B16,Operacional!F:F,"NA - 0") -> 18 | D16: =SUMIFS(Operacional!F:F,Operacional!C:C,'Summary BPL'!B16) -> 12 | E16: =+IFERROR(D16/C16,0) -> 0.66666667
A17: CALIDAD | B17: Limpieza | C17: =COUNTIF(Operacional!C:C,'Summary BPL'!B17)-COUNTIFS(Operacional!C:C,'Summary BPL'!B17,Operacional!F:F,"N/A")-COUNTIFS(Operacional!C:C,'Summary BPL'!B17,Operacional!F:F,"NA - 1")-COUNTIFS(Operacional!C:C,'Summary BPL'!B17,Operacional!F:F,"NA - 0") -> 10 | D17: =SUMIFS(Operacional!F:F,Operacional!C:C,'Summary BPL'!B17) -> 10 | E17: =+IFERROR(D17/C17,0) -> 1
A18: CALIDAD | B18: Manejo Integrado de Plagas | C18: =COUNTIF(Operacional!C:C,'Summary BPL'!B18)-COUNTIFS(Operacional!C:C,'Summary BPL'!B18,Operacional!F:F,"N/A")-COUNTIFS(Operacional!C:C,'Summary BPL'!B18,Operacional!F:F,"NA - 1")-COUNTIFS(Operacional!C:C,'Summary BPL'!B18,Operacional!F:F,"NA - 0") -> 6 | D18: =SUMIFS(Operacional!F:F,Operacional!C:C,'Summary BPL'!B18) -> 6 | E18: =+IFERROR(D18/C18,0) -> 1
A19: CALIDAD | B19: Sector Embolsate | C19: =COUNTIF(Operacional!C:C,'Summary BPL'!B19)-COUNTIFS(Operacional!C:C,'Summary BPL'!B19,Operacional!F:F,"N/A")-COUNTIFS(Operacional!C:C,'Summary BPL'!B19,Operacional!F:F,"NA - 1")-COUNTIFS(Operacional!C:C,'Summary BPL'!B19,Operacional!F:F,"NA - 0") -> 0 | D19: =SUMIFS(Operacional!F:F,Operacional!C:C,'Summary BPL'!B19) -> 0 | E19: =+IFERROR(D19/C19,0) -> 0
A21: INFRAESTRUCTURA LAYOUT Y FLOTA | B21: Entorno - Acceso | C21: =COUNTIF(Operacional!C:C,'Summary BPL'!B21)-COUNTIFS(Operacional!C:C,'Summary BPL'!B21,Operacional!F:F,"N/A")-COUNTIFS(Operacional!C:C,'Summary BPL'!B21,Operacional!F:F,"NA - 1")-COUNTIFS(Operacional!C:C,'Summary BPL'!B21,Operacional!F:F,"NA - 0") -> 1 | D21: =SUMIFS(Operacional!F:F,Operacional!C:C,'Summary BPL'!B21) -> 1 | E21: =+IFERROR(D21/C21,0) -> 1
A22: INFRAESTRUCTURA LAYOUT Y FLOTA | B22: Seguridad Externa | C22: =COUNTIF(Operacional!C:C,'Summary BPL'!B22)-COUNTIFS(Operacional!C:C,'Summary BPL'!B22,Operacional!F:F,"N/A")-COUNTIFS(Operacional!C:C,'Summary BPL'!B22,Operacional!F:F,"NA - 1")-COUNTIFS(Operacional!C:C,'Summary BPL'!B22,Operacional!F:F,"NA - 0") -> 4 | D22: =SUMIFS(Operacional!F:F,Operacional!C:C,'Summary BPL'!B22) -> 4 | E22: =+IFERROR(D22/C22,0) -> 1
A23: INFRAESTRUCTURA LAYOUT Y FLOTA | B23: Predio, Accesibilidad y Circulacion | C23: =COUNTIF(Operacional!C:C,'Summary BPL'!B23)-COUNTIFS(Operacional!C:C,'Summary BPL'!B23,Operacional!F:F,"N/A")-COUNTIFS(Operacional!C:C,'Summary BPL'!B23,Operacional!F:F,"NA - 1")-COUNTIFS(Operacional!C:C,'Summary BPL'!B23,Operacional!F:F,"NA - 0") -> 5 | D23: =SUMIFS(Operacional!F:F,Operacional!C:C,'Summary BPL'!B23) -> 2 | E23: =+IFERROR(D23/C23,0) -> 0.4
A24: INFRAESTRUCTURA LAYOUT Y FLOTA | B24: Seguridad Interna | C24: =COUNTIF(Operacional!C:C,'Summary BPL'!B24)-COUNTIFS(Operacional!C:C,'Summary BPL'!B24,Operacional!F:F,"N/A")-COUNTIFS(Operacional!C:C,'Summary BPL'!B24,Operacional!F:F,"NA - 1")-COUNTIFS(Operacional!C:C,'Summary BPL'!B24,Operacional!F:F,"NA - 0") -> 2 | D24: =SUMIFS(Operacional!F:F,Operacional!C:C,'Summary BPL'!B24) -> 2 | E24: =+IFERROR(D24/C24,0) -> 1
A25: INFRAESTRUCTURA LAYOUT Y FLOTA | B25: Techos y Paredes: Estado | C25: =COUNTIF(Operacional!C:C,'Summary BPL'!B25)-COUNTIFS(Operacional!C:C,'Summary BPL'!B25,Operacional!F:F,"N/A")-COUNTIFS(Operacional!C:C,'Summary BPL'!B25,Operacional!F:F,"NA - 1")-COUNTIFS(Operacional!C:C,'Summary BPL'!B25,Operacional!F:F,"NA - 0") -> 4 | D25: =SUMIFS(Operacional!F:F,Operacional!C:C,'Summary BPL'!B25) -> 3 | E25: =+IFERROR(D25/C25,0) -> 0.75
A26: INFRAESTRUCTURA LAYOUT Y FLOTA | B26: Pisos y Juntas: Estado | C26: =COUNTIF(Operacional!C:C,'Summary BPL'!B26)-COUNTIFS(Operacional!C:C,'Summary BPL'!B26,Operacional!F:F,"N/A")-COUNTIFS(Operacional!C:C,'Summary BPL'!B26,Operacional!F:F,"NA - 1")-COUNTIFS(Operacional!C:C,'Summary BPL'!B26,Operacional!F:F,"NA - 0") -> 4 | D26: =SUMIFS(Operacional!F:F,Operacional!C:C,'Summary BPL'!B26) -> 3 | E26: =+IFERROR(D26/C26,0) -> 0.75
A27: INFRAESTRUCTURA LAYOUT Y FLOTA | B27: Aberturas | C27: =COUNTIF(Operacional!C:C,'Summary BPL'!B27)-COUNTIFS(Operacional!C:C,'Summary BPL'!B27,Operacional!F:F,"N/A")-COUNTIFS(Operacional!C:C,'Summary BPL'!B27,Operacional!F:F,"NA - 1")-COUNTIFS(Operacional!C:C,'Summary BPL'!B27,Operacional!F:F,"NA - 0") -> 3 | D27: =SUMIFS(Operacional!F:F,Operacional!C:C,'Summary BPL'!B27) -> 2 | E27: =+IFERROR(D27/C27,0) -> 0.66666667
... A52: 5S | B52: Método de 5"S" | C52: =COUNTIF(Operacional!C:C,'Summary BPL'!B52)-COUNTIFS(Operacional!C:C,'Summary BPL'!B52,Operacional!F:F,"N/A")-COUNTIFS(Operacional!C:C,'Summary BPL'!B52,Operacional!F:F,"NA - 1")-COUNTIFS(Operacional!C:C,'Summary BPL'!B52,Operacional!F:F,"NA - 0") -> 4 | D52: =SUMIFS(Operacional!F:F,Operacional!C:C,'Summary BPL'!B52) -> 3 | E52: =+IFERROR(D52/C52,0) -> 0.75
A54: PROCESOS LOGISTICOS | B54: Planificación de Compras | C54: =COUNTIF(Estandarización!C:C,'Summary BPL'!B54)-COUNTIFS(Estandarización!C:C,'Summary BPL'!B54,Estandarización!F:F,"N/A")-COUNTIFS(Estandarización!C:C,'Summary BPL'!B54,Estandarización!F:F,"NA - 1")-COUNTIFS(Estandarización!C:C,'Summary BPL'!B54,Estandarización!F:F,"NA - 0") -> 2 | D54: =SUMIFS(Estandarización!F:F,Estandarización!C:C,'Summary BPL'!B54) -> 2 | E54: =+IFERROR(D54/C54,0) -> 1
A55: PROCESOS LOGISTICOS | B55: Activación del Abastecimiento | C55: =COUNTIF(Estandarización!C:C,'Summary BPL'!B55)-COUNTIFS(Estandarización!C:C,'Summary BPL'!B55,Estandarización!F:F,"N/A")-COUNTIFS(Estandarización!C:C,'Summary BPL'!B55,Estandarización!F:F,"NA - 1")-COUNTIFS(Estandarización!C:C,'Summary BPL'!B55,Estandarización!F:F,"NA - 0") -> 1 | D55: =SUMIFS(Estandarización!F:F,Estandarización!C:C,'Summary BPL'!B55) -> 1 | E55: =+IFERROR(D55/C55,0) -> 1
A56: PROCESOS LOGISTICOS | B56: Recepción | C56: =COUNTIF(Estandarización!C:C,'Summary BPL'!B56)-COUNTIFS(Estandarización!C:C,'Summary BPL'!B56,Estandarización!F:F,"N/A")-COUNTIFS(Estandarización!C:C,'Summary BPL'!B56,Estandarización!F:F,"NA - 1")-COUNTIFS(Estandarización!C:C,'Summary BPL'!B56,Estandarización!F:F,"NA - 0") -> 1 | D56: =SUMIFS(Estandarización!F:F,Estandarización!C:C,'Summary BPL'!B56) -> 1 | E56: =+IFERROR(D56/C56,0) -> 1
A57: PROCESOS LOGISTICOS | B57: Organización del Layout | C57: =COUNTIF(Estandarización!C:C,'Summary BPL'!B57)-COUNTIFS(Estandarización!C:C,'Summary BPL'!B57,Estandarización!F:F,"N/A")-COUNTIFS(Estandarización!C:C,'Summary BPL'!B57,Estandarización!F:F,"NA - 1")-COUNTIFS(Estandarización!C:C,'Summary BPL'!B57,Estandarización!F:F,"NA - 0") -> 2 | D57: =SUMIFS(Estandarización!F:F,Estandarización!C:C,'Summary BPL'!B57) -> 1 | E57: =+IFERROR(D57/C57,0) -> 0.5
A58: PROCESOS LOGISTICOS | B58: Identificación | C58: =COUNTIF(Estandarización!C:C,'Summary BPL'!B58)-COUNTIFS(Estandarización!C:C,'Summary BPL'!B58,Estandarización!F:F,"N/A")-COUNTIFS(Estandarización!C:C,'Summary BPL'!B58,Estandarización!F:F,"NA - 1")-COUNTIFS(Estandarización!C:C,'Summary BPL'!B58,Estandarización!F:F,"NA - 0") -> 4 | D58: =SUMIFS(Estandarización!F:F,Estandarización!C:C,'Summary BPL'!B58) -> 4 | E58: =+IFERROR(D58/C58,0) -> 1
A59: PROCESOS LOGISTICOS | B59: Rotación | C59: =COUNTIF(Estandarización!C:C,'Summary BPL'!B59)-COUNTIFS(Estandarización!C:C,'Summary BPL'!B59,Estandarización!F:F,"N/A")-COUNTIFS(Estandarización!C:C,'Summary BPL'!B59,Estandarización!F:F,"NA - 1")-COUNTIFS(Estandarización!C:C,'Summary BPL'!B59,Estandarización!F:F,"NA - 0") -> 3 | D59: =SUMIFS(Estandarización!F:F,Estandarización!C:C,'Summary BPL'!B59) -> 3 | E59: =+IFERROR(D59/C59,0) -> 1
A60: PROCESOS LOGISTICOS | B60: Inventarios Rotativos | C60: =COUNTIF(Estandarización!C:C,'Summary BPL'!B60)-COUNTIFS(Estandarización!C:C,'Summary BPL'!B60,Estandarización!F:F,"N/A")-COUNTIFS(Estandarización!C:C,'Summary BPL'!B60,Estandarización!F:F,"NA - 1")-COUNTIFS(Estandarización!C:C,'Summary BPL'!B60,Estandarización!F:F,"NA - 0") -> 3 | D60: =SUMIFS(Estandarización!F:F,Estandarización!C:C,'Summary BPL'!B60) -> 3 | E60: =+IFERROR(D60/C60,0) -> 1
A61: PROCESOS LOGISTICOS | B61: Asignación de Consolidados | C61: =COUNTIF(Estandarización!C:C,'Summary BPL'!B61)-COUNTIFS(Estandarización!C:C,'Summary BPL'!B61,Estandarización!F:F,"N/A")-COUNTIFS(Estandarización!C:C,'Summary BPL'!B61,Estandarización!F:F,"NA - 1")-COUNTIFS(Estandarización!C:C,'Summary BPL'!B61,Estandarización!F:F,"NA - 0") -> 1 | D61: =SUMIFS(Estandarización!F:F,Estandarización!C:C,'Summary BPL'!B61) -> 1 | E61: =+IFERROR(D61/C61,0) -> 1
A62: PROCESOS LOGISTICOS | B62: Control de Consolidado | C62: =COUNTIF(Estandarización!C:C,'Summary BPL'!B62)-COUNTIFS(Estandarización!C:C,'Summary BPL'!B62,Estandarización!F:F,"N/A")-COUNTIFS(Estandarización!C:C,'Summary BPL'!B62,Estandarización!F:F,"NA - 1")-COUNTIFS(Estandarización!C:C,'Summary BPL'!B62,Estandarización!F:F,"NA - 0") -> 2 | D62: =SUMIFS(Estandarización!F:F,Estandarización!C:C,'Summary BPL'!B62) -> 2 | E62: =+IFERROR(D62/C62,0) -> 1
A63: PROCESOS LOGISTICOS | B63: Armado de Pedidos | C63: =COUNTIF(Estandarización!C:C,'Summary BPL'!B63)-COUNTIFS(Estandarización!C:C,'Summary BPL'!B63,Estandarización!F:F,"N/A")-COUNTIFS(Estandarización!C:C,'Summary BPL'!B63,Estandarización!F:F,"NA - 1")-COUNTIFS(Estandarización!C:C,'Summary BPL'!B63,Estandarización!F:F,"NA - 0") -> 3 | D63: =SUMIFS(Estandarización!F:F,Estandarización!C:C,'Summary BPL'!B63) -> 3 | E63: =+IFERROR(D63/C63,0) -> 1
A64: PROCESOS LOGISTICOS | B64: Pedidos Listos Para Carga | C64: =COUNTIF(Estandarización!C:C,'Summary BPL'!B64)-COUNTIFS(Estandarización!C:C,'Summary BPL'!B64,Estandarización!F:F,"N/A")-COUNTIFS(Estandarización!C:C,'Summary BPL'!B64,Estandarización!F:F,"NA - 1")-COUNTIFS(Estandarización!C:C,'Summary BPL'!B64,Estandarización!F:F,"NA - 0") -> 1 | D64: =SUMIFS(Estandarización!F:F,Estandarización!C:C,'Summary BPL'!B64) -> 1 | E64: =+IFERROR(D64/C64,0) -> 1
A65: PROCESOS LOGISTICOS | B65: Carga de Pedidos | C65: =COUNTIF(Estandarización!C:C,'Summary BPL'!B65)-COUNTIFS(Estandarización!C:C,'Summary BPL'!B65,Estandarización!F:F,"N/A")-COUNTIFS(Estandarización!C:C,'Summary BPL'!B65,Estandarización!F:F,"NA - 1")-COUNTIFS(Estandarización!C:C,'Summary BPL'!B65,Estandarización!F:F,"NA - 0") -> 2 | D65: =SUMIFS(Estandarización!F:F,Estandarización!C:C,'Summary BPL'!B65) -> 2 | E65: =+IFERROR(D65/C65,0) -> 1
... A92: GESTION DE PROVEEDORES | B92: Abastecimiento con Criterios de Sustentabilidad | C92: =COUNTIF(Estandarización!C:C,'Summary BPL'!B92)-COUNTIFS(Estandarización!C:C,'Summary BPL'!B92,Estandarización!F:F,"N/A")-COUNTIFS(Estandarización!C:C,'Summary BPL'!B92,Estandarización!F:F,"NA - 1")-COUNTIFS(Estandarización!C:C,'Summary BPL'!B92,Estandarización!F:F,"NA - 0") -> 1 | D92: =SUMIFS(Estandarización!F:F,Estandarización!C:C,'Summary BPL'!B92) -> 0 | E92: =+IFERROR(D92/C92,0) -> 0
D93: =SUMIFS(Estandarización!F:F,Estandarización!C:C,'Summary BPL'!B93) -> 0 | E93: =+IFERROR(D93/C93,0) -> 0
A94: RELACIONES Y DESARROLLO DE LA COMUNIDAD | B94: Gestión de Impactos de la Operación en la Comunidad | C94: =COUNTIF(Estandarización!C:C,'Summary BPL'!B94)-COUNTIFS(Estandarización!C:C,'Summary BPL'!B94,Estandarización!F:F,"N/A")-COUNTIFS(Estandarización!C:C,'Summary BPL'!B94,Estandarización!F:F,"NA - 1")-COUNTIFS(Estandarización!C:C,'Summary BPL'!B94,Estandarización!F:F,"NA - 0") -> 2 | D94: =SUMIFS(Estandarización!F:F,Estandarización!C:C,'Summary BPL'!B94) -> 0 | E94: =+IFERROR(D94/C94,0) -> 0
A95: RELACIONES Y DESARROLLO DE LA COMUNIDAD | B95: Involucramiento y Desarrollo de la Comunidad | C95: =COUNTIF(Estandarización!C:C,'Summary BPL'!B95)-COUNTIFS(Estandarización!C:C,'Summary BPL'!B95,Estandarización!F:F,"N/A")-COUNTIFS(Estandarización!C:C,'Summary BPL'!B95,Estandarización!F:F,"NA - 1")-COUNTIFS(Estandarización!C:C,'Summary BPL'!B95,Estandarización!F:F,"NA - 0") -> 1 | D95: =SUMIFS(Estandarización!F:F,Estandarización!C:C,'Summary BPL'!B95) -> 0 | E95: =+IFERROR(D95/C95,0) -> 0
A97: GESTION AMBIENTAL | B97: Gestión Ambiental | C97: =COUNTIF(Estandarización!C:C,'Summary BPL'!B97)-COUNTIFS(Estandarización!C:C,'Summary BPL'!B97,Estandarización!F:F,"N/A")-COUNTIFS(Estandarización!C:C,'Summary BPL'!B97,Estandarización!F:F,"NA - 1")-COUNTIFS(Estandarización!C:C,'Summary BPL'!B97,Estandarización!F:F,"NA - 0") -> 5 | D97: =SUMIFS(Estandarización!F:F,Estandarización!C:C,'Summary BPL'!B97) -> 0 | E97: =+IFERROR(D97/C97,0) -> 0
A99: PLANEAMIENTO ESTRATEGICO | B99: Planificación Estratégica | C99: =COUNTIF(Mejora!C:C,'Summary BPL'!B99)-COUNTIFS(Mejora!C:C,'Summary BPL'!B99,Mejora!F:F,"N/A")-COUNTIFS(Mejora!C:C,'Summary BPL'!B99,Mejora!F:F,"NA - 1")-COUNTIFS(Mejora!C:C,'Summary BPL'!B99,Mejora!F:F,"NA - 0") -> 7 | D99: =SUMIFS(Mejora!F:F,Mejora!C:C,'Summary BPL'!B99) -> 3 | E99: =+IFERROR(D99/C99,0) -> 0.42857143
A100: PLANEAMIENTO ESTRATEGICO | B100: Planificación Táctica | C100: =COUNTIF(Mejora!C:C,'Summary BPL'!B100)-COUNTIFS(Mejora!C:C,'Summary BPL'!B100,Mejora!F:F,"N/A")-COUNTIFS(Mejora!C:C,'Summary BPL'!B100,Mejora!F:F,"NA - 1")-COUNTIFS(Mejora!C:C,'Summary BPL'!B100,Mejora!F:F,"NA - 0") -> 3 | D100: =SUMIFS(Mejora!F:F,Mejora!C:C,'Summary BPL'!B100) -> 2 | E100: =+IFERROR(D100/C100,0) -> 0.66666667
D101: =SUMIFS(Mejora!F:F,Mejora!C:C,'Summary BPL'!B101) -> 0 | E101: =+IFERROR(D101/C101,0) -> 0
A102: GERENCIAMIENTO Y MEJORA CONTINUA | B102: Introducción a la Mejora Continúa | C102: =COUNTIF(Mejora!C:C,'Summary BPL'!B102)-COUNTIFS(Mejora!C:C,'Summary BPL'!B102,Mejora!F:F,"N/A")-COUNTIFS(Mejora!C:C,'Summary BPL'!B102,Mejora!F:F,"NA - 1")-COUNTIFS(Mejora!C:C,'Summary BPL'!B102,Mejora!F:F,"NA - 0") -> 3 | D102: =SUMIFS(Mejora!F:F,Mejora!C:C,'Summary BPL'!B102) -> 0 | E102: =+IFERROR(D102/C102,0) -> 0
A103: GERENCIAMIENTO Y MEJORA CONTINUA | B103: Sugerencias de Mejora | C103: =COUNTIF(Mejora!C:C,'Summary BPL'!B103)-COUNTIFS(Mejora!C:C,'Summary BPL'!B103,Mejora!F:F,"N/A")-COUNTIFS(Mejora!C:C,'Summary BPL'!B103,Mejora!F:F,"NA - 1")-COUNTIFS(Mejora!C:C,'Summary BPL'!B103,Mejora!F:F,"NA - 0") -> 2 | D103: =SUMIFS(Mejora!F:F,Mejora!C:C,'Summary BPL'!B103) -> 2 | E103: =+IFERROR(D103/C103,0) -> 1

Sheet Guia Evidencias 5,0
A1: NRO. | B1: Buena Practica Logistica | D1: Componente | E1: Foco | F1: Zoom | G1: Guia de Evidencia
A3: 1 | B3: SEGURIDAD
A4: 1.1 | B4: Permisos y Habilitaciones | C4: 1.1.1 | D4: Habilitación de negocios Municipal (Verificar vencimiento) | E4: MAHPI | F4: - | G4: Copia digital de Habilitación Municipal
A5: 1.1 | B5: Permisos y Habilitaciones | C5: 1.1.2 | D5: Planos de edificio habilitados por autoridad competente | E5: - | F5: - | G5: Copia digital de planos edilicios
A6: 1.1 | B6: Permisos y Habilitaciones | C6: 1.1.3 | D6: Planos eléctricos e instalaciones habilitados de acuerdo a normativa (firma de profesional habilitado) | E6: MAHPI | F6: - | G6: Copia digital de planos eléctricos
A7: 1.1 | B7: Permisos y Habilitaciones | C7: 1.1.4 | D7: Habilitación de bomberos. Solicitar estudio de Carga de Fuego en caso de no aplicar la habilitación (tema municipal) | E7: MAHPI | F7: - | G7: Copia digital de Habilitación de bomberos.Solicitar estudio de Carga de Fuego en caso de no aplicar.
A8: 1.1 | B8: Permisos y Habilitaciones | C8: 1.1.5 | D8: Habilitación de Secretaría de energía (si aplica) | E8: MAHPI | F8: - | G8: Copia digital de Habilitación de Secretaría de Energía o empresa que realizó la instalación
A9: 1.2 | B9: Cumplimiento de Resoluciones H&S | C9: 1.2.1 | D9: Cuenta con un profesional de H&S y sus funciones son realización de las evaluaciones, planes de trabajo y capacitación | E9: MAHPI | F9: - | G9: Solicitar Nombre, apellido, telefono/mail de contacto
A10: 1.2 | B10: Cumplimiento de Resoluciones H&S | C10: 1.2.2 | D10: El distribuidor cuenta con servicio Médico | E10: MAHPI | F10: - | G10: Copia digital de constancia de cobertura
A11: 1.2 | B11: Cumplimiento de Resoluciones H&S | C11: 1.2.3 | D11: ART (Horas de servicio Médico, análisis médicos pre-ocupacionales y periódicos) | E11: MAHPI | F11: - | G11: Copia digital de constancia de cobertura
A12: 1.2 | B12: Cumplimiento de Resoluciones H&S | C12: 1.2.4 | D12: ITVs de flota: el distribuidor evidencia documentación vigente, para vehículos propios y terceros | E12: MAHPI | F12: - | G12: Copia digital de RTO y/o VTV. Listado de flota. Propia y terceros contratados
A13: 1.2 | B13: Cumplimiento de Resoluciones H&S | C13: 1.2.5 | D13: Cuenta con permiso de manejo para autoelevadores y equipo de manipuleo. Hace uso de las protecciones de seguridad correspondientes. | E13: - | F13: - | G13: Copia digital de ultimo permiso de trabajo utilizado para manejo de Autoelevador)
A14: 1.3 | B14: Evaluacion de Riesgo y Plan de Gestion | C14: 1.3.1 | D14: Están los principales riesgos identificados basandose en las 9 causas de accidentes consideradas de mayor significación por Grupo Arcor (ver PG-MHP02-9900-00001-2010) | E14: MAHPI | F14: - | G14: Excel detallando las 9 causas principales y el nivel de riesgo en el distribuidor. Areas, puestos de trabajo y tareas asociadas.
A15: 1.3 | B15: Evaluacion de Riesgo y Plan de Gestion | C15: 1.3.2 | D15: A cada riesgo identificado, se le asoció que EPPs o procedimiento se debe utilizar para reducir la exposición o disminuir su impacto | E15: - | F15: - | G15: Excel detallando todas las causas y el nivel de riesgo en el distribuidor + medidas para reducir el riesgo (epp/procedimiento). Riesgo revisado luego de la medida
... A58: 1.11 | B58: Riesgos Durante la Entrega | C58: 1.11.4 | D58: Se cuenta con un análisis de las rutas peligrosas (ej. riesgos de robo, curvas peligrosas, etc.) | E58: - | F58: - | G58: Ver registro - imagen - del ruteo. Calificación de zonas/rutas
A59: 2 | B59: CALIDAD | E59: - | F59: - | G59: -
A60: 2.1 | B60: Control de Temperaturas | C60: 2.1.1 | D60: La temperatura de los productos secos no supera los 30°C (promedio máximo diario) y 35°C máximo y se garantiza mediante elemento de medición y registros | E60: - | F60: QA | G60: Registro de temperaturas Sector Secos con detalle por hora y promedio diario. Sin desvíos. Registro de los ultimos 12 meses. EN VERANO 2 MEDICIONES DIARIAS MINIMA.
A61: 2.1 | B61: Control de Temperaturas | C61: 2.1.2 | D61: La temperatura de los productos refrigerados se encuentra comprendida entre 15°C y 25°C y se garantiza mediante registros | E61: CRITICO.14 | F61: QA | G61: Registro de temperaturas Sector Refrigerado con detalle por hora y promedio diario. Sin desvíos. Registro de los ultimos 12 meses. EN VERANO 2 MEDICIONES DIARIAS MINIMA.
A62: 2.1 | B62: Control de Temperaturas | C62: 2.1.3 | D62: La temperatura de los productos congelados se encuentra en -18°C y -22°C y se garantiza mediante registros | E62: CRITICO.14 | F62: QA | G62: Registro de temperaturas Sector Congelados con detalle por hora y promedio diario. Sin desvíos. Registro de los ultimos 12 meses
A63: 2.1 | B63: Control de Temperaturas | C63: 2.1.4 | D63: Existe un registro de contrastación y/o calibración de termómetros que garantice el correcto funcionamiento (verificar aplicación de estandar de calibración de termohigrómetros) | E63: - | F63: QA | G63: Verificar que se posea un equipo "patrón". Verificar certificados de calibración vigentes (ambos equipos - instalados y patrón)
A64: 2.1 | B64: Control de Temperaturas | C64: 2.1.5 | D64: Los instrumentos de medición alertan ante variaciones inaceptables de temperatura o fallas en el equipo de refrigeración | E64: - | F64: QA | G64: Verificar sistema de alertas de los sensores
A65: 2.2 | B65: Cuidado del producto durante las distintas etapas | C65: 2.2.1 | D65: Control general de la carga incluye vencimientos | E65: - | F65: QA | G65: Verifique checks de ingreso: Se controla que los productos cuenten con el VENCIMIENTO en forma
A66: 2.2 | B66: Cuidado del producto durante las distintas etapas | C66: 2.2.2 | D66: Control general de cantidad y estado de bultos recibidos | E66: - | F66: QA | G66: Verifique checks de ingreso: Se controla CANTIDAD y ESTADO
A67: 2.2 | B67: Cuidado del producto durante las distintas etapas | C67: 2.2.3 | D67: Controlan y poseen un registro de la temperatura con la que arriba la carga de Helados. Se da aviso y se toman acciones en caso de desvios. | E67: - | F67: QA | G67: Verifique checks de ingreso: Se controla/registra TEMPERATURA de arribo (Helados). Verificar registros y ver si hubo desvios y si hubo ver avisos.
A68: 2.2 | B68: Cuidado del producto durante las distintas etapas | C68: 2.2.4 | D68: Controlan y poseen un registro de la temperatura con la que arriba la carga de Refrigerados. Se da aviso y se toman acciones en caso de desvios | E68: - | F68: QA | G68: Verifique checks de ingreso: Se controla/registra TEMPERATURA de arribo (Refrigerados). Verificar registros y ver si hubo desvios y si hubo ver avisos.
A69: 2.2 | B69: Cuidado del producto durante las distintas etapas | C69: 2.2.5 | D69: Se identifican claramente los vencimientos | E69: - | F69: QA | G69: Almacenamiento: Revisión visual de productos. Deben contener las fechas de vencimiento visibles
A70: 2.2 | B70: Cuidado del producto durante las distintas etapas | C70: 2.2.6 | D70: Los bultos almacenados se encuentran en buen estado de conservación, apilabilidad y separación de la estiba contra la pared | E70: - | F70: QA | G70: Revisión visual de productos. Verifique 45 cm de la pared. Estado general.
A71: 2.2 | B71: Cuidado del producto durante las distintas etapas | C71: 2.2.7 | D71: Los productos que requieren acondicionamiento de temperatura (según Maestro de Artículos) se encuentran almacenados dentro de la cámara desde el momento de la recepción | E71: - | F71: QA | G71: Revisión visual. Productos bañados, rellenos, alfajores, gomas (no todas) y barras (no todas).
... A105: 2.5 | B105: Sector Embolsate | C105: 2.5.3 | D105: Se garantiza Monitoreo Integral de Plagas adecuada al Area de Fraccionamiento y a los Productos a Fraccionar. | E105: - | F105: - | G105: Disponen de Cebos para Roedores y Lampara UV
A106: 3 | B106: INFRAESTRUCTURA LAYOUT Y FLOTA
A107: 3.1 | B107: Entorno - Acceso | C107: 3.1.1 | D107: Cuenta con Acceso para circulacion de Semirremolques ( de 28 a 30 pallet) | E107: CRITICO.2 | F107: - | G107: Verificar ingreso o medir dimensiones del acceso aptas para recibir camiones de tipo semirremolque
A108: 3.2 | B108: Seguridad Externa | C108: 3.2.1 | D108: El predio del distribuidor es un predio Cerrado, o se encuentra en Zona Industrial o Logistica. | E108: - | F108: - | G108: Inspección visual o entrevista al distribuidor o empleados
A109: 3.2 | B109: Seguridad Externa | C109: 3.2.2 | D109: Se encuentra en un Zona Segura, con vigilancia de fuerzas publicas o privadas | E109: - | F109: - | G109: Inspección visual o entrevista al distribuidor o empleados
A110: 3.2 | B110: Seguridad Externa | C110: 3.2.3 | D110: Perimetro provisto con iluminacion publica o propia | E110: - | F110: - | G110: Inspección visual o entrevista al distribuidor o empleados
A111: 3.2 | B111: Seguridad Externa | C111: 3.2.4 | D111: Existen cámaras de video externas pública o propia que cubran el ingreso principal o aledaños | E111: - | F111: - | G111: Inspección visual o entrevista al distribuidor o empleados
A112: 3.3 | B112: Predio, Accesibilidad y Circulacion | C112: 3.3.1 | D112: Entorno sin problemas de congestionamiento de tráfico, y no realiza descarga de mercadería en la vía pública | E112: - | F112: - | G112: Inspección visual y validar que los vehiculos al momento de la carga/decarga no obstaculicen el trafico"
A113: 3.3 | B113: Predio, Accesibilidad y Circulacion | C113: 3.3.2 | D113: Poseen alero para la carga/descarga en condiciones climáticas desfavorables y evita demoras de la unidad | E113: - | F113: - | G113: Inspección visual y validar que los vehiculos al momento de la carga/decarga no obstaculicen el trafico"
A114: 3.3 | B114: Predio, Accesibilidad y Circulacion | C114: 3.3.3 | D114: Fácil maniobrabilidad | E114: - | F114: - | G114: Inspección visual y validar que los vehiculos al momento de la carga/decarga no obstaculicen el trafico"
A115: 3.3 | B115: Predio, Accesibilidad y Circulacion | C115: 3.3.4 | D115: Calles y accesos en buen estado, sin pendientes y asfaltados. | E115: - | F115: - | G115: Inspección visual y validar que los vehiculos al momento de la carga/decarga no obstaculicen el trafico"
A116: 3.3 | B116: Predio, Accesibilidad y Circulacion | C116: 3.3.5 | D116: Las políticas, procedimientos e infraestructura está alineado a los principios de Arcor bajo el Manual de Consideraciones Básicas para la Inclusión de Personas con Discapacidad. | E116: - | F116: SUST | G116: Inspección visual y validar que los vehiculos al momento de la carga/decarga no obstaculicen el trafico
A117: 3.4 | B117: Seguridad Interna | C117: 3.4.1 | D117: Cuenta con Sistema de Alarmas en depósito y oficinas | E117: - | F117: - | G117: Inspección visual
A118: 3.4 | B118: Seguridad Interna | C118: 3.4.2 | D118: Cuenta con Cámaras de Video en distintos sectores, con grabación y registro | E118: - | F118: - | G118: Inspección visual
... A180: 3.20 | B180: Gestión de Residuos | C180: 3.20.5 | D180: Se mantienen acuerdos flexibles con organismos recicladores y/o proveedores que aseguren la correcta disposición de materiales como cartón, plástico y papel, y se lleva un registro actualizado con tipo y cantidad de material entregado. Actualizado de la cantidad de material de este tipo generado y puesto en sistemas de economia circular. | E180: - | F180: SUST | G180: Inspección visual, de registros, y análisis
A181: 4 | B181: ORGANIZACIÓN Y CULTURA
A182: 4.1 | B182: Gobernanza (Ética y Cultura) | C182: 4.1.1 | D182: La Distribuidora cuenta con un documento formalizado y comunicado que incluye Misión, Visión y Valores. | E182: - | F182: SUST | G182: Documento que contenga Misión, Visión y Valores. Registro de la comunicación via mail, carteleria, codigo qr, whatsapp
A183: 4.1 | B183: Gobernanza (Ética y Cultura) | C183: 4.1.2 | D183: Misión, Visión y Valores de la Distribuidora presentan a la sustentabilidad como un modelo de gestión estratégico para la competitividad del negocio. | E183: - | F183: SUST | G183: En la Misión, Vision y Valores se debe mencionar a la sustentabilidad
A184: 4.1 | B184: Gobernanza (Ética y Cultura) | C184: 4.1.3 | D184: Dispone de una Política de Sustentabilidad formalizada y comunicada. | E184: - | F184: SUST | G184: Fomentar y Comunicar Politica de Sustentabilidad
A185: 4.1 | B185: Gobernanza (Ética y Cultura) | C185: 4.1.4 | D185: Cuenta con un Código de Ética y Conducta formalizado y comunicado al personal de todos los niveles de la empresa. El mismo se encuentra alineado con la ultima versión del Código de Ética y Conducta del Grupo Arcor. | E185: - | F185: SUST | G185: Fomentar y Comunicar el Código de Ética y Conducta
A186: 4.2 | B186: Organigramas y Perfiles | C186: 4.2.1 | D186: Los organigrama y la estructura del distribuidor se encuentran comunicados | E186: - | F186: - | G186: Existe un Organigrama que establece funciones y jerarquías en la distribuidora, incluyendo los perfiles de puestos principales. Formato digital
A187: 4.2 | B187: Organigramas y Perfiles | C187: 4.2.2 | D187: Se encuentra definido y documentado el perfil del puesto de MML logística | E187: - | F187: - | G187: Documento que cuente con la definicion del Perfil de Puestos, competencias necesarias, objetivos e indicadores del puesto.
A188: 4.2 | B188: Organigramas y Perfiles | C188: 4.2.3 | D188: Se encuentran definidos los perfiles de puestos principales (comercial y administrativo) | E188: - | F188: - | G188: Documento que cuente con la definicion del Perfil de Puestos, competencias necesarias, objetivos e indicadores del puesto.
A189: 4.2 | B189: Organigramas y Perfiles | C189: 4.2.4 | D189: El organigrama se encuentra definido y documentado por la distribuidora | E189: - | F189: - | G189: Existe un Organigrama que establece funciones y jerarquías en la distribuidora, incluyendo los perfiles de puestos principales. Formato digital
A190: 4.3 | B190: Cultura de Buenas prácticas de manufactura | C190: 4.3.1 | D190: Se evidencia el conocimiento y la aplicación de Buenas Prácticas de Manufactura, (ropa de trabajo en condiciones, está definida la zona donde se puede fumar o consumir alimentos y bebidas) | E190: - | F190: QA | G190: Carteleria de zona para fumar, cocina/comedor para consumir alimentos o bebidas. Estado de la ropa de los empleados, registro que se dan dos mudas por año
A191: 4.4 | B191: Selección de Personal | C191: 4.4.1 | D191: Ante la vacante de un puesto, prioriza a sus empleados en igualdad de condiciones con los postulantes externos. | E191: - | F191: SUST | G191: Evidencia de difusion de búsquedas internas a traves de correos electronicos, carteleria. Algun caso de rotación interna
A192: 4.4 | B192: Selección de Personal | C192: 4.4.2 | D192: Cuenta con políticas y prácticas alineadas a la Política de Promoción de los Derechos Humanos de Grupo Arcor. | E192: - | F192: SUST | G192: Conocimiento y comunicación de Politica de Compromiso con el respeto a los derechos humanos. Publicar politica en grupos de difusion, publicada en facebook/linkdin. Carteleria, capacitaciones, etc.
A193: 4.5 | B193: Remuneración y beneficios | C193: 4.5.1 | D193: El establecimiento cuenta con una capacitación anual de los beneficios que forman parte de la remuneración | E193: - | F193: - | G193: Registro de la capacitación, temas que se dictaron, cantidad de horas destinadas. PLAN ANUAL con minimo de 6 capacitaciones anuales
... A205: 4.9 | B205: Evaluaciones de desempeño y cumplimiento de objetivos | C205: 4.9.1 | D205: Hay evaluación formal del personal al menos anual dando feedback de oportunidades de desarrollo | E205: - | F205: - | G205: Plan de desarrollo profesional
A206: 4.9 | C206: 4.9.2 | D206: El distribuidor premia de acuerdo al cumplimiento de objetivos individuales y el empleado tiene conocimiento de este incentivo (bono de desempeño) | E206: - | F206: - | G206: Plan de medicion de objetivos
A207: 5 | B207: 5S
A208: 5.1 | B208: Método de 5"S" | C208: 5.1.1 | D208: Posee implementadas las 3 primeras "S" (CLASIFICAR - ORDENAR - LIMPIAR) | E208: - | F208: QA | G208: Visualización visual de las diferentes áreas.
A209: 5.1 | B209: Método de 5"S" | C209: 5.1.2 | D209: Se auditan con frecuencia determinada los niveles de orden y limpieza alcanzados en Depósito. Se evidencia planilla de auditoría y análisis de resultados de los últimos 3 meses | E209: - | F209: QA | G209: Registro de las auditorias realizadas.
A210: 5.1 | B210: Método de 5"S" | C210: 5.1.3 | D210: Se generan Planes de acción en base a los resultados de las Auditorías en todas las áreas. Verificar si se toman las acciones correctivas de los puntos levantados | E210: - | F210: QA | G210: Registro de los planes de acciones.
A211: 5.1 | B211: Método de 5"S" | C211: 5.1.4 | D211: Está implementada cada una de las 5Ss en todas las áreas de la Distribuidora, se mantiene en el tiempo y es base para mejoras edilicias, de procesos y de clima laboral. Se evidencia el último año de Auditorías 5S, alcance de resultados (>90%) y comunicaciones. | E211: - | F211: QA | G211: Visualización. Registro y evidencia de los ultimos 12 meses contando con plan de implementacion de 5s
A212: 5.1 | B212: Método de 5"S" | C212: 5.1.5 | D212: Se auditan con frecuencia mensual los niveles de orden y limpieza alcanzados en Sector POP (orden + identificación + inventario y colocación de mobiliario en PDV) | E212: - | F212: - | G212: Registro de las auditorias realizadas en Sector POP.
A213: 6 | B213: PROCESOS LOGISTICOS
A214: 6.1 | B214: Planificación de Compras | C214: 6.1.1 | D214: Se informa/comunica las compras (de volumen mayor a los normal o excepcionales) a Logística para que pueda planificar la operación de descarga y espacio necesario (Registro, email, etc.) | E214: - | F214: - | G214: No aplica este año
A215: 6.1 | B215: Planificación de Compras | C215: 6.1.2 | D215: Realizan compras proporcionales y distribuidas dentro del mes | E215: - | F215: - | G215: No aplica este año
A216: 6.2 | B216: Activación del Abastecimiento | C216: 6.2.1 | D216: Logística recibe el IAD (Informe Avanzado de Despacho) | E216: - | F216: - | G216: Revisar correos recibidos por el logístico y cualquier contacto proactivo con Arcor desde el Informe Avanzado de Despacho (IAD), con el transporte para prever horarios de arribo, administrar demoras o adelantos, incluyendo la logística de última milla
A217: 6.3 | B217: Recepción | C217: 6.3.1 | D217: Las novedades se transmiten a CRM Logístico de ARCOR por correo, teniendo en cuenta el instructivo establecido para el envío de la documentación de respaldo | E217: - | F217: - | G217: Revisar documentacion de algun arribo y contactos con CRM.
A218: 6.4 | B218: Organización del Layout | C218: 6.4.1 | D218: Frecuencia definida documentada de revisión y/o modificación del lay-out (mínimo cada 3 meses, máximo cada 6 meses) | E218: - | F218: - | G218: planilla de calculo por medio de la cual analiza el ordenamiento del lay-out. Consultar con la gente cada cuanto revisan el ordenamiento del Layout
A219: 6.4 | B219: Organización del Layout | C219: 6.4.2 | D219: Pasillos organizados por algún criterio lógico (Negocio, ABC, familia, etc.) | E219: - | F219: - | G219: planilla de calculo por medio de la cual analiza el ordenamiento del lay-out. Inspeccion visual
A220: 6.5 | B220: Identificación | C220: 6.5.1 | D220: Cada área del lay out se encuentra demarcada (Zonas pintadas en el piso) | E220: - | F220: - | G220: Revisión del lay out si las zonas estan delimitadas y demarcadas. Evidencia visual
A221: 6.5 | B221: Identificación | C221: 6.5.2 | D221: Áreas principales identificadas (Recepción-Despacho-Devoluciones-Mercadería no comercializable-picking/almacenamiento) | E221: - | F221: - | G221: Revisión del lay out si las areas principales estan identificadas. Evidencia visual
A222: 6.5 | B222: Identificación | C222: 6.5.3 | D222: No hay superposición entre áreas críticas (Despacho y Recepción por ej.) | E222: - | F222: - | G222: Revisión del lay out si no hay superposicion entre areas criticas. Evidencia visual
A223: 6.5 | B223: Identificación | C223: 6.5.4 | D223: El lugar se encuentra identificado con cartelería | E223: - | F223: - | G223: Revisión visual del layout y recorrida periférica.
A224: 6.6 | B224: Rotación | C224: 6.6.1 | D224: Control de rotación y vencimientos junto al inventario rotativo y/o auditorias de 5S | E224: - | F224: - | G224: Revisar que utilicen un correcto control de Stock. Verificar que las unidades en Picking son las proximas a vencer
A225: 6.6 | B225: Rotación | C225: 6.6.2 | D225: Se lleva registro de las unidades vencidas | E225: - | F225: - | G225: Evidenciar el registro (escrito o digital) con las unidades vencidas. Detallar cantidad y productos
... A239: 6.13 | B239: Rechazos / Devoluciones | C239: 6.13.1 | D239: Registro de motivos para posterior análisis y mejora del proceso de rechazos | E239: - | F239: - | G239: El punto se valida contando con una planilla para registrar los productos rechazados
A240: 7 | B240: ESTANDARIZACION
A241: 7.1 | B241: Politica de Manejo de Vidrio | C241: 7.1.1 | D241: Cuenta con la Política de manejo de vidrio | E241: - | F241: - | G241: Revisar la documentacion "Planilla modelo control para politica de manejo de vidrio"
A242: 7.2 | B242: Coordinación del Abastecimiento | C242: 7.2.1 | D242: Previsión de espacio para el guardado/almacenamiento y/o reordenamiento de la mercadería | E242: CRITICO.6 | F242: - | G242: Revisar sectores de descarga, su ubicación y tamaño. Hablar con la gente para ver si se planifica.
A243: 7.2 | B243: Coordinación del Abastecimiento | C243: 7.2.2 | D243: Previsión de personas y equipo (Apilador/Autoelevador) necesarias para la descarga | E243: CRITICO.6 | F243: - | G243: Hablar con la gente para ver si se planifica. Quienes estan a cargo de la descarga, cuantas personas son. En caso de equipos alquilados para descarga, consultar sobre como aseguran la disponibilidad del mismo
A244: 7.2 | B244: Coordinación del Abastecimiento | C244: 7.2.3 | D244: Cuenta con una ventana horaria de 8hs para recepción de mercadería | E244: CRITICO.6 | F244: - | G244: Se consulta al distribuidor cual es la ventana horaria para la recepcion
A245: 7.2 | B245: Coordinación del Abastecimiento | C245: 7.2.4 | D245: El distribuidor tiene zonas definidas para la descarga | E245: CRITICO.6 | F245: - | G245: Revisar sectores de descarga, su ubicación y tamaño. La zona debe estar bien identificada
A246: 7.3 | B246: Despacho | C246: 7.3.1 | D246: Cuenta con una check-list para controlar las adecuadas condiciones de higiene, limpieza y acondicionamiento de la unidad contenedora del vehículo | E246: - | F246: - | G246: Revisión visual de los productos en despacho. Completar con la planilla modelo subida a la plataforma. Verificar su uso y frecuencia
A247: 7.3 | B247: Despacho | C247: 7.3.2 | D247: Cuenta con una estrategia de ruteo por sistema que minimiza los km recorridos y con ello el uso de combustible para la entrega de producto. | E247: - | F247: SUST | G247: Registro donde se pueda ver la comparativa de distintas rutas. Revisar si cuenta con una herramienta que determine automaticamente el ruteo mas corto
